Workbook

Sheet Lisez-moi
A1: COTE — base de suivi des cotes
A3: Généré le | B3: 46310
A4: Dernier relevé | B4: 46310
A5: Dashboard | B5: https://mattchampavier-ui.github.io/cote-auto/
A7: Fonctionnement | B7: Ce fichier est régénéré automatiquement à chaque relevé (chaque lundi et le 1er du mois) à partir de tout l'historique.
B8: Il est aussi joint au récap mensuel par mail. Toute modification faite à la main ici sera écrasée : enregistre une copie pour annoter.
A10: Onglets
A11: Analyse du mois | B11: Situation actuelle de chaque véhicule : score, signal, prix, tendances, offre, ventes. Indicateurs clés en haut.
A12: Historique mensuel | B12: Une ligne par véhicule et par mois (dernier relevé du mois). Variations vs mois précédent calculées par formule.
A13: Médianes par mois | B13: Tableau croisé véhicule × mois des prix médians (formules sur l'onglet Historique mensuel).
A14: Indice base 100 | B14: Évolution de la médiane depuis le premier mois suivi (100 = premier mois), avec graphique.
A15: Relevés | B15: Tous les relevés bruts, y compris l'amorce manuelle de septembre 2026.
A16: Annonces | B16: Chaque annonce avec tout ce que fournit LeBonCoin : version et finition exactes, prix, ancien prix, estimation de prix LeBonCoin (min/max, positionnement), km, année, mise en circulation, carburant, boîte, puissance, couleur, entretien, historique, vendeur pro/particulier, localisation, photos, description ; durée en ligne et baisses de prix.
A17: Historique des prix | B17: Chaque prix relevé pour chaque annonce, avec l'évolution d'un relevé à l'autre.
A18: Par année-modèle | B18: Prix moyen, plus bas, plus haut et km moyen par véhicule et par année-modèle (annonces en vente).
A19: Par kilométrage | B19: Mêmes indicateurs par tranche de kilométrage : mesure la décote liée au km.
A20: Bonnes affaires | B20: Annonces du dernier relevé au moins 15 % sous la cote attendue pour leur kilométrage.
A21: Véhicules | B21: Liste des véhicules suivis ou retirés et leurs critères de recherche.
A23: Définitions
A24: Médiane | B24: Prix médian des annonces retenues (après filtres : pièces, épaves, autres versions, doublons, prix aberrants).
A25: Cote à km réf. | B25: Prix attendu à un kilométrage de référence fixe (régression prix/km) : compare les mois sans biais de kilométrage.
A26: Position fourchette | B26: 0 % = au plancher, 100 % = au plafond de prix observé (ou saisi pendant les 3 premiers mois).
A27: Score | B27: Sur 100 : rareté 20 %, désirabilité 20 %, « dernier de » 10 %, proximité du plancher 20 %, momentum 15 %, marché 15 %.
A28: Ventes | B28: Annonces disparues entre deux relevés. Une annonce peut aussi être retirée sans vente : c'est une estimation.
A29: Avertissement | B29: Outil de suivi de marché, pas un conseil d'achat.

Sheet Analyse du mois
A1: Analyse au 15/10/2026
A3: Véhicules suivis | C3: Score moyen | E3: Annonces actives
A4: =COUNTA(A9:A24) | C4: =IFERROR(AVERAGEIF(N9:N24,">0",C9:C24),0) | E4: =SUM(N9:N24)
A5: Ventes sur 30 jours | C5: Signaux d'achat | E5: Bonnes affaires
A6: =SUM(O9:O24) | C6: =COUNTIF(D9:D24,"Signal d'achat") | E6: =SUM(Q9:Q24)
A8: Véhicule | B8: Catégorie | C8: Score /100 | D8: Signal | E8: Médiane | F8: Plancher | G8: Plafond | H8: Position fourchette | I8: Tendance 1 mois | J8: Tendance 3 mois | K8: Tendance 12 mois | L8: Cote à km réf. | M8: Km réf. | N8: Annonces | O8: Vendues (30 j) | P8: Délai de vente | Q8: Bonnes affaires | R8: Rareté | S8: Désirabilité | T8: Dernier de | U8: Proximité plancher | V8: Momentum | W8: Marché | X8: Dernier relevé | Y8: LeBonCoin | Z8: Part de pros (en vente) | AA8: Part avec carnet d'entretien | AB8: Écart moyen vs estimation LBC | AC8: Jours en ligne moyens
A9: Peugeot 208 GTi 30th | B9: Hot-hatch récente à tirage limité | C9: 70.2 | D9: Signal d'achat | E9: 15900 | F9: 12000 | G9: 24000 | H9: =IF(AND(ISNUMBER(E9),ISNUMBER(F9),ISNUMBER(G9),G9>F9),(E9-F9)/(G9-F9),"") | L9: 15360 | M9: 100000 | N9: 11 | O9: 2 | P9: 61 | Q9: 2 | R9: 85 | S9: 80 | T9: 65 | U9: 68 | V9: 50 | W9: 65 | X9: 46310 | Y9: Voir | Z9: =IFERROR(COUNTIFS(Annonces!$A$2:$A$701,$A9,Annonces!$E$2:$E$701,"En vente",Annonces!$AF$2:$AF$701,"Pro")/COUNTIFS(Annonces!$A$2:$A$701,$A9,Annonces!$E$2:$E$701,"En vente",Annonces!$AF$2:$AF$701,"<>"),"") | AA9: =IFERROR(COUNTIFS(Annonces!$A$2:$A$701,$A9,Annonces!$E$2:$E$701,"En vente",Annonces!$AD$2:$AD$701,"*arnet*")/COUNTIFS(Annonces!$A$2:$A$701,$A9,Annonces!$E$2:$E$701,"En vente",Annonces!$AD$2:$AD$701,"<>"),"") | AB9: =IFERROR(AVERAGEIFS(Annonces!$R$2:$R$701,Annonces!$A$2:$A$701,$A9,Annonces!$E$2:$E$701,"En vente"),"") | AC9: =IFERROR(AVERAGEIFS(Annonces!$J$2:$J$701,Annonces!$A$2:$A$701,$A9,Annonces!$E$2:$E$701,"En vente"),"")
A10: Porsche 911 997 Carrera S | B10: Sportive iconique | C10: 68.9 | D10: Signal d'achat | E10: 54990 | F10: 40000 | G10: 75000 | H10: =IF(AND(ISNUMBER(E10),ISNUMBER(F10),ISNUMBER(G10),G10>F10),(E10-F10)/(G10-F10),"") | L10: 55870 | M10: 100000 | N10: 39 | O10: 0 | Q10: 3 | R10: 40 | S10: 90 | T10: 90 | U10: 57 | V10: 50 | W10: 100 | X10: 46310 | Y10: Voir | Z10: =IFERROR(COUNTIFS(Annonces!$A$2:$A$701,$A10,Annonces!$E$2:$E$701,"En vente",Annonces!$AF$2:$AF$701,"Pro")/COUNTIFS(Annonces!$A$2:$A$701,$A10,Annonces!$E$2:$E$701,"En vente",Annonces!$AF$2:$AF$701,"<>"),"") | AA10: =IFERROR(COUNTIFS(Annonces!$A$2:$A$701,$A10,Annonces!$E$2:$E$701,"En vente",Annonces!$AD$2:$AD$701,"*arnet*")/COUNTIFS(Annonces!$A$2:$A$701,$A10,Annonces!$E$2:$E$701,"En vente",Annonces!$AD$2:$AD$701,"<>"),"") | AB10: =IFERROR(AVERAGEIFS(Annonces!$R$2:$R$701,Annonces!$A$2:$A$701,$A10,Annonces!$E$2:$E$701,"En vente"),"") | AC10: =IFERROR(AVERAGEIFS(Annonces!$J$2:$J$701,Annonces!$A$2:$A$701,$A10,Annonces!$E$2:$E$701,"En vente"),"")
A11: Peugeot 205 GTI | B11: Hot-hatch icône des années 80 | C11: 67.3 | D11: À surveiller | E11: 15450 | F11: 13125 | G11: 20675 | H11: =IF(AND(ISNUMBER(E11),ISNUMBER(F11),ISNUMBER(G11),G11>F11),(E11-F11)/(G11-F11),"") | L11: 16890 | M11: 190000 | N11: 40 | O11: 0 | Q11: 5 | R11: 45 | S11: 85 | T11: 50 | U11: 69 | V11: 50 | W11: 100 | X11: 46310 | Y11: Voir | Z11: =IFERROR(COUNTIFS(Annonces!$A$2:$A$701,$A11,Annonces!$E$2:$E$701,"En vente",Annonces!$AF$2:$AF$701,"Pro")/COUNTIFS(Annonces!$A$2:$A$701,$A11,Annonces!$E$2:$E$701,"En vente",Annonces!$AF$2:$AF$701,"<>"),"") | AA11: =IFERROR(COUNTIFS(Annonces!$A$2:$A$701,$A11,Annonces!$E$2:$E$701,"En vente",Annonces!$AD$2:$AD$701,"*arnet*")/COUNTIFS(Annonces!$A$2:$A$701,$A11,Annonces!$E$2:$E$701,"En vente",Annonces!$AD$2:$AD$701,"<>"),"") | AB11: =IFERROR(AVERAGEIFS(Annonces!$R$2:$R$701,Annonces!$A$2:$A$701,$A11,Annonces!$E$2:$E$701,"En vente"),"") | AC11: =IFERROR(AVERAGEIFS(Annonces!$J$2:$J$701,Annonces!$A$2:$A$701,$A11,Annonces!$E$2:$E$701,"En vente"),"")
A12: Peugeot 206 RC | B12: Hot-hatch youngtimer 2000-2005 | C12: 65.9 | D12: À surveiller | E12: 9000 | F12: 6500 | G12: 13500 | H12: =IF(AND(ISNUMBER(E12),ISNUMBER(F12),ISNUMBER(G12),G12>F12),(E12-F12)/(G12-F12),"") | L12: 11050 | M12: 150000 | N12: 40 | O12: 0 | Q12: 5 | R12: 45 | S12: 70 | T12: 75 | U12: 64 | V12: 50 | W12: 100 | X12: 46310 | Y12: Voir | Z12: =IFERROR(COUNTIFS(Annonces!$A$2:$A$701,$A12,Annonces!$E$2:$E$701,"En vente",Annonces!$AF$2:$AF$701,"Pro")/COUNTIFS(Annonces!$A$2:$A$701,$A12,Annonces!$E$2:$E$701,"En vente",Annonces!$AF$2:$AF$701,"<>"),"") | AA12: =IFERROR(COUNTIFS(Annonces!$A$2:$A$701,$A12,Annonces!$E$2:$E$701,"En vente",Annonces!$AD$2:$AD$701,"*arnet*")/COUNTIFS(Annonces!$A$2:$A$701,$A12,Annonces!$E$2:$E$701,"En vente",Annonces!$AD$2:$AD$701,"<>"),"") | AB12: =IFERROR(AVERAGEIFS(Annonces!$R$2:$R$701,Annonces!$A$2:$A$701,$A12,Annonces!$E$2:$E$701,"En vente"),"") | AC12: =IFERROR(AVERAGEIFS(Annonces!$J$2:$J$701,Annonces!$A$2:$A$701,$A12,Annonces!$E$2:$E$701,"En vente"),"")
A13: Renault Twingo 1 découvrable | B13: Citadine iconique, variante toit ouvrant | C13: 65.5 | D13: À surveiller | E13: 3000 | F13: 1500 | G13: 6500 | H13: =IF(AND(ISNUMBER(E13),ISNUMBER(F13),ISNUMBER(G13),G13>F13),(E13-F13)/(G13-F13),"") | L13: 3530 | M13: 150000 | N13: 37 | O13: 0 | Q13: 5 | R13: 55 | S13: 65 | T13: 50 | U13: 70 | V13: 50 | W13: 100 | X13: 46310 | Y13: Voir | Z13: =IFERROR(COUNTIFS(Annonces!$A$2:$A$701,$A13,Annonces!$E$2:$E$701,"En vente",Annonces!$AF$2:$AF$701,"Pro")/COUNTIFS(Annonces!$A$2:$A$701,$A13,Annonces!$E$2:$E$701,"En vente",Annonces!$AF$2:$AF$701,"<>"),"") | AA13: =IFERROR(COUNTIFS(Annonces!$A$2:$A$701,$A13,Annonces!$E$2:$E$701,"En vente",Annonces!$AD$2:$AD$701,"*arnet*")/COUNTIFS(Annonces!$A$2:$A$701,$A13,Annonces!$E$2:$E$701,"En vente",Annonces!$AD$2:$AD$701,"<>"),"") | AB13: =IFERROR(AVERAGEIFS(Annonces!$R$2:$R$701,Annonces!$A$2:$A$701,$A13,Annonces!$E$2:$E$701,"En vente"),"") | AC13: =IFERROR(AVERAGEIFS(Annonces!$J$2:$J$701,Annonces!$A$2:$A$701,$A13,Annonces!$E$2:$E$701,"En vente"),"")
A14: Honda S2000 | B14: Roadster japonais culte | C14: 65.2 | D14: À surveiller | E14: 23900 | F14: 14900 | G14: 28950 | H14: =IF(AND(ISNUMBER(E14),ISNUMBER(F14),ISNUMBER(G14),G14>F14),(E14-F14)/(G14-F14),"") | L14: 22870 | M14: 140000 | N14: 39 | O14: 0 | Q14: 5 | R14: 50 | S14: 85 | T14: 85 | U14: 36 | V14: 50 | W14: 100 | X14: 46310 | Y14: Voir | Z14: =IFERROR(COUNTIFS(Annonces!$A$2:$A$701,$A14,Annonces!$E$2:$E$701,"En vente",Annonces!$AF$2:$AF$701,"Pro")/COUNTIFS(Annonces!$A$2:$A$701,$A14,Annonces!$E$2:$E$701,"En vente",Annonces!$AF$2:$AF$701,"<>"),"") | AA14: =IFERROR(COUNTIFS(Annonces!$A$2:$A$701,$A14,Annonces!$E$2:$E$701,"En vente",Annonces!$AD$2:$AD$701,"*arnet*")/COUNTIFS(Annonces!$A$2:$A$701,$A14,Annonces!$E$2:$E$701,"En vente",Annonces!$AD$2:$AD$701,"<>"),"") | AB14: =IFERROR(AVERAGEIFS(Annonces!$R$2:$R$701,Annonces!$A$2:$A$701,$A14,Annonces!$E$2:$E$701,"En vente"),"") | AC14: =IFERROR(AVERAGEIFS(Annonces!$J$2:$J$701,Annonces!$A$2:$A$701,$A14,Annonces!$E$2:$E$701,"En vente"),"")
A15: Renault Clio II RS (172/182 ch) | B15: Hot-hatch youngtimer 2000-2005 | C15: 62.8 | D15: À surveiller | E15: 10195 | F15: 5000 | G15: 17000 | H15: =IF(AND(ISNUMBER(E15),ISNUMBER(F15),ISNUMBER(G15),G15>F15),(E15-F15)/(G15-F15),"") | L15: 10520 | M15: 160000 | N15: 36 | O15: 0 | Q15: 5 | R15: 40 | S15: 75 | T15: 60 | U15: 57 | V15: 50 | W15: 100 | X15: 46310 | Y15: Voir | Z15: =IFERROR(COUNTIFS(Annonces!$A$2:$A$701,$A15,Annonces!$E$2:$E$701,"En vente",Annonces!$AF$2:$AF$701,"Pro")/COUNTIFS(Annonces!$A$2:$A$701,$A15,Annonces!$E$2:$E$701,"En vente",Annonces!$AF$2:$AF$701,"<>"),"") | AA15: =IFERROR(COUNTIFS(Annonces!$A$2:$A$701,$A15,Annonces!$E$2:$E$701,"En vente",Annonces!$AD$2:$AD$701,"*arnet*")/COUNTIFS(Annonces!$A$2:$A$701,$A15,Annonces!$E$2:$E$701,"En vente",Annonces!$AD$2:$AD$701,"<>"),"") | AB15: =IFERROR(AVERAGEIFS(Annonces!$R$2:$R$701,Annonces!$A$2:$A$701,$A15,Annonces!$E$2:$E$701,"En vente"),"") | AC15: =IFERROR(AVERAGEIFS(Annonces!$J$2:$J$701,Annonces!$A$2:$A$701,$A15,Annonces!$E$2:$E$701,"En vente"),"")
A16: Peugeot 306 S16 | B16: Hot-hatch youngtimer 1990-2000 | C16: 61.9 | D16: À surveiller | E16: 9500 | F16: 6800 | G16: 15000 | H16: =IF(AND(ISNUMBER(E16),ISNUMBER(F16),ISNUMBER(G16),G16>F16),(E16-F16)/(G16-F16),"") | L16: 11490 | M16: 180000 | N16: 33 | O16: 0 | Q16: 5 | R16: 40 | S16: 65 | T16: 50 | U16: 67 | V16: 50 | W16: 100 | X16: 46310 | Y16: Voir | Z16: =IFERROR(COUNTIFS(Annonces!$A$2:$A$701,$A16,Annonces!$E$2:$E$701,"En vente",Annonces!$AF$2:$AF$701,"Pro")/COUNTIFS(Annonces!$A$2:$A$701,$A16,Annonces!$E$2:$E$701,"En vente",Annonces!$AF$2:$AF$701,"<>"),"") | AA16: =IFERROR(COUNTIFS(Annonces!$A$2:$A$701,$A16,Annonces!$E$2:$E$701,"En vente",Annonces!$AD$2:$AD$701,"*arnet*")/COUNTIFS(Annonces!$A$2:$A$701,$A16,Annonces!$E$2:$E$701,"En vente",Annonces!$AD$2:$AD$701,"<>"),"") | AB16: =IFERROR(AVERAGEIFS(Annonces!$R$2:$R$701,Annonces!$A$2:$A$701,$A16,Annonces!$E$2:$E$701,"En vente"),"") | AC16: =IFERROR(AVERAGEIFS(Annonces!$J$2:$J$701,Annonces!$A$2:$A$701,$A16,Annonces!$E$2:$E$701,"En vente"),"")
A17: BMW Z3 1.9i / 2.0i | B17: Roadster youngtimer | C17: 61.9 | D17: À surveiller | E17: 10245 | F17: 9498 | G17: 12740 | H17: =IF(AND(ISNUMBER(E17),ISNUMBER(F17),ISNUMBER(G17),G17>F17),(E17-F17)/(G17-F17),"") | L17: 10900 | M17: 130000 | N17: 24 | O17: 0 | Q17: 3 | R17: 35 | S17: 65 | T17: 40 | U17: 77 | V17: 50 | W17: 100 | X17: 46310 | Y17: Voir | Z17: =IFERROR(COUNTIFS(Annonces!$A$2:$A$701,$A17,Annonces!$E$2:$E$701,"En vente",Annonces!$AF$2:$AF$701,"Pro")/COUNTIFS(Annonces!$A$2:$A$701,$A17,Annonces!$E$2:$E$701,"En vente",Annonces!$AF$2:$AF$701,"<>"),"") | AA17: =IFERROR(COUNTIFS(Annonces!$A$2:$A$701,$A17,Annonces!$E$2:$E$701,"En vente",Annonces!$AD$2:$AD$701,"*arnet*")/COUNTIFS(Annonces!$A$2:$A$701,$A17,Annonces!$E$2:$E$701,"En vente",Annonces!$AD$2:$AD$701,"<>"),"") | AB17: =IFERROR(AVERAGEIFS(Annonces!$R$2:$R$701,Annonces!$A$2:$A$701,$A17,Annonces!$E$2:$E$701,"En vente"),"") | AC17: =IFERROR(AVERAGEIFS(Annonces!$J$2:$J$701,Annonces!$A$2:$A$701,$A17,Annonces!$E$2:$E$701,"En vente"),"")
A18: Volkswagen Golf IV GTI 25th Anniversary | B18: Hot-hatch à série limitée | C18: 61 | D18: À surveiller | E18: 11000 | F18: 11000 | G18: 11000 | H18: =IF(AND(ISNUMBER(E18),ISNUMBER(F18),ISNUMBER(G18),G18>F18),(E18-F18)/(G18-F18),"") | L18: 11000 | M18: 200000 | N18: 1 | O18: 0 | Q18: 0 | R18: 70 | S18: 65 | T18: 55 | U18: 100 | V18: 50 | W18: 7 | X18: 46310 | Y18: Voir | Z18: =IFERROR(COUNTIFS(Annonces!$A$2:$A$701,$A18,Annonces!$E$2:$E$701,"En vente",Annonces!$AF$2:$AF$701,"Pro")/COUNTIFS(Annonces!$A$2:$A$701,$A18,Annonces!$E$2:$E$701,"En vente",Annonces!$AF$2:$AF$701,"<>"),"") | AA18: =IFERROR(COUNTIFS(Annonces!$A$2:$A$701,$A18,Annonces!$E$2:$E$701,"En vente",Annonces!$AD$2:$AD$701,"*arnet*")/COUNTIFS(Annonces!$A$2:$A$701,$A18,Annonces!$E$2:$E$701,"En vente",Annonces!$AD$2:$AD$701,"<>"),"") | AB18: =IFERROR(AVERAGEIFS(Annonces!$R$2:$R$701,Annonces!$A$2:$A$701,$A18,Annonces!$E$2:$E$701,"En vente"),"") | AC18: =IFERROR(AVERAGEIFS(Annonces!$J$2:$J$701,Annonces!$A$2:$A$701,$A18,Annonces!$E$2:$E$701,"En vente"),"")
A19: Porsche Boxster 987 | B19: Roadster Porsche | C19: 60.1 | D19: À surveiller | E19: 29250 | F19: 20000 | G19: 45000 | H19: =IF(AND(ISNUMBER(E19),ISNUMBER(F19),ISNUMBER(G19),G19>F19),(E19-F19)/(G19-F19),"") | L19: 32020 | M19: 80000 | N19: 40 | O19: 0 | Q19: 5 | R19: 30 | S19: 75 | T19: 40 | U19: 63 | V19: 50 | W19: 100 | X19: 46310 | Y19: Voir | Z19: =IFERROR(COUNTIFS(Annonces!$A$2:$A$701,$A19,Annonces!$E$2:$E$701,"En vente",Annonces!$AF$2:$AF$701,"Pro")/COUNTIFS(Annonces!$A$2:$A$701,$A19,Annonces!$E$2:$E$701,"En vente",Annonces!$AF$2:$AF$701,"<>"),"") | AA19: =IFERROR(COUNTIFS(Annonces!$A$2:$A$701,$A19,Annonces!$E$2:$E$701,"En vente",Annonces!$AD$2:$AD$701,"*arnet*")/COUNTIFS(Annonces!$A$2:$A$701,$A19,Annonces!$E$2:$E$701,"En vente",Annonces!$AD$2:$AD$701,"<>"),"") | AB19: =IFERROR(AVERAGEIFS(Annonces!$R$2:$R$701,Annonces!$A$2:$A$701,$A19,Annonces!$E$2:$E$701,"En vente"),"") | AC19: =IFERROR(AVERAGEIFS(Annonces!$J$2:$J$701,Annonces!$A$2:$A$701,$A19,Annonces!$E$2:$E$701,"En vente"),"")
A20: Porsche Boxster 986 | B20: Roadster d'entrée de gamme Porsche | C20: 58.4 | D20: À surveiller | E20: 19890 | F20: 15000 | G20: 27000 | H20: =IF(AND(ISNUMBER(E20),ISNUMBER(F20),ISNUMBER(G20),G20>F20),(E20-F20)/(G20-F20),"") | L20: 20520 | M20: 110000 | N20: 40 | O20: 0 | Q20: 5 | R20: 35 | S20: 70 | T20: 30 | U20: 59 | V20: 50 | W20: 100 | X20: 46310 | Y20: Voir | Z20: =IFERROR(COUNTIFS(Annonces!$A$2:$A$701,$A20,Annonces!$E$2:$E$701,"En vente",Annonces!$AF$2:$AF$701,"Pro")/COUNTIFS(Annonces!$A$2:$A$701,$A20,Annonces!$E$2:$E$701,"En vente",Annonces!$AF$2:$AF$701,"<>"),"") | AA20: =IFERROR(COUNTIFS(Annonces!$A$2:$A$701,$A20,Annonces!$E$2:$E$701,"En vente",Annonces!$AD$2:$AD$701,"*arnet*")/COUNTIFS(Annonces!$A$2:$A$701,$A20,Annonces!$E$2:$E$701,"En vente",Annonces!$AD$2:$AD$701,"<>"),"") | AB20: =IFERROR(AVERAGEIFS(Annonces!$R$2:$R$701,Annonces!$A$2:$A$701,$A20,Annonces!$E$2:$E$701,"En vente"),"") | AC20: =IFERROR(AVERAGEIFS(Annonces!$J$2:$J$701,Annonces!$A$2:$A$701,$A20,Annonces!$E$2:$E$701,"En vente"),"")
A21: Renault Mégane II RS R26 | B21: Hot-hatch à série limitée | C21: 58 | D21: À surveiller | E21: 22990 | F21: 19900 | G21: 24990 | H21: =IF(AND(ISNUMBER(E21),ISNUMBER(F21),ISNUMBER(G21),G21>F21),(E21-F21)/(G21-F21),"") | L21: 23170 | M21: 100000 | N21: 15 | O21: 5 | P21: 62 | Q21: 2 | R21: 55 | S21: 75 | T21: 50 | U21: 39 | V21: 50 | W21: 78 | X21: 46310 | Y21: Voir | Z21: =IFERROR(COUNTIFS(Annonces!$A$2:$A$701,$A21,Annonces!$E$2:$E$701,"En vente",Annonces!$AF$2:$AF$701,"Pro")/COUNTIFS(Annonces!$A$2:$A$701,$A21,Annonces!$E$2:$E$701,"En vente",Annonces!$AF$2:$AF$701,"<>"),"") | AA21: =IFERROR(COUNTIFS(Annonces!$A$2:$A$701,$A21,Annonces!$E$2:$E$701,"En vente",Annonces!$AD$2:$AD$701,"*arnet*")/COUNTIFS(Annonces!$A$2:$A$701,$A21,Annonces!$E$2:$E$701,"En vente",Annonces!$AD$2:$AD$701,"<>"),"") | AB21: =IFERROR(AVERAGEIFS(Annonces!$R$2:$R$701,Annonces!$A$2:$A$701,$A21,Annonces!$E$2:$E$701,"En vente"),"") | AC21: =IFERROR(AVERAGEIFS(Annonces!$J$2:$J$701,Annonces!$A$2:$A$701,$A21,Annonces!$E$2:$E$701,"En vente"),"")
A22: Mazda MX-5 NA | B22: Roadster youngtimer | C22: 56.1 | D22: À surveiller | E22: 11990 | F22: 8938 | G22: 13875 | H22: =IF(AND(ISNUMBER(E22),ISNUMBER(F22),ISNUMBER(G22),G22>F22),(E22-F22)/(G22-F22),"") | L22: 11470 | M22: 160000 | N22: 38 | O22: 0 | Q22: 5 | R22: 25 | S22: 75 | T22: 60 | U22: 38 | V22: 50 | W22: 100 | X22: 46310 | Y22: Voir | Z22: =IFERROR(COUNTIFS(Annonces!$A$2:$A$701,$A22,Annonces!$E$2:$E$701,"En vente",Annonces!$AF$2:$AF$701,"Pro")/COUNTIFS(Annonces!$A$2:$A$701,$A22,Annonces!$E$2:$E$701,"En vente",Annonces!$AF$2:$AF$701,"<>"),"") | AA22: =IFERROR(COUNTIFS(Annonces!$A$2:$A$701,$A22,Annonces!$E$2:$E$701,"En vente",Annonces!$AD$2:$AD$701,"*arnet*")/COUNTIFS(Annonces!$A$2:$A$701,$A22,Annonces!$E$2:$E$701,"En vente",Annonces!$AD$2:$AD$701,"<>"),"") | AB22: =IFERROR(AVERAGEIFS(Annonces!$R$2:$R$701,Annonces!$A$2:$A$701,$A22,Annonces!$E$2:$E$701,"En vente"),"") | AC22: =IFERROR(AVERAGEIFS(Annonces!$J$2:$J$701,Annonces!$A$2:$A$701,$A22,Annonces!$E$2:$E$701,"En vente"),"")
A23: Citroën Saxo VTS 16V | B23: Hot-hatch youngtimer 2000-2005 | C23: 56 | D23: À surveiller | E23: 6750 | F23: 4500 | G23: 9500 | H23: =IF(AND(ISNUMBER(E23),ISNUMBER(F23),ISNUMBER(G23),G23>F23),(E23-F23)/(G23-F23),"") | L23: 7450 | M23: 150000 | N23: 40 | O23: 0 | Q23: 5 | R23: 30 | S23: 55 | T23: 55 | U23: 55 | V23: 50 | W23: 100 | X23: 46310 | Y23: Voir | Z23: =IFERROR(COUNTIFS(Annonces!$A$2:$A$701,$A23,Annonces!$E$2:$E$701,"En vente",Annonces!$AF$2:$AF$701,"Pro")/COUNTIFS(Annonces!$A$2:$A$701,$A23,Annonces!$E$2:$E$701,"En vente",Annonces!$AF$2:$AF$701,"<>"),"") | AA23: =IFERROR(COUNTIFS(Annonces!$A$2:$A$701,$A23,Annonces!$E$2:$E$701,"En vente",Annonces!$AD$2:$AD$701,"*arnet*")/COUNTIFS(Annonces!$A$2:$A$701,$A23,Annonces!$E$2:$E$701,"En vente",Annonces!$AD$2:$AD$701,"<>"),"") | AB23: =IFERROR(AVERAGEIFS(Annonces!$R$2:$R$701,Annonces!$A$2:$A$701,$A23,Annonces!$E$2:$E$701,"En vente"),"") | AC23: =IFERROR(AVERAGEIFS(Annonces!$J$2:$J$701,Annonces!$A$2:$A$701,$A23,Annonces!$E$2:$E$701,"En vente"),"")
A24: Alfa Romeo 156 2.5 V6 24V | B24: Berline sportive youngtimer | C24: 52.8 | D24: Attendre | E24: 6995 | F24: 4293 | G24: 8050 | H24: =IF(AND(ISNUMBER(E24),ISNUMBER(F24),ISNUMBER(G24),G24>F24),(E24-F24)/(G24-F24),"") | L24: 7010 | M24: 200000 | N24: 8 | O24: 2 | P24: 41 | Q24: 3 | R24: 50 | S24: 65 | T24: 70 | U24: 28 | V24: 50 | W24: 64 | X24: 46310 | Y24: Voir | Z24: =IFERROR(COUNTIFS(Annonces!$A$2:$A$701,$A24,Annonces!$E$2:$E$701,"En vente",Annonces!$AF$2:$AF$701,"Pro")/COUNTIFS(Annonces!$A$2:$A$701,$A24,Annonces!$E$2:$E$701,"En vente",Annonces!$AF$2:$AF$701,"<>"),"") | AA24: =IFERROR(COUNTIFS(Annonces!$A$2:$A$701,$A24,Annonces!$E$2:$E$701,"En vente",Annonces!$AD$2:$AD$701,"*arnet*")/COUNTIFS(Annonces!$A$2:$A$701,$A24,Annonces!$E$2:$E$701,"En vente",Annonces!$AD$2:$AD$701,"<>"),"") | AB24: =IFERROR(AVERAGEIFS(Annonces!$R$2:$R$701,Annonces!$A$2:$A$701,$A24,Annonces!$E$2:$E$701,"En vente"),"") | AC24: =IFERROR(AVERAGEIFS(Annonces!$J$2:$J$701,Annonces!$A$2:$A$701,$A24,Annonces!$E$2:$E$701,"En vente"),"")

Sheet Historique mensuel
A1: Mois | B1: Véhicule | C1: Médiane | D1: Évol. médiane vs mois préc. | E1: P25 | F1: P75 | G1: Cote à km réf. | H1: Évol. cote km réf. | I1: Annonces | J1: Nouvelles annonces | K1: Vendues | L1: Délai de vente | M1: Relevés dans le mois | N1: Score /100 | O1: Évol. score (pts) | P1: Signal
A2: 2026-10 | B2: Alfa Romeo 156 2.5 V6 24V | C2: 6995 | D2: =IF(AND($B2=$B1,ISNUMBER(C2),ISNUMBER(C1)),C2/C1-1,"") | E2: 4293 | F2: 8050 | G2: 7010 | H2: =IF(AND($B2=$B1,ISNUMBER(G2),ISNUMBER(G1)),G2/G1-1,"") | I2: 8 | J2: 10 | K2: 2 | L2: 41 | M2: 2 | N2: 52.8 | O2: =IF(AND($B2=$B1,ISNUMBER(N2),ISNUMBER(N1)),N2-N1,"") | P2: Attendre
A3: 2026-10 | B3: BMW Z3 1.9i / 2.0i | C3: 10245 | D3: =IF(AND($B3=$B2,ISNUMBER(C3),ISNUMBER(C2)),C3/C2-1,"") | E3: 9498 | F3: 11993 | G3: 10900 | H3: =IF(AND($B3=$B2,ISNUMBER(G3),ISNUMBER(G2)),G3/G2-1,"") | I3: 24 | J3: 38 | K3: 0 | M3: 2 | N3: 61.9 | O3: =IF(AND($B3=$B2,ISNUMBER(N3),ISNUMBER(N2)),N3-N2,"") | P3: À surveiller
A4: 2026-09 | B4: Citroën Saxo VTS 16V | C4: 6600 | D4: =IF(AND($B4=$B3,ISNUMBER(C4),ISNUMBER(C3)),C4/C3-1,"") | H4: =IF(AND($B4=$B3,ISNUMBER(G4),ISNUMBER(G3)),G4/G3-1,"") | I4: 2 | J4: 0 | M4: 1 | N4: 43.6 | O4: =IF(AND($B4=$B3,ISNUMBER(N4),ISNUMBER(N3)),N4-N3,"") | P4: Attendre
A5: 2026-10 | B5: Citroën Saxo VTS 16V | C5: 6750 | D5: =IF(AND($B5=$B4,ISNUMBER(C5),ISNUMBER(C4)),C5/C4-1,"") | E5: 5000 | F5: 8850 | G5: 7450 | H5: =IF(AND($B5=$B4,ISNUMBER(G5),ISNUMBER(G4)),G5/G4-1,"") | I5: 40 | J5: 57 | K5: 0 | M5: 2 | N5: 56 | O5: =IF(AND($B5=$B4,ISNUMBER(N5),ISNUMBER(N4)),N5-N4,"") | P5: À surveiller
A6: 2026-10 | B6: Honda S2000 | C6: 23900 | D6: =IF(AND($B6=$B5,ISNUMBER(C6),ISNUMBER(C5)),C6/C5-1,"") | E6: 17950 | F6: 28950 | G6: 22870 | H6: =IF(AND($B6=$B5,ISNUMBER(G6),ISNUMBER(G5)),G6/G5-1,"") | I6: 39 | J6: 51 | K6: 0 | M6: 2 | N6: 65.2 | O6: =IF(AND($B6=$B5,ISNUMBER(N6),ISNUMBER(N5)),N6-N5,"") | P6: À surveiller
A7: 2026-10 | B7: Mazda MX-5 NA | C7: 11990 | D7: =IF(AND($B7=$B6,ISNUMBER(C7),ISNUMBER(C6)),C7/C6-1,"") | E7: 8938 | F7: 13875 | G7: 11470 | H7: =IF(AND($B7=$B6,ISNUMBER(G7),ISNUMBER(G6)),G7/G6-1,"") | I7: 38 | J7: 45 | K7: 0 | M7: 2 | N7: 56.1 | O7: =IF(AND($B7=$B6,ISNUMBER(N7),ISNUMBER(N6)),N7-N6,"") | P7: À surveiller
A8: 2026-10 | B8: Peugeot 205 GTI | C8: 15450 | D8: =IF(AND($B8=$B7,ISNUMBER(C8),ISNUMBER(C7)),C8/C7-1,"") | E8: 13125 | F8: 20000 | G8: 16890 | H8: =IF(AND($B8=$B7,ISNUMBER(G8),ISNUMBER(G7)),G8/G7-1,"") | I8: 40 | J8: 65 | K8: 0 | M8: 2 | N8: 67.3 | O8: =IF(AND($B8=$B7,ISNUMBER(N8),ISNUMBER(N7)),N8-N7,"") | P8: À surveiller
A9: 2026-09 | B9: Peugeot 206 RC | C9: 6790 | D9: =IF(AND($B9=$B8,ISNUMBER(C9),ISNUMBER(C8)),C9/C8-1,"") | H9: =IF(AND($B9=$B8,ISNUMBER(G9),ISNUMBER(G8)),G9/G8-1,"") | I9: 1 | J9: 0 | M9: 1 | N9: 58.2 | O9: =IF(AND($B9=$B8,ISNUMBER(N9),ISNUMBER(N8)),N9-N8,"") | P9: À surveiller
A10: 2026-10 | B10: Peugeot 206 RC | C10: 9000 | D10: =IF(AND($B10=$B9,ISNUMBER(C10),ISNUMBER(C9)),C10/C9-1,"") | E10: 6975 | F10: 12100 | G10: 11050 | H10: =IF(AND($B10=$B9,ISNUMBER(G10),ISNUMBER(G9)),G10/G9-1,"") | I10: 40 | J10: 25 | K10: 0 | M10: 2 | N10: 65.9 | O10: =IF(AND($B10=$B9,ISNUMBER(N10),ISNUMBER(N9)),N10-N9,"") | P10: À surveiller
A11: 2026-09 | B11: Peugeot 208 GTi 30th | C11: 15990 | D11: =IF(AND($B11=$B10,ISNUMBER(C11),ISNUMBER(C10)),C11/C10-1,"") | H11: =IF(AND($B11=$B10,ISNUMBER(G11),ISNUMBER(G10)),G11/G10-1,"") | I11: 7 | J11: 0 | M11: 1 | N11: 67.4 | O11: =IF(AND($B11=$B10,ISNUMBER(N11),ISNUMBER(N10)),N11-N10,"") | P11: À surveiller
A12: 2026-10 | B12: Peugeot 208 GTi 30th | C12: 15900 | D12: =IF(AND($B12=$B11,ISNUMBER(C12),ISNUMBER(C11)),C12/C11-1,"") | E12: 14695 | F12: 17885 | G12: 15360 | H12: =IF(AND($B12=$B11,ISNUMBER(G12),ISNUMBER(G11)),G12/G11-1,"") | I12: 11 | J12: 13 | K12: 2 | L12: 61 | M12: 2 | N12: 70.2 | O12: =IF(AND($B12=$B11,ISNUMBER(N12),ISNUMBER(N11)),N12-N11,"") | P12: Signal d'achat
A13: 2026-10 | B13: Peugeot 306 S16 | C13: 9500 | D13: =IF(AND($B13=$B12,ISNUMBER(C13),ISNUMBER(C12)),C13/C12-1,"") | E13: 8000 | F13: 15000 | G13: 11490 | H13: =IF(AND($B13=$B12,ISNUMBER(G13),ISNUMBER(G12)),G13/G12-1,"") | I13: 33 | J13: 41 | K13: 0 | M13: 2 | N13: 61.9 | O13: =IF(AND($B13=$B12,ISNUMBER(N13),ISNUMBER(N12)),N13-N12,"") | P13: À surveiller
A14: 2026-09 | B14: Porsche 911 997 Carrera S | C14: 51000 | D14: =IF(AND($B14=$B13,ISNUMBER(C14),ISNUMBER(C13)),C14/C13-1,"") | H14: =IF(AND($B14=$B13,ISNUMBER(G14),ISNUMBER(G13)),G14/G13-1,"") | I14: 11 | J14: 0 | M14: 1 | N14: 67.2 | O14: =IF(AND($B14=$B13,ISNUMBER(N14),ISNUMBER(N13)),N14-N13,"") | P14: À surveiller
A15: 2026-10 | B15: Porsche 911 997 Carrera S | C15: 54990 | D15: =IF(AND($B15=$B14,ISNUMBER(C15),ISNUMBER(C14)),C15/C14-1,"") | E15: 49940 | F15: 59900 | G15: 55870 | H15: =IF(AND($B15=$B14,ISNUMBER(G15),ISNUMBER(G14)),G15/G14-1,"") | I15: 39 | J15: 66 | K15: 0 | M15: 2 | N15: 68.9 | O15: =IF(AND($B15=$B14,ISNUMBER(N15),ISNUMBER(N14)),N15-N14,"") | P15: Signal d'achat
A16: 2026-09 | B16: Porsche Boxster 986 | C16: 22425 | D16: =IF(AND($B16=$B15,ISNUMBER(C16),ISNUMBER(C15)),C16/C15-1,"") | H16: =IF(AND($B16=$B15,ISNUMBER(G16),ISNUMBER(G15)),G16/G15-1,"") | I16: 4 | J16: 0 | M16: 1 | N16: 43.1 | O16: =IF(AND($B16=$B15,ISNUMBER(N16),ISNUMBER(N15)),N16-N15,"") | P16: Attendre
A17: 2026-10 | B17: Porsche Boxster 986 | C17: 19890 | D17: =IF(AND($B17=$B16,ISNUMBER(C17),ISNUMBER(C16)),C17/C16-1,"") | E17: 17375 | F17: 21990 | G17: 20520 | H17: =IF(AND($B17=$B16,ISNUMBER(G17),ISNUMBER(G16)),G17/G16-1,"") | I17: 40 | J17: 63 | K17: 0 | M17: 2 | N17: 58.4 | O17: =IF(AND($B17=$B16,ISNUMBER(N17),ISNUMBER(N16)),N17-N16,"") | P17: À surveiller
A18: 2026-09 | B18: Porsche Boxster 987 | C18: 43990 | D18: =IF(AND($B18=$B17,ISNUMBER(C18),ISNUMBER(C17)),C18/C17-1,"") | H18: =IF(AND($B18=$B17,ISNUMBER(G18),ISNUMBER(G17)),G18/G17-1,"") | I18: 5 | J18: 0 | M18: 1 | N18: 38.3 | O18: =IF(AND($B18=$B17,ISNUMBER(N18),ISNUMBER(N17)),N18-N17,"") | P18: Attendre
A19: 2026-10 | B19: Porsche Boxster 987 | C19: 29250 | D19: =IF(AND($B19=$B18,ISNUMBER(C19),ISNUMBER(C18)),C19/C18-1,"") | E19: 26675 | F19: 34493 | G19: 32020 | H19: =IF(AND($B19=$B18,ISNUMBER(G19),ISNUMBER(G18)),G19/G18-1,"") | I19: 40 | J19: 62 | K19: 0 | M19: 2 | N19: 60.1 | O19: =IF(AND($B19=$B18,ISNUMBER(N19),ISNUMBER(N18)),N19-N18,"") | P19: À surveiller
A20: 2026-09 | B20: Renault Clio II RS (172/182 ch) | C20: 8899.5 | D20: =IF(AND($B20=$B19,ISNUMBER(C20),ISNUMBER(C19)),C20/C19-1,"") | H20: =IF(AND($B20=$B19,ISNUMBER(G20),ISNUMBER(G19)),G20/G19-1,"") | I20: 2 | J20: 0 | M20: 1 | N20: 52 | O20: =IF(AND($B20=$B19,ISNUMBER(N20),ISNUMBER(N19)),N20-N19,"") | P20: Attendre
A21: 2026-10 | B21: Renault Clio II RS (172/182 ch) | C21: 10195 | D21: =IF(AND($B21=$B20,ISNUMBER(C21),ISNUMBER(C20)),C21/C20-1,"") | E21: 7900 | F21: 12248 | G21: 10520 | H21: =IF(AND($B21=$B20,ISNUMBER(G21),ISNUMBER(G20)),G21/G20-1,"") | I21: 36 | J21: 53 | K21: 0 | M21: 2 | N21: 62.8 | O21: =IF(AND($B21=$B20,ISNUMBER(N21),ISNUMBER(N20)),N21-N20,"") | P21: À surveiller
A22: 2026-10 | B22: Renault Mégane II RS R26 | C22: 22990 | D22: =IF(AND($B22=$B21,ISNUMBER(C22),ISNUMBER(C21)),C22/C21-1,"") | E22: 19900 | F22: 24495 | G22: 23170 | H22: =IF(AND($B22=$B21,ISNUMBER(G22),ISNUMBER(G21)),G22/G21-1,"") | I22: 15 | J22: 20 | K22: 5 | L22: 62 | M22: 2 | N22: 58 | O22: =IF(AND($B22=$B21,ISNUMBER(N22),ISNUMBER(N21)),N22-N21,"") | P22: À surveiller
A23: 2026-09 | B23: Renault Twingo 1 découvrable | C23: 5490 | D23: =IF(AND($B23=$B22,ISNUMBER(C23),ISNUMBER(C22)),C23/C22-1,"") | H23: =IF(AND($B23=$B22,ISNUMBER(G23),ISNUMBER(G22)),G23/G22-1,"") | I23: 6 | J23: 0 | M23: 1 | N23: 46.5 | O23: =IF(AND($B23=$B22,ISNUMBER(N23),ISNUMBER(N22)),N23-N22,"") | P23: Attendre
A24: 2026-10 | B24: Renault Twingo 1 découvrable | C24: 3000 | D24: =IF(AND($B24=$B23,ISNUMBER(C24),ISNUMBER(C23)),C24/C23-1,"") | E24: 2400 | F24: 3650 | G24: 3530 | H24: =IF(AND($B24=$B23,ISNUMBER(G24),ISNUMBER(G23)),G24/G23-1,"") | I24: 37 | J24: 50 | K24: 0 | M24: 2 | N24: 65.5 | O24: =IF(AND($B24=$B23,ISNUMBER(N24),ISNUMBER(N23)),N24-N23,"") | P24: À surveiller
A25: 2026-10 | B25: Volkswagen Golf IV GTI 25th Anniversary | C25: 11000 | D25: =IF(AND($B25=$B24,ISNUMBER(C25),ISNUMBER(C24)),C25/C24-1,"") | E25: 11000 | F25: 11000 | G25: 11000 | H25: =IF(AND($B25=$B24,ISNUMBER(G25),ISNUMBER(G24)),G25/G24-1,"") | I25: 1 | J25: 1 | K25: 0 | M25: 1 | N25: 61 | O25: =IF(AND($B25=$B24,ISNUMBER(N25),ISNUMBER(N24)),N25-N24,"") | P25: À surveiller

Sheet Médianes par mois
A1: Véhicule | B1: 2026-09 | C1: 2026-10
A2: Alfa Romeo 156 2.5 V6 24V | B2: =IFERROR(AVERAGEIFS('Historique mensuel'!$C$2:$C$25,'Historique mensuel'!$B$2:$B$25,$A2,'Historique mensuel'!$A$2:$A$25,B$1),"") | C2: =IFERROR(AVERAGEIFS('Historique mensuel'!$C$2:$C$25,'Historique mensuel'!$B$2:$B$25,$A2,'Historique mensuel'!$A$2:$A$25,C$1),"")
A3: BMW Z3 1.9i / 2.0i | B3: =IFERROR(AVERAGEIFS('Historique mensuel'!$C$2:$C$25,'Historique mensuel'!$B$2:$B$25,$A3,'Historique mensuel'!$A$2:$A$25,B$1),"") | C3: =IFERROR(AVERAGEIFS('Historique mensuel'!$C$2:$C$25,'Historique mensuel'!$B$2:$B$25,$A3,'Historique mensuel'!$A$2:$A$25,C$1),"")
A4: Citroën Saxo VTS 16V | B4: =IFERROR(AVERAGEIFS('Historique mensuel'!$C$2:$C$25,'Historique mensuel'!$B$2:$B$25,$A4,'Historique mensuel'!$A$2:$A$25,B$1),"") | C4: =IFERROR(AVERAGEIFS('Historique mensuel'!$C$2:$C$25,'Historique mensuel'!$B$2:$B$25,$A4,'Historique mensuel'!$A$2:$A$25,C$1),"")
A5: Honda S2000 | B5: =IFERROR(AVERAGEIFS('Historique mensuel'!$C$2:$C$25,'Historique mensuel'!$B$2:$B$25,$A5,'Historique mensuel'!$A$2:$A$25,B$1),"") | C5: =IFERROR(AVERAGEIFS('Historique mensuel'!$C$2:$C$25,'Historique mensuel'!$B$2:$B$25,$A5,'Historique mensuel'!$A$2:$A$25,C$1),"")
A6: Mazda MX-5 NA | B6: =IFERROR(AVERAGEIFS('Historique mensuel'!$C$2:$C$25,'Historique mensuel'!$B$2:$B$25,$A6,'Historique mensuel'!$A$2:$A$25,B$1),"") | C6: =IFERROR(AVERAGEIFS('Historique mensuel'!$C$2:$C$25,'Historique mensuel'!$B$2:$B$25,$A6,'Historique mensuel'!$A$2:$A$25,C$1),"")
A7: Peugeot 205 GTI | B7: =IFERROR(AVERAGEIFS('Historique mensuel'!$C$2:$C$25,'Historique mensuel'!$B$2:$B$25,$A7,'Historique mensuel'!$A$2:$A$25,B$1),"") | C7: =IFERROR(AVERAGEIFS('Historique mensuel'!$C$2:$C$25,'Historique mensuel'!$B$2:$B$25,$A7,'Historique mensuel'!$A$2:$A$25,C$1),"")
A8: Peugeot 206 RC | B8: =IFERROR(AVERAGEIFS('Historique mensuel'!$C$2:$C$25,'Historique mensuel'!$B$2:$B$25,$A8,'Historique mensuel'!$A$2:$A$25,B$1),"") | C8: =IFERROR(AVERAGEIFS('Historique mensuel'!$C$2:$C$25,'Historique mensuel'!$B$2:$B$25,$A8,'Historique mensuel'!$A$2:$A$25,C$1),"")
A9: Peugeot 208 GTi 30th | B9: =IFERROR(AVERAGEIFS('Historique mensuel'!$C$2:$C$25,'Historique mensuel'!$B$2:$B$25,$A9,'Historique mensuel'!$A$2:$A$25,B$1),"") | C9: =IFERROR(AVERAGEIFS('Historique mensuel'!$C$2:$C$25,'Historique mensuel'!$B$2:$B$25,$A9,'Historique mensuel'!$A$2:$A$25,C$1),"")
A10: Peugeot 306 S16 | B10: =IFERROR(AVERAGEIFS('Historique mensuel'!$C$2:$C$25,'Historique mensuel'!$B$2:$B$25,$A10,'Historique mensuel'!$A$2:$A$25,B$1),"") | C10: =IFERROR(AVERAGEIFS('Historique mensuel'!$C$2:$C$25,'Historique mensuel'!$B$2:$B$25,$A10,'Historique mensuel'!$A$2:$A$25,C$1),"")
A11: Porsche 911 997 Carrera S | B11: =IFERROR(AVERAGEIFS('Historique mensuel'!$C$2:$C$25,'Historique mensuel'!$B$2:$B$25,$A11,'Historique mensuel'!$A$2:$A$25,B$1),"") | C11: =IFERROR(AVERAGEIFS('Historique mensuel'!$C$2:$C$25,'Historique mensuel'!$B$2:$B$25,$A11,'Historique mensuel'!$A$2:$A$25,C$1),"")
A12: Porsche Boxster 986 | B12: =IFERROR(AVERAGEIFS('Historique mensuel'!$C$2:$C$25,'Historique mensuel'!$B$2:$B$25,$A12,'Historique mensuel'!$A$2:$A$25,B$1),"") | C12: =IFERROR(AVERAGEIFS('Historique mensuel'!$C$2:$C$25,'Historique mensuel'!$B$2:$B$25,$A12,'Historique mensuel'!$A$2:$A$25,C$1),"")
A13: Porsche Boxster 987 | B13: =IFERROR(AVERAGEIFS('Historique mensuel'!$C$2:$C$25,'Historique mensuel'!$B$2:$B$25,$A13,'Historique mensuel'!$A$2:$A$25,B$1),"") | C13: =IFERROR(AVERAGEIFS('Historique mensuel'!$C$2:$C$25,'Historique mensuel'!$B$2:$B$25,$A13,'Historique mensuel'!$A$2:$A$25,C$1),"")
... A17: Volkswagen Golf IV GTI 25th Anniversary | B17: =IFERROR(AVERAGEIFS('Historique mensuel'!$C$2:$C$25,'Historique mensuel'!$B$2:$B$25,$A17,'Historique mensuel'!$A$2:$A$25,B$1),"") | C17: =IFERROR(AVERAGEIFS('Historique mensuel'!$C$2:$C$25,'Historique mensuel'!$B$2:$B$25,$A17,'Historique mensuel'!$A$2:$A$25,C$1),"")

Sheet Indice base 100
A1: Évolution de la médiane, base 100 au premier mois suivi de chaque véhicule
A2: Valeurs calculées par le robot à partir de l'onglet Historique mensuel (cases vides = pas de relevé ce mois-là, pour que le graphique ne les compte pas comme des zéros).
A4: Mois | B4: Alfa Romeo 156 2.5 V6 24V | C4: BMW Z3 1.9i / 2.0i | D4: Citroën Saxo VTS 16V | E4: Honda S2000 | F4: Mazda MX-5 NA | G4: Peugeot 205 GTI | H4: Peugeot 206 RC | I4: Peugeot 208 GTi 30th | J4: Peugeot 306 S16 | K4: Porsche 911 997 Carrera S | L4: Porsche Boxster 986 | M4: Porsche Boxster 987 | N4: Renault Clio II RS (172/182 ch) | O4: Renault Mégane II RS R26 | P4: Renault Twingo 1 découvrable | Q4: Volkswagen Golf IV GTI 25th Anniversary
A5: 2026-09 | D5: 100 | H5: 100 | I5: 100 | K5: 100 | L5: 100 | M5: 100 | N5: 100 | P5: 100
A6: 2026-10 | B6: 100 | C6: 100 | D6: 102.3 | E6: 100 | F6: 100 | G6: 100 | H6: 132.5 | I6: 99.4 | J6: 100 | K6: 107.8 | L6: 88.7 | M6: 66.5 | N6: 114.6 | O6: 100 | P6: 54.6 | Q6: 100

Sheet Relevés
A1: Date | B1: Véhicule | C1: Source | D1: Annonces | E1: Min | F1: P25 | G1: Médiane | H1: P75 | I1: Max | J1: Km médian | K1: Cote à km réf. | L1: Km réf. | M1: Nouvelles | N1: Vendues | O1: Délai de vente | P1: Part de pros | Q1: Annonces écartées
A2: 46310 | B2: Alfa Romeo 156 2.5 V6 24V | C2: apify | D2: 8 | E2: 3200 | F2: 4293 | G2: 6995 | H2: 8050 | I2: 14900 | J2: 201000 | K2: 7010 | L2: 200000 | M2: 2 | N2: 2 | O2: 41 | P2: 0.25 | Q2: 6
A3: 46310 | B3: BMW Z3 1.9i / 2.0i | C3: apify | D3: 24 | E3: 7000 | F3: 9498 | G3: 10245 | H3: 11993 | I3: 15000 | J3: 142000 | K3: 10900 | L3: 130000 | M3: 24 | N3: 0 | P3: 0.58 | Q3: 16
A4: 46310 | B4: Citroën Saxo VTS 16V | C4: apify | D4: 40 | E4: 800 | F4: 5000 | G4: 6750 | H4: 8850 | I4: 16000 | J4: 188000 | K4: 7450 | L4: 150000 | M4: 17 | N4: 0 | P4: 0.03 | Q4: 0
A5: 46310 | B5: Honda S2000 | C5: apify | D5: 39 | E5: 4599 | F5: 17950 | G5: 23900 | H5: 28950 | I5: 49990 | J5: 135000 | K5: 22870 | L5: 140000 | M5: 12 | N5: 0 | P5: 0.38 | Q5: 1
A6: 46310 | B6: Mazda MX-5 NA | C6: apify | D6: 38 | E6: 3000 | F6: 8938 | G6: 11990 | H6: 13875 | I6: 17990 | J6: 163000 | K6: 11470 | L6: 160000 | M6: 8 | N6: 0 | P6: 0.16 | Q6: 2
A7: 46310 | B7: Peugeot 205 GTI | C7: apify | D7: 40 | E7: 9800 | F7: 13125 | G7: 15450 | H7: 20000 | I7: 31000 | J7: 187000 | K7: 16890 | L7: 190000 | M7: 27 | N7: 0 | P7: 0.13 | Q7: 0
A8: 46310 | B8: Peugeot 206 RC | C8: apify | D8: 40 | E8: 5900 | F8: 6975 | G8: 9000 | H8: 12100 | I8: 17900 | J8: 170000 | K8: 11050 | L8: 150000 | M8: 23 | N8: 0 | P8: 0.08 | Q8: 0
A9: 46310 | B9: Peugeot 208 GTi 30th | C9: apify | D9: 11 | E9: 10500 | F9: 14695 | G9: 15900 | H9: 17885 | I9: 23490 | J9: 84000 | K9: 15360 | L9: 100000 | M9: 3 | N9: 2 | O9: 61 | P9: 0.45 | Q9: 1
A10: 46310 | B10: Peugeot 306 S16 | C10: apify | D10: 33 | E10: 3500 | F10: 8000 | G10: 9500 | H10: 15000 | I10: 26800 | J10: 191000 | K10: 11490 | L10: 180000 | M10: 16 | N10: 0 | P10: 0.03 | Q10: 7
A11: 46310 | B11: Porsche 911 997 Carrera S | C11: apify | D11: 39 | E11: 45990 | F11: 49940 | G11: 54990 | H11: 59900 | I11: 69990 | J11: 105000 | K11: 55870 | L11: 100000 | M11: 30 | N11: 0 | P11: 0.85 | Q11: 1
A12: 46310 | B12: Porsche Boxster 986 | C12: apify | D12: 40 | E12: 10999 | F12: 17375 | G12: 19890 | H12: 21990 | I12: 26000 | J12: 125000 | K12: 20520 | L12: 110000 | M12: 23 | N12: 0 | P12: 0.5 | Q12: 0
A13: 46310 | B13: Porsche Boxster 987 | C13: apify | D13: 40 | E13: 19900 | F13: 26675 | G13: 29250 | H13: 34493 | I13: 49900 | J13: 99000 | K13: 32020 | L13: 80000 | M13: 24 | N13: 0 | P13: 0.55 | Q13: 0
A14: 46310 | B14: Renault Clio II RS (172/182 ch) | C14: apify | D14: 36 | E14: 4000 | F14: 7900 | G14: 10195 | H14: 12248 | I14: 19500 | J14: 167000 | K14: 10520 | L14: 160000 | M14: 15 | N14: 0 | P14: 0.25 | Q14: 4
A15: 46310 | B15: Renault Mégane II RS R26 | C15: apify | D15: 15 | E15: 14900 | F15: 19900 | G15: 22990 | H15: 24495 | I15: 31490 | J15: 109000 | K15: 23170 | L15: 100000 | M15: 2 | N15: 5 | O15: 62 | P15: 0.6 | Q15: 3
A16: 46310 | B16: Renault Twingo 1 découvrable | C16: apify | D16: 37 | E16: 1690 | F16: 2400 | G16: 3000 | H16: 3650 | I16: 5990 | J16: 175000 | K16: 3530 | L16: 150000 | M16: 23 | N16: 0 | P16: 0.16 | Q16: 3
A17: 46310 | B17: Volkswagen Golf IV GTI 25th Anniversary | C17: apify | D17: 1 | E17: 11000 | F17: 11000 | G17: 11000 | H17: 11000 | I17: 11000 | J17: 195000 | K17: 11000 | L17: 200000 | M17: 1 | N17: 0 | P17: 0 | Q17: 4
A18: 46296 | B18: Alfa Romeo 156 2.5 V6 24V | C18: apify | D18: 8 | E18: 3200 | F18: 4293 | G18: 5695 | H18: 7125 | I18: 8800 | J18: 198000 | K18: 5700 | L18: 200000 | M18: 8 | N18: 0 | P18: 0.25 | Q18: 6
A19: 46296 | B19: BMW Z3 1.9i / 2.0i | C19: apify | D19: 14 | E19: 7490 | F19: 9990 | G19: 11240 | H19: 12740 | I19: 17900 | J19: 125000 | K19: 12020 | L19: 130000 | M19: 14 | N19: 0 | P19: 0.86 | Q19: 26
A20: 46296 | B20: Citroën Saxo VTS 16V | C20: apify | D20: 40 | E20: 1600 | F20: 4875 | G20: 6350 | H20: 8350 | I20: 12980 | J20: 189000 | K20: 7750 | L20: 150000 | M20: 40 | N20: 0 | P20: 0.03 | Q20: 0
A21: 46296 | B21: Honda S2000 | C21: apify | D21: 39 | E21: 4599 | F21: 14900 | G21: 21000 | H21: 27500 | I21: 49990 | J21: 139000 | K21: 22260 | L21: 140000 | M21: 39 | N21: 0 | P21: 0.38 | Q21: 1
A22: 46296 | B22: Mazda MX-5 NA | C22: apify | D22: 37 | E22: 3990 | F22: 9500 | G22: 11980 | H22: 13500 | I22: 17990 | J22: 163000 | K22: 11580 | L22: 160000 | M22: 37 | N22: 0 | P22: 0.14 | Q22: 3
A23: 46296 | B23: Peugeot 205 GTI | C23: apify | D23: 38 | E23: 5500 | F23: 14925 | G23: 18000 | H23: 20675 | I23: 31000 | J23: 185000 | K23: 17870 | L23: 190000 | M23: 38 | N23: 0 | P23: 0.11 | Q23: 2
A24: 46296 | B24: Peugeot 206 RC | C24: apify | D24: 39 | E24: 5400 | F24: 7500 | G24: 9990 | H24: 12600 | I24: 18500 | J24: 159000 | K24: 11240 | L24: 150000 | M24: 2 | N24: 0 | P24: 0.1 | Q24: 1
A25: 46296 | B25: Peugeot 208 GTi 30th | C25: apify | D25: 10 | E25: 10500 | F25: 13368 | G25: 14940 | H25: 17100 | I25: 23490 | J25: 110000 | K25: 16280 | L25: 100000 | M25: 10 | N25: 0 | P25: 0.4 | Q25: 0
A26: 46296 | B26: Peugeot 306 S16 | C26: apify | D26: 25 | E26: 1000 | F26: 6800 | G26: 8200 | H26: 12800 | I26: 26800 | J26: 185000 | K26: 9790 | L26: 180000 | M26: 25 | N26: 0 | P26: 0 | Q26: 5
A27: 46296 | B27: Porsche 911 997 Carrera S | C27: apify | D27: 36 | E27: 39990 | F27: 49988 | G27: 51395 | H27: 56240 | I27: 69599 | J27: 110000 | K27: 55200 | L27: 100000 | M27: 36 | N27: 0 | P27: 0.83 | Q27: 4
... A32: 46296 | B32: Renault Twingo 1 découvrable | C32: apify | D32: 27 | E32: 699 | F32: 2095 | G32: 2990 | H32: 3550 | I32: 5990 | J32: 165000 | K32: 3380 | L32: 150000 | M32: 27 | N32: 0 | P32: 0.22 | Q32: 13
A33: 46273 | B33: Citroën Saxo VTS 16V | C33: manuel | D33: 2 | E33: 6500 | G33: 6600 | I33: 6700 | J33: 153683
A34: 46273 | B34: Peugeot 206 RC | C34: manuel | D34: 1 | E34: 6790 | G34: 6790 | I34: 6790 | J34: 244000
A35: 46273 | B35: Peugeot 208 GTi 30th | C35: manuel | D35: 7 | E35: 12990 | G35: 15990 | I35: 23490 | J35: 108000
A36: 46273 | B36: Porsche 911 997 Carrera S | C36: manuel | D36: 11 | E36: 46500 | G36: 51000 | I36: 74900 | J36: 100000
A37: 46273 | B37: Porsche Boxster 986 | C37: manuel | D37: 4 | E37: 17986 | G37: 22425 | I37: 26900 | J37: 110000
A38: 46273 | B38: Porsche Boxster 987 | C38: manuel | D38: 5 | E38: 33000 | G38: 43990 | I38: 72986 | J38: 65000
A39: 46273 | B39: Renault Clio II RS (172/182 ch) | C39: manuel | D39: 2 | E39: 6000 | G39: 8899.5 | I39: 11799 | J39: 168000
A40: 46273 | B40: Renault Twingo 1 découvrable | C40: manuel | D40: 6 | E40: 1500 | G40: 5490 | I40: 6290 | J40: 150000

Sheet Annonces
A1: Véhicule | B1: Titre | C1: Version | D1: Finition | E1: Statut | F1: Publiée le | G1: Première vue | H1: Dernière vue | I1: Partie le | J1: Jours en ligne | K1: Prix initial | L1: Prix actuel | M1: Baisse de prix | N1: Nb de baisses | O1: Ancien prix affiché | P1: Estimation LBC min | Q1: Estimation LBC max | R1: Écart vs estimation LBC | S1: Positionnement LBC | T1: Km | U1: Année | V1: Mise en circulation | W1: Carburant | X1: Boîte | Y1: Puissance DIN (ch) | Z1: Puissance fiscale (CV) | AA1: Couleur | AB1: Portes | AC1: Type | AD1: Entretien | AE1: Historique | AF1: Vendeur | AG1: Ville | AH1: Code postal | AI1: Département | AJ1: Région | AK1: Photos | AL1: Remontée payante | AM1: Urgent | AN1: Description (extrait) | AO1: Autres caractéristiques | AP1: Annonce | AQ1: Id
A2: Alfa Romeo 156 2.5 V6 24V | B2: Alfa Roméo 156 SW V6 2,5l 24s | E2: En vente | F2: 46303 | G2: 46237 | H2: 46310 | J2: =IF(OR(ISNUMBER(F2),ISNUMBER(G2)),IF(ISNUMBER(I2),I2,H2)-IF(ISNUMBER(F2),F2,G2),"") | K2: 7500 | L2: 7500 | M2: =IF(AND(ISNUMBER(K2),ISNUMBER(L2),K2>0),1-L2/K2,"") | N2: 0 | R2: =IF(AND(ISNUMBER(L2),ISNUMBER(P2),ISNUMBER(Q2)),L2/((P2+Q2)/2)-1,"") | T2: 316324 | U2: 2003 | V2: 10/2003 | W2: Essence | X2: Manuelle | Y2: 190 | Z2: 14 | AA2: Noir | AB2: 5 | AC2: Break | AF2: Particulier | AG2: La Chaussée-Saint-Victor | AH2: 41260 | AI2: Loir-et-Cher | AJ2: Centre | AK2: 3 | AM2: Non | AN2: Alfa Roméo 156 de 2003 V6 Busso 2,5l 24 soupapes finition TI. Parfaitement entretenue : courroie de distribution et pompe à eau faites en 2024 (facture). vidange moteur boîte 2025 (facture) Intérieur cuir noir spécifique TI en excellent état général. 4 Pneus neuf Triangle train avant récent. Alternateur, démarreur, embrayage remplacer Voiture avec entretien suivi depuis l'achat | AO2: Dommages : Non endommagé ; Sellerie : Tout cuir ; Équipements intérieurs : Jantes en alliage, Régulateur de vitesse ; vehicle_euro_emissions_standard : Euro 3 ; Permis : Avec permis ; Importé : false | AP2: Voir | AQ2: 2903975057
A3: Alfa Romeo 156 2.5 V6 24V | B3: Alfa Romeo 156 2.5 V6 Busso | E3: En vente | F3: 46259 | G3: 46259 | H3: 46310 | J3: =IF(OR(ISNUMBER(F3),ISNUMBER(G3)),IF(ISNUMBER(I3),I3,H3)-IF(ISNUMBER(F3),F3,G3),"") | K3: 8800 | L3: 8800 | M3: =IF(AND(ISNUMBER(K3),ISNUMBER(L3),K3>0),1-L3/K3,"") | N3: 0 | R3: =IF(AND(ISNUMBER(L3),ISNUMBER(P3),ISNUMBER(Q3)),L3/((P3+Q3)/2)-1,"") | T3: 200000 | U3: 2001 | V3: 06/2001 | W3: Essence | X3: Manuelle | Y3: 192 | Z3: 13 | AA3: Gris | AB3: 4 | AC3: Berline | AD3: Véhicule non fumeur, Factures disponibles, Réparations utiles déjà faites | AF3: Particulier | AG3: Waldighofen | AH3: 68640 | AI3: Haut-Rhin | AJ3: Alsace | AK3: 10 | AM3: Non | AN3: Magnifique Alfa Romeo 156 équipée du légendaire V6 Busso 2.5 24V atmosphérique (192 ch), un moteur recherché pour sa sonorité exceptionnelle et son caractère unique. 200 000 km – boîte manuelle – très bel état général. Véhicule importé de Suisse, avec historique et factures d’entretien disponibles. Nombreux travaux récents réalisés : * Ligne d’échappement Ragazzon * Ressorts Eibach neufs * Train avant révisé (rotules, articulations…) * Pompe à essence neuve * Joints de couvre-culasse remplacés * | AO3: vehicle_technical_inspection_valid : Oui ; Contrôle technique : 2028 ; Sellerie : Tout cuir ; Équipements intérieurs : Climatisation ; Permis : Avec permis ; Importé : false | AP3: Voir | AQ3: 3222893175
A4: Alfa Romeo 156 2.5 V6 24V | B4: Alfa romeo 156 2.5 v6 24v | C4: 156 2.5 V6 24v | D4: Base | E4: En vente | F4: 46225 | G4: 46225 | H4: 46310 | J4: =IF(OR(ISNUMBER(F4),ISNUMBER(G4)),IF(ISNUMBER(I4),I4,H4)-IF(ISNUMBER(F4),F4,G4),"") | K4: 6490 | L4: 6490 | M4: =IF(AND(ISNUMBER(K4),ISNUMBER(L4),K4>0),1-L4/K4,"") | N4: 0 | O4: 6790 | R4: =IF(AND(ISNUMBER(L4),ISNUMBER(P4),ISNUMBER(Q4)),L4/((P4+Q4)/2)-1,"") | T4: 196500 | U4: 1998 | V4: 04/1998 | W4: Essence | X4: Manuelle | Y4: 190 | Z4: 14 | AA4: Bleu | AB4: 4 | AC4: Berline | AF4: Pro | AG4: Abbeville | AH4: 80100 | AI4: Somme | AJ4: Picardie | AK4: 43 | AM4: Non | AN4: L'Agence TransakAuto ABBEVILLE, société spécialisée en courtage automobile, 1er réseau d'intermédiation automobile auprès des particuliers avec + de 180 agences en France depuis 2011, vous propose ce véhicule Alfa Romeo, 156, Bleu, 14 chevaux fiscaux, 4 portes, 196 500 km. ⚠ 🔦 Véhicule visible uniquement sur rdv à l'agence TransakAuto ABBEVILLE, du mardi au samedi de Lundi - Vendredi 10h - 19h Samedi 10h - 18h Véhicule en dépôt-vente [non stocké sur place]. Visible uniquement sur rendez-vous da | AO4: Équipements intérieurs : Climatisation, Jantes en alliage ; VO récent : false ; custom_ref : VO42668613 ; Importé : true ; vehicle_history_report_status : visible ; spare_parts_availability : Non renseignée | AP4: Voir | AQ4: 3237198858
A5: Alfa Romeo 156 2.5 V6 24V | B5: Alfa 156 2.5 v6 GPL | E5: En vente | F5: 46267 | G5: 46267 | H5: 46310 | J5: =IF(OR(ISNUMBER(F5),ISNUMBER(G5)),IF(ISNUMBER(I5),I5,H5)-IF(ISNUMBER(F5),F5,G5),"") | K5: 3200 | L5: 3200 | M5: =IF(AND(ISNUMBER(K5),ISNUMBER(L5),K5>0),1-L5/K5,"") | N5: 0 | R5: =IF(AND(ISNUMBER(L5),ISNUMBER(P5),ISNUMBER(Q5)),L5/((P5+Q5)/2)-1,"") | T5: 202000 | U5: 1999 | V5: 07/1999 | W5: Essence | X5: Manuelle | Y5: 190 | Z5: 13 | AA5: Noir | AB5: 4 | AC5: Berline | AF5: Particulier | AG5: Romans | AH5: 79260 | AI5: Deux-Sèvres | AJ5: Poitou-Charentes | AK5: 3 | AM5: Non | AN5: Alfa 156 2.5 v6 équipe GPL 202000 km Sortie de grange n' a pas roulé depuis 6 ans . Démarré de temps en temps pour la lubrification. Amortisseur bilstein Ressort court H&R Intermédiaire ragazzon Silencieux ragazzon Intérieur cuir momo | AO5: Permis : Avec permis ; Importé : false | AP5: Voir | AQ5: 3261414202
A6: Alfa Romeo 156 2.5 V6 24V | B6: Alfa romeo 166 v6 busso 2003 | E6: En vente | F6: 46268 | G6: 46268 | H6: 46310 | J6: =IF(OR(ISNUMBER(F6),ISNUMBER(G6)),IF(ISNUMBER(I6),I6,H6)-IF(ISNUMBER(F6),F6,G6),"") | K6: 4390 | L6: 4390 | M6: =IF(AND(ISNUMBER(K6),ISNUMBER(L6),K6>0),1-L6/K6,"") | N6: 0 | R6: =IF(AND(ISNUMBER(L6),ISNUMBER(P6),ISNUMBER(Q6)),L6/((P6+Q6)/2)-1,"") | T6: 207800 | U6: 2003 | V6: 01/2003 | W6: Essence | X6: Manuelle | Y6: 188 | Z6: 14 | AA6: Gris | AB6: 4 | AC6: Berline | AD6: Carnet d'entretien disponible, Véhicule non fumeur, Factures disponibles | AF6: Particulier | AG6: Lapalisse | AH6: 03120 | AI6: Allier | AJ6: Auvergne | AK6: 3 | AM6: Non | AN6: Vends mon Alfa Romeo 166 V6 de 2003 avec 207800kms moteur busso 2.5 V6 188 ch (156 / 164) beaucoup d'options intérieur cuir, gps, radio cd, régulateur de vitesse, climatisation, jantes alu etc Le véhicule est en bon état pour son âge pochette de bord disponible (factures aussi) Moteur boite fonctionne parfaitement (distribution 2018) CT ok et papiers à mon nom Plus d'information par Téléphone uniquement ,merci échange possible 4x4 ou véhicule sportive gti 16 crx vtec turbo.. Prix à déb si achete | AO6: Dommages : Bon état général ; Sellerie : Tout cuir ; Équipements intérieurs : Climatisation, Coffre à ouverture électrique, Jantes en alliage, Ordinateur de bord, Phares anti-brouillard, Roue de secours, Régulateur de vitesse, Sièges chauffants, Sièges en cuir, Sièges électriques, Système de navigation ; Permis : Avec permis ; Importé : false | AP6: Voir | AQ6: 3262191550
A7: Alfa Romeo 156 2.5 V6 24V | B7: Alfa Romeo 156 v6 SW 2.5 | E7: En vente | F7: 46289 | G7: 46289 | H7: 46310 | J7: =IF(OR(ISNUMBER(F7),ISNUMBER(G7)),IF(ISNUMBER(I7),I7,H7)-IF(ISNUMBER(F7),F7,G7),"") | K7: 4000 | L7: 4000 | M7: =IF(AND(ISNUMBER(K7),ISNUMBER(L7),K7>0),1-L7/K7,"") | N7: 0 | R7: =IF(AND(ISNUMBER(L7),ISNUMBER(P7),ISNUMBER(Q7)),L7/((P7+Q7)/2)-1,"") | T7: 175000 | U7: 2004 | V7: 01/2004 | W7: Essence | X7: Manuelle | Y7: 192 | Z7: 14 | AA7: Noir | AB7: 5 | AC7: Berline | AD7: Factures disponibles, Carnet d'entretien disponible | AF7: Particulier | AG7: Mortcerf | AH7: 77163 | AI7: Seine-et-Marne | AJ7: Ile-de-France | AK7: 3 | AM7: Non | AN7: Bonjour Je vends mon Alfa Romeo 156 v6 2.5 En break, SW. Phase 3. Assez bon état général. 178 000 kms Cuir beige abricot a l intérieur Entretien effectué, distribution, embrayage, bougies, soufflet de transmission, pompe a eau.... Ct ok Parcours toutes distances. Disponible pour tous renseignements | AO7: vehicle_technical_inspection_valid : Non ; Dommages : Bon état général ; Sellerie : Tout cuir ; Équipements intérieurs : Climatisation, Jantes en alliage, Ordinateur de bord, Régulateur de vitesse, Rétroviseurs dégivrants, Siège arrière rabattable, Siège réglable en hauteur, Sièges en cuir, Vitres électriques arrières, Volant réglable en hauteur, Volant réglable en profondeur ; vehicle_euro_emissions_standard : Euro 5 ; Permis : Avec permis ; Importé : false ; vehicle_history_teaser_critair : 3 ; vehicle_history_teaser_owners : 5 ; vehicle_history_teaser_expertises : false ; vehicle_history_teaser_special_uses : false ; vehicle_history_teaser_atypical_operations : false ; vehicle_history_teaser_importations : false | AP7: Voir | AQ7: 3275564839
A8: Alfa Romeo 156 2.5 V6 24V | B8: Alfa Romeo 156 2.5 V6 Busso Rouge 1997 | E8: En vente | F8: 46298 | G8: 46298 | H8: 46310 | J8: =IF(OR(ISNUMBER(F8),ISNUMBER(G8)),IF(ISNUMBER(I8),I8,H8)-IF(ISNUMBER(F8),F8,G8),"") | K8: 14900 | L8: 14900 | M8: =IF(AND(ISNUMBER(K8),ISNUMBER(L8),K8>0),1-L8/K8,"") | N8: 0 | R8: =IF(AND(ISNUMBER(L8),ISNUMBER(P8),ISNUMBER(Q8)),L8/((P8+Q8)/2)-1,"") | T8: 55000 | U8: 1997 | V8: 11/1997 | W8: Essence | X8: Manuelle | Y8: 190 | Z8: 14 | AA8: Rouge | AB8: 4 | AC8: Berline | AF8: Pro | AG8: Saint-Junien | AH8: 87200 | AI8: Haute-Vienne | AJ8: Limousin | AK8: 5 | AM8: Non | AN8: La Maison du Cylindre, garage spécialisé dans l'achat-vente et l'entretien de véhicules de collection, situé en Haute-Vienne (87), vous propose : Alfa Romeo 156 2.5 V6 Busso Rouge 1997 en superbe état intérieur et extérieur Kilométrage : 55 000 km relevé compteur Moteur : V6 Busso 2.5L 190ch Boîte de vitesses manuelle 6 rapports Teinte Rosso Alfa Sellerie velours gris logotée Alfa Romeo Freins à disques ventilés à l'avant ABS Direction assistée Vitres électriques Fermeture centralisée Rétroviseu | AO8: Sellerie : Tissu ; Permis : Sans permis ; VO récent : false ; Importé : false ; vehicle_history_report_status : visible ; vehicle_history_teaser_critair : 3 ; vehicle_history_teaser_owners : 2 ; vehicle_history_teaser_expertises : false ; vehicle_history_teaser_special_uses : false ; vehicle_history_teaser_atypical_operations : true ; vehicle_history_teaser_importations : true ; spare_parts_availability : Non renseignée | AP8: Voir | AQ8: 3281190008
A9: Alfa Romeo 156 2.5 V6 24V | B9: Alfa Romeo 156 2.5 V6 24V | E9: En vente | F9: 46301 | G9: 46301 | H9: 46310 | J9: =IF(OR(ISNUMBER(F9),ISNUMBER(G9)),IF(ISNUMBER(I9),I9,H9)-IF(ISNUMBER(F9),F9,G9),"") | K9: 7800 | L9: 7800 | M9: =IF(AND(ISNUMBER(K9),ISNUMBER(L9),K9>0),1-L9/K9,"") | N9: 0 | R9: =IF(AND(ISNUMBER(L9),ISNUMBER(P9),ISNUMBER(Q9)),L9/((P9+Q9)/2)-1,"") | T9: 213808 | U9: 2002 | V9: 03/2002 | W9: Essence | X9: Manuelle | Y9: 192 | Z9: 14 | AA9: Gris | AB9: 4 | AC9: Berline | AD9: Carnet d'entretien disponible, Factures disponibles, Véhicule non fumeur, Réparations utiles déjà faites | AE9: Première main | AF9: Particulier | AG9: Le Havre | AH9: 76620 | AI9: Seine-Maritime | AJ9: Haute-Normandie | AK9: 3 | AM9: Non | AN9: Bonjour , Avis aux passionnés et connaisseurs de la marque au trèfle ,Je me sépare à contre-cœur de mon Alfa Romeo 156 V6 2.5 de 2002, équipée du mythique moteur Arese (sonorité et comportement d'exception). Le véhicule a toujours été respecté, temps de chauffe et d'arrêt scrupuleusement appliqués, aucunes corrosion ! Dossier de factures monumentale. Énorme préparation esthétique et mécanique récente (plusieurs milliers d'euros investis cette année). ⚙️ TRAIN AVANT & CHÂSSIS (Refait à neuf en Ju | AO9: vehicle_technical_inspection_valid : Non ; Dommages : Traces d’usure normales ; Sellerie : Tout cuir ; Équipements intérieurs : Régulateur de vitesse, Sièges chauffants, Sièges en cuir ; vehicle_euro_emissions_standard : Euro 3 ; Permis : Avec permis ; Importé : false ; vehicle_history_teaser_critair : 3 ; vehicle_history_teaser_owners : 3 ; vehicle_history_teaser_expertises : false ; vehicle_history_teaser_special_uses : false ; vehicle_history_teaser_atypical_operations : false ; vehicle_history_teaser_importations : false | AP9: Voir | AQ9: 3283116401
A10: Alfa Romeo 156 2.5 V6 24V | B10: ALFA ROMEO 156 2.5 V6 24V BOÎTE AUTOMATIQUE 195cv COMPLÈTEMENT RÉVISÉ | E10: Partie | F10: 46244 | G10: 46244 | H10: 46296 | I10: 46310 | J10: =IF(OR(ISNUMBER(F10),ISNUMBER(G10)),IF(ISNUMBER(I10),I10,H10)-IF(ISNUMBER(F10),F10,G10),"") | K10: 4900 | L10: 4900 | M10: =IF(AND(ISNUMBER(K10),ISNUMBER(L10),K10>0),1-L10/K10,"") | N10: 0 | R10: =IF(AND(ISNUMBER(L10),ISNUMBER(P10),ISNUMBER(Q10)),L10/((P10+Q10)/2)-1,"") | T10: 147000 | U10: 2001 | W10: Essence | X10: Automatique | Y10: 195 | Z10: 10 | AA10: Ivoire | AB10: 5 | AC10: Berline | AF10: Pro | AG10: Blotzheim | AH10: 68730 | AI10: Haut-Rhin | AJ10: Alsace | AP10: Voir | AQ10: 3212500586
A11: Alfa Romeo 156 2.5 V6 24V | B11: Alfa Romeo 156 2.5 V6 24V | E11: Partie | F11: 46281 | G11: 46281 | H11: 46296 | I11: 46310 | J11: =IF(OR(ISNUMBER(F11),ISNUMBER(G11)),IF(ISNUMBER(I11),I11,H11)-IF(ISNUMBER(F11),F11,G11),"") | K11: 7000 | L11: 7000 | M11: =IF(AND(ISNUMBER(K11),ISNUMBER(L11),K11>0),1-L11/K11,"") | N11: 0 | R11: =IF(AND(ISNUMBER(L11),ISNUMBER(P11),ISNUMBER(Q11)),L11/((P11+Q11)/2)-1,"") | T11: 160000 | U11: 2002 | W11: Essence | X11: Automatique | Y11: 192 | Z11: 14 | AA11: Autre | AB11: 4 | AC11: Berline | AF11: Particulier | AG11: Marne-la-Vallée | AH11: 77186 | AI11: Seine-et-Marne | AJ11: Ile-de-France | AP11: Voir | AQ11: 3270896149
A12: BMW Z3 1.9i / 2.0i | B12: BMW z3 | E12: En vente | F12: 46300 | G12: 46300 | H12: 46310 | J12: =IF(OR(ISNUMBER(F12),ISNUMBER(G12)),IF(ISNUMBER(I12),I12,H12)-IF(ISNUMBER(F12),F12,G12),"") | K12: 7000 | L12: 7000 | M12: =IF(AND(ISNUMBER(K12),ISNUMBER(L12),K12>0),1-L12/K12,"") | N12: 0 | O12: 8000 | R12: =IF(AND(ISNUMBER(L12),ISNUMBER(P12),ISNUMBER(Q12)),L12/((P12+Q12)/2)-1,"") | T12: 158652 | U12: 1999 | V12: 08/1999 | W12: Essence | X12: Manuelle | Y12: 118 | Z12: 8 | AA12: Gris | AB12: 2 | AC12: Cabriolet | AF12: Particulier | AG12: Mallemort | AH12: 13370 | AI12: Bouches-du-Rhône | AJ12: Provence-Alpes-Côte d'Azur | AK12: 3 | AM12: Non | AN12: BMW z3 en bon état | AO12: Dommages : Bon état général ; Sellerie : Tissu ; Équipements intérieurs : Climatisation, Phares anti-brouillard, Sièges électriques ; Permis : Avec permis ; Importé : false | AP12: Voir | AQ12: 3211730689
A13: BMW Z3 1.9i / 2.0i | B13: BMW Z3 Roadster 1.8i 115ch SELLERIE NEUVE | C13: Z3 Roadster 1.8i 115ch | D13: Base | E13: En vente | F13: 46280 | G13: 46280 | H13: 46310 | J13: =IF(OR(ISNUMBER(F13),ISNUMBER(G13)),IF(ISNUMBER(I13),I13,H13)-IF(ISNUMBER(F13),F13,G13),"") | K13: 8990 | L13: 8990 | M13: =IF(AND(ISNUMBER(K13),ISNUMBER(L13),K13>0),1-L13/K13,"") | N13: 0 | R13: =IF(AND(ISNUMBER(L13),ISNUMBER(P13),ISNUMBER(Q13)),L13/((P13+Q13)/2)-1,"") | T13: 147000 | U13: 1996 | V13: 05/1996 | W13: Essence | X13: Manuelle | Y13: 116 | Z13: 9 | AA13: Gris | AB13: 2 | AF13: Pro | AG13: Abbeville | AH13: 80100 | AI13: Somme | AJ13: Picardie | AK13: 50 | AL13: Oui | AM13: Non | AN13: L'Agence TransakAuto ABBEVILLE, société spécialisée en courtage automobile, 1er réseau d'intermédiation automobile auprès des particuliers avec + de 180 agences en France depuis 2011, vous propose ce véhicule Bmw, Z3, Gris, 9 chevaux fiscaux, 2 portes, 147 000 km. ⚠ 🔦 Véhicule visible uniquement sur rdv à l'agence TransakAuto ABBEVILLE, du mardi au samedi de Lundi - Vendredi 10h - 19h Samedi 10h - 18h Véhicule en dépôt-vente [non stocké sur place]. Visible uniquement sur rendez-vous dans votre | AO13: Équipements intérieurs : Jantes en alliage, Sièges en cuir ; VO récent : false ; custom_ref : VO17964933 ; Importé : true ; vehicle_history_report_status : visible ; spare_parts_availability : Non renseignée | AP13: Voir | AQ13: 3237198765
A14: BMW Z3 1.9i / 2.0i | B14: BMW Z3 1.8L Roadster 115CV / CARROSSERIE NEUVE BMW / ENTRETIEN À JOUR / ÉTAT CONCOURS | C14: Z3 Roadster 1.8i 115ch | D14: Base | E14: En vente | F14: 46225 | G14: 46225 | H14: 46310 | J14: =IF(OR(ISNUMBER(F14),ISNUMBER(G14)),IF(ISNUMBER(I14),I14,H14)-IF(ISNUMBER(F14),F14,G14),"") | K14: 12990 | L14: 12990 | M14: =IF(AND(ISNUMBER(K14),ISNUMBER(L14),K14>0),1-L14/K14,"") | N14: 0 | O14: 13490 | R14: =IF(AND(ISNUMBER(L14),ISNUMBER(P14),ISNUMBER(Q14)),L14/((P14+Q14)/2)-1,"") | T14: 104800 | U14: 1997 | V14: 03/1997 | W14: Essence | X14: Manuelle | Y14: 116 | Z14: 7 | AA14: Noir | AB14: 2 | AC14: Cabriolet | AF14: Pro | AG14: Saint-Quentin | AH14: 02100 | AI14: Aisne | AJ14: Picardie | AK14: 39 | AL14: Oui | AM14: Non | AN14: L'Agence TransakAuto SAINT-QUENTIN, société spécialisée en courtage automobile, 1er réseau d'intermédiation automobile auprès des particuliers avec + de 180 agences en France depuis 2011, vous propose ce véhicule Bmw, Z3, Noir, 7 chevaux fiscaux, 2 portes, 104 800 km. 🚗 Véhicule visible uniquement sur rdv à l'agence TransakAuto SAINT-QUENTIN, du mardi au samedi de 10H00 à 18H00. Merci de nous appeler avant toute venue afin de vérifier sa disponibilité ainsi que les modalités de la visite. (Une | AO14: Équipements intérieurs : Climatisation, Jantes en alliage, Phares anti-brouillard, Sièges chauffants ; VO récent : false ; custom_ref : VO15721372 ; Importé : true ; vehicle_history_report_status : visible ; spare_parts_availability : Non renseignée | AP14: Voir | AQ14: 3237237759
A15: BMW Z3 1.9i / 2.0i | B15: BMW Z3 Roadster 1.8i 115ch GARANTIE 12 MOIS | C15: Z3 Roadster 1.8i 115ch | D15: Base | E15: En vente | F15: 46293 | G15: 46293 | H15: 46310 | J15: =IF(OR(ISNUMBER(F15),ISNUMBER(G15)),IF(ISNUMBER(I15),I15,H15)-IF(ISNUMBER(F15),F15,G15),"") | K15: 9990 | L15: 9990 | M15: =IF(AND(ISNUMBER(K15),ISNUMBER(L15),K15>0),1-L15/K15,"") | N15: 0 | R15: =IF(AND(ISNUMBER(L15),ISNUMBER(P15),ISNUMBER(Q15)),L15/((P15+Q15)/2)-1,"") | T15: 151000 | U15: 1999 | V15: 07/1999 | W15: Essence | X15: Manuelle | Y15: 116 | Z15: 7 | AA15: Bleu | AB15: 2 | AC15: Cabriolet | AF15: Pro | AG15: Béziers | AH15: 34500 | AI15: Hérault | AJ15: Languedoc-Roussillon | AK15: 13 | AL15: Oui | AM15: Non | AN15: BMW Z3 Roadster 1.8i 115ch GARANTIE 12 MOIS cabriolet, bleu, 7 cv, 2 portes, première mise en circulation le 01/07/1999, garantie 12 mois. Véhicule décrit avec ses équipements de série. Les équipements, les options et la version décrits sont sous réserve d erreurs de saisie. Ils doivent être vérifiés par l acheteur pendant l essai ou à la livraison. La garantie actuelle peut être étendue jusqu à 48 mois. Nous pouvons reprendre votre véhicule pour cet achat ou vous proposer un financement avec no | AO15: Équipements intérieurs : Jantes en alliage, Vitres électriques arrières ; Permis : Avec permis ; VO récent : false ; custom_ref : 64DV000520 ; Importé : true ; vehicle_history_report_status : visible ; spare_parts_availability : Non renseignée | AP15: Voir | AQ15: 3243864537
A16: BMW Z3 1.9i / 2.0i | B16: Bmw z3 | C16: Z3 Roadster 1.8i 115ch | D16: Base | E16: En vente | F16: 46309 | G16: 46309 | H16: 46310 | J16: =IF(OR(ISNUMBER(F16),ISNUMBER(G16)),IF(ISNUMBER(I16),I16,H16)-IF(ISNUMBER(F16),F16,G16),"") | K16: 12000 | L16: 12000 | M16: =IF(AND(ISNUMBER(K16),ISNUMBER(L16),K16>0),1-L16/K16,"") | N16: 0 | R16: =IF(AND(ISNUMBER(L16),ISNUMBER(P16),ISNUMBER(Q16)),L16/((P16+Q16)/2)-1,"") | T16: 65000 | U16: 1996 | V16: 10/1996 | W16: Essence | X16: Manuelle | Y16: 115 | Z16: 7 | AA16: Noir | AB16: 2 | AC16: Cabriolet | AF16: Particulier | AG16: Saint-Victoret | AH16: 13730 | AI16: Bouches-du-Rhône | AJ16: Provence-Alpes-Côte d'Azur | AK16: 3 | AM16: Non | AN16: Bmw Z3, faible, kilométrage en très bon état Peinture d'origine, prix 12 000 € | AO16: Dommages : Excellent état (proche du neuf) ; Sellerie : Tout cuir ; vehicle_euro_emissions_standard : Euro 2 ; Permis : Avec permis ; Importé : false | AP16: Voir | AQ16: 3246077665
A17: BMW Z3 1.9i / 2.0i | B17: Bmw z3 | C17: Base_Z3 Roadster 1.9i 140ch | D17: Base | E17: En vente | F17: 46302 | G17: 46302 | H17: 46310 | J17: =IF(OR(ISNUMBER(F17),ISNUMBER(G17)),IF(ISNUMBER(I17),I17,H17)-IF(ISNUMBER(F17),F17,G17),"") | K17: 10500 | L17: 10500 | M17: =IF(AND(ISNUMBER(K17),ISNUMBER(L17),K17>0),1-L17/K17,"") | N17: 0 | O17: 10900 | R17: =IF(AND(ISNUMBER(L17),ISNUMBER(P17),ISNUMBER(Q17)),L17/((P17+Q17)/2)-1,"") | T17: 168200 | U17: 1996 | V17: 07/1996 | W17: Essence | X17: Manuelle | Y17: 140 | Z17: 10 | AA17: Gris | AB17: 2 | AC17: Cabriolet | AF17: Particulier | AG17: Bagnoles de l'Orne Normandie | AH17: 61140 | AI17: Orne | AJ17: Basse-Normandie | AK17: 3 | AM17: Non | AN17: BMW Z3 Roadster de 1996, un cabriolet très agréable a conduire, extérieur gris métal avec un intérieur rouge bordeaux - Marque : BMW - Modèle : Z3 - Année : 1996 - Kilométrage : 168 200 km - Motorisation : 1.9i 140 ch - Carburant : Essence - Boîte de vitesses : Manuelle - Couleur : Gris - Type : Cabriolet Roadster - Nombre de sièges : 2 - Nombre de portes : 2 - Puissance fiscale : 10 Cv - Contrôle technique : Valide jusqu'en 05/2027 Capote remplacée en 2020. N'hésitez pas à me contacter pour plu | AO17: Sellerie : Tout cuir ; Équipements intérieurs : Siège réglable en hauteur, Sièges chauffants, Sièges en cuir, Sièges électriques ; Permis : Avec permis ; Importé : false | AP17: Voir | AQ17: 3246862811
A18: BMW Z3 1.9i / 2.0i | B18: Bmw z3 | E18: En vente | F18: 46261 | G18: 46261 | H18: 46310 | J18: =IF(OR(ISNUMBER(F18),ISNUMBER(G18)),IF(ISNUMBER(I18),I18,H18)-IF(ISNUMBER(F18),F18,G18),"") | K18: 11900 | L18: 11900 | M18: =IF(AND(ISNUMBER(K18),ISNUMBER(L18),K18>0),1-L18/K18,"") | N18: 0 | O18: 12900 | R18: =IF(AND(ISNUMBER(L18),ISNUMBER(P18),ISNUMBER(Q18)),L18/((P18+Q18)/2)-1,"") | T18: 96810 | U18: 1999 | V18: 06/1999 | W18: Essence | X18: Manuelle | Y18: 118 | Z18: 8 | AA18: Rouge | AB18: 2 | AC18: Cabriolet | AF18: Particulier | AG18: Mirmande | AH18: 26270 | AI18: Drôme | AJ18: Rhône-Alpes | AK18: 7 | AM18: Non | AN18: Je vends un très beau cabriolet BMW Z3, modèle "M" avec une mise à jour du calculateur au E85 (éthanol), grosse économie dans les déplacements, (0,83 e/l au lieu de 2,25 e/l) très bien entretenu avec seulement 96810 kilomètres pour un véhicule de 1999. C'est un modèle M, avec la particularité de posséder des jantes aluminium BMW à déports (d'origine) ce qui lui procure une super tenue de route. D'autre part, contrairement à beaucoup de ce modèle de cabriolet, il ne possède pas des sièges en cuir | AO18: vehicle_technical_inspection_valid : Non ; Dommages : Excellent état (proche du neuf) ; Sellerie : Tissu ; Permis : Avec permis ; Importé : false ; vehicle_history_teaser_critair : 3 ; vehicle_history_teaser_owners : 2 ; vehicle_history_teaser_expertises : false ; vehicle_history_teaser_special_uses : false ; vehicle_history_teaser_atypical_operations : true ; vehicle_history_teaser_importations : true | AP18: Voir | AQ18: 3257804096
A19: BMW Z3 1.9i / 2.0i | B19: Bmw z3 1.9 140ch roadster + entretien à jour + garantie | C19: Z3 Roadster 1.9i 140ch | D19: Base | E19: En vente | F19: 46268 | G19: 46268 | H19: 46310 | J19: =IF(OR(ISNUMBER(F19),ISNUMBER(G19)),IF(ISNUMBER(I19),I19,H19)-IF(ISNUMBER(F19),F19,G19),"") | K19: 9990 | L19: 9990 | M19: =IF(AND(ISNUMBER(K19),ISNUMBER(L19),K19>0),1-L19/K19,"") | N19: 0 | R19: =IF(AND(ISNUMBER(L19),ISNUMBER(P19),ISNUMBER(Q19)),L19/((P19+Q19)/2)-1,"") | T19: 137000 | U19: 1998 | V19: 05/1998 | W19: Essence | X19: Manuelle | Y19: 140 | Z19: 9 | AA19: Gris | AB19: 2 | AC19: Cabriolet | AF19: Pro | AG19: Saint-Laurent-des-Vignes | AH19: 24100 | AI19: Dordogne | AJ19: Aquitaine | AK19: 15 | AL19: Oui | AM19: Non | AN19: BMW Z3 1.9 140CH ROADSTER + ENTRETIEN À JOUR + GARANTIE cabriolet, gris, 9 cv, 2 portes, première mise en circulation le 13/05/1998, garantie 98 mois. 2 places OPTIONS ET ÉQUIPEMENTS : Garantie : - Garantie 3 mois - Garantie 6 mois Pack : - équipements Sécurité : - Airbags Autres équipements et informations : - Démarche ( hors carte gris) - Les véhicules sont visible uniquement sur rendez-vous - Malgré tout le soin apporté à nos annonces des erreurs peuvent s'être glissées (options - Nettoyage P | AO19: Permis : Avec permis ; VO récent : false ; custom_ref : 0001136 ; Importé : true ; vehicle_history_report_status : visible ; spare_parts_availability : Non renseignée | AP19: Voir | AQ19: 3262111623
A20: BMW Z3 1.9i / 2.0i | B20: BMW Z3 1.9 i 140cv | C20: Z3 Roadster 1.9i 140ch | D20: Base | E20: En vente | F20: 46273 | G20: 46273 | H20: 46310 | J20: =IF(OR(ISNUMBER(F20),ISNUMBER(G20)),IF(ISNUMBER(I20),I20,H20)-IF(ISNUMBER(F20),F20,G20),"") | K20: 10990 | L20: 10990 | M20: =IF(AND(ISNUMBER(K20),ISNUMBER(L20),K20>0),1-L20/K20,"") | N20: 0 | O20: 11390 | R20: =IF(AND(ISNUMBER(L20),ISNUMBER(P20),ISNUMBER(Q20)),L20/((P20+Q20)/2)-1,"") | T20: 116200 | U20: 1999 | V20: 03/1999 | W20: Essence | X20: Manuelle | Y20: 140 | Z20: 9 | AA20: Violet | AB20: 2 | AC20: Cabriolet | AF20: Pro | AG20: Metz | AH20: 57050 | AI20: Moselle | AJ20: Lorraine | AK20: 20 | AL20: Oui | AM20: Non | AN20: AVEC FACTURES CT MOINS DE 6MOIS Pour vous garantir un accueil personnalisé et un accompagnement de qualité, tous nos véhicules sont visibles uniquement sur rendez-vous. L’AGENCE AUTOMOBILIÈRE accompagne chaque vente dans un esprit de confiance, d’honnêteté et de transparence. Découvrez plus de 5 000 véhicules d'occasion rigoureusement sélectionnés sur notre site. La garantie légale de conformité ne s'applique pas dans une vente entre particuliers. OPTIONS ET ÉQUIPEMENTS : Intérieur : - Climatisa | AO20: Équipements intérieurs : Climatisation, Vitres électriques arrières ; VO récent : false ; custom_ref : 508254 ; Importé : true ; vehicle_history_report_status : visible ; spare_parts_availability : Non renseignée | AP20: Voir | AQ20: 3265952895
A21: BMW Z3 1.9i / 2.0i | B21: Bmw z3 | E21: En vente | F21: 46279 | G21: 46279 | H21: 46310 | J21: =IF(OR(ISNUMBER(F21),ISNUMBER(G21)),IF(ISNUMBER(I21),I21,H21)-IF(ISNUMBER(F21),F21,G21),"") | K21: 9500 | L21: 9500 | M21: =IF(AND(ISNUMBER(K21),ISNUMBER(L21),K21>0),1-L21/K21,"") | N21: 0 | O21: 10000 | R21: =IF(AND(ISNUMBER(L21),ISNUMBER(P21),ISNUMBER(Q21)),L21/((P21+Q21)/2)-1,"") | T21: 186000 | U21: 1997 | V21: 05/1997 | W21: Essence | X21: Manuelle | Y21: 140 | Z21: 10 | AA21: Noir | AB21: 2 | AC21: Cabriolet | AD21: Véhicule non fumeur | AF21: Particulier | AG21: Saint-Nicolas-de-Redon | AH21: 44460 | AI21: Loire-Atlantique | AJ21: Pays de la Loire | AK21: 9 | AM21: Non | AN21: BMW Z3 phase 1 de 1997 Je vend ce véhicule pour des projets financiers. C’est une bmw z3 de 1997 en phase 1, moteur 1,9l 140chv, de couleur noir intérieur beige, avec hard-top. Ce véhicule est équipé d’une demi ligne (après catalyseur) en inox faites sur mesure, je la vend avec celle d’origine. Très bon état général, n’hésitez pas à me contacter par message pour plus de détails. Ce véhicule sera vendu avec le contrôle technique à jour (rien à prévoir) Il sera aussi vendue avec : - les jantes d’o | AO21: vehicle_technical_inspection_valid : Non ; Dommages : Bon état général ; Sellerie : Tout cuir ; Équipements intérieurs : Bluetooth, Sièges en cuir, Sièges électriques ; Permis : Avec permis ; Importé : false | AP21: Voir | AQ21: 3269719393
A22: BMW Z3 1.9i / 2.0i | B22: Bmw Z3 ROADSTER 2.0 I 150 M | C22: Z3 M Roadster M 325ch | D22: Base | E22: En vente | F22: 46280 | G22: 46280 | H22: 46310 | J22: =IF(OR(ISNUMBER(F22),ISNUMBER(G22)),IF(ISNUMBER(I22),I22,H22)-IF(ISNUMBER(F22),F22,G22),"") | K22: 14990 | L22: 14990 | M22: =IF(AND(ISNUMBER(K22),ISNUMBER(L22),K22>0),1-L22/K22,"") | N22: 0 | R22: =IF(AND(ISNUMBER(L22),ISNUMBER(P22),ISNUMBER(Q22)),L22/((P22+Q22)/2)-1,"") | T22: 165500 | U22: 2000 | V22: 04/2000 | W22: Essence | X22: Manuelle | Y22: 150 | Z22: 10 | AA22: Bleu | AB22: 2 | AC22: Cabriolet | AF22: Pro | AG22: Pibrac | AH22: 31820 | AI22: Haute-Garonne | AJ22: Midi-Pyrénées | AK22: 29 | AL22: Oui | AM22: Non | AN22: Bmw Z3 ROADSTER 2.0 I 150 M, roadster, bleu, 10 cv, 2 portes, première mise en circulation le 21/04/2000. 2 places 🏎️ **BMW Z3 Roadster – 2.0i 150 M** 📅 2000 | 📊 165 000 km | ⛽ Essence – 150 ch (2.0 6 cylindres) | 🔧 Boîte manuelle | 🔩 Propulsion ✨ **Le roadster emblématique, élégant et plaisir à l’état pur !** Cette **BMW Z3 Roadster 2.0i 150 ch** en finition **M** est une véritable voiture plaisir. Son **6 cylindres en ligne**, sa propulsion et son format compact offrent une expérience de | AO22: Permis : Avec permis ; VO récent : false ; custom_ref : BHC_85C69B ; Importé : true ; vehicle_history_report_status : visible ; spare_parts_availability : Non renseignée | AP22: Voir | AQ22: 3270344321
A23: BMW Z3 1.9i / 2.0i | B23: BMW Z3 2.0i A | C23: Z3 Roadster 1.9iA 150ch | D23: Base | E23: En vente | F23: 46281 | G23: 46281 | H23: 46310 | J23: =IF(OR(ISNUMBER(F23),ISNUMBER(G23)),IF(ISNUMBER(I23),I23,H23)-IF(ISNUMBER(F23),F23,G23),"") | K23: 12990 | L23: 12990 | M23: =IF(AND(ISNUMBER(K23),ISNUMBER(L23),K23>0),1-L23/K23,"") | N23: 0 | R23: =IF(AND(ISNUMBER(L23),ISNUMBER(P23),ISNUMBER(Q23)),L23/((P23+Q23)/2)-1,"") | T23: 133000 | U23: 1999 | V23: 09/1999 | W23: Essence | X23: Automatique | Y23: 150 | Z23: 10 | AA23: Noir | AB23: 2 | AC23: Cabriolet | AF23: Pro | AG23: La Roche-sur-Yon | AH23: 85000 | AI23: Vendée | AJ23: Pays de la Loire | AK23: 14 | AL23: Oui | AM23: Non | AN23: BMW Z3 2.0i A roadster, noir, 10 cv, 2 portes, couleur intérieure : noir, première mise en circulation le 01/09/1999. BackCar c'est une équipe dynamique et flexible, toujours à votre écoute et transparente pour répondre à vos besoins automobiles. Nous vous offrons un large choix de véhicules en stock, prêts à être découverts sur notre parc, ainsi qu'un service de recherche sur mesure pour des véhicules neufs ou d'occasion. Nos services : Entretien à jour et véhicules entièrement révisés Véhicule | AO23: Sellerie : Tout cuir ; Équipements intérieurs : Climatisation, Jantes en alliage, Sièges sport, Vitres électriques arrières ; Permis : Avec permis ; VO récent : false ; custom_ref : 24ok77d ; Importé : true ; vehicle_history_report_status : visible ; spare_parts_availability : Non renseignée | AP23: Voir | AQ23: 3271024428
A24: BMW Z3 1.9i / 2.0i | B24: BMW Z3 Roadster 1.8i ROADSTER E36 Roadster 1.8i - 1613-0000365 | C24: Z3 Roadster 1.8i 115ch | D24: Base | E24: En vente | F24: 46281 | G24: 46281 | H24: 46310 | J24: =IF(OR(ISNUMBER(F24),ISNUMBER(G24)),IF(ISNUMBER(I24),I24,H24)-IF(ISNUMBER(F24),F24,G24),"") | K24: 13200 | L24: 13200 | M24: =IF(AND(ISNUMBER(K24),ISNUMBER(L24),K24>0),1-L24/K24,"") | N24: 0 | R24: =IF(AND(ISNUMBER(L24),ISNUMBER(P24),ISNUMBER(Q24)),L24/((P24+Q24)/2)-1,"") | T24: 85000 | U24: 1997 | V24: 09/1997 | W24: Essence | X24: Manuelle | Y24: 115 | Z24: 7 | AA24: Gris | AB24: 2 | AC24: Cabriolet | AF24: Pro | AG24: Bègles | AH24: 33130 | AI24: Gironde | AJ24: Aquitaine | AK24: 10 | AL24: Oui | AM24: Non | AN24: 🚗 COACH MY CAR France 🚗 📅 Visite et essai : Uniquement sur rendez-vous. 🚚 Livraison : Vente à distance et livraison à domicile possibles (sur devis). 💰 Financement : Des solutions adaptées à votre budget sont disponibles. 🛡️ Garantie incluse : Tous nos véhicules sont garantis 6 mois / 10 000 km (valable pour les véhicules de moins de 25 ans et moins de 250 000 km). 🚀 Extension de garantie : En option jusqu'à 36 mois pour rouler l'esprit tranquille. 🔒 Sécurité : Complémentaire Automobile | AO24: Équipements intérieurs : Bluetooth, Climatisation, Jantes en alliage, Vitres électriques arrières ; VO récent : false ; custom_ref : 1613-0000365 ; Importé : true ; vehicle_history_report_status : visible ; spare_parts_availability : Non renseignée | AP24: Voir | AQ24: 3271039169
A25: BMW Z3 1.9i / 2.0i | B25: Bmw z3 roadster 1.8 | C25: Z3 Roadster 1.8i 115ch | D25: Base | E25: En vente | F25: 46289 | G25: 46289 | H25: 46310 | J25: =IF(OR(ISNUMBER(F25),ISNUMBER(G25)),IF(ISNUMBER(I25),I25,H25)-IF(ISNUMBER(F25),F25,G25),"") | K25: 9990 | L25: 9990 | M25: =IF(AND(ISNUMBER(K25),ISNUMBER(L25),K25>0),1-L25/K25,"") | N25: 0 | R25: =IF(AND(ISNUMBER(L25),ISNUMBER(P25),ISNUMBER(Q25)),L25/((P25+Q25)/2)-1,"") | T25: 225000 | U25: 2000 | V25: 10/2000 | W25: Essence | X25: Manuelle | Y25: 116 | Z25: 7 | AA25: Noir | AB25: 2 | AC25: Cabriolet | AF25: Pro | AG25: Marquise | AH25: 62250 | AI25: Pas-de-Calais | AJ25: Nord-Pas-de-Calais | AK25: 6 | AL25: Oui | AM25: Non | AN25: BMW Z3 ROADSTER 1.8 cabriolet, noir, 7 cv, 2 portes, première mise en circulation le 16/10/2000. CLSPRESTIGEAUTO VOUS PROPOSE UNE BMW Z3 Année: 2000 kms:225000 ch:116 2 places OPTIONS ET ÉQUIPEMENTS : Autres équipements et informations : - Classe Crit'air : 3 - Puissance kilowatt : 85 kw - consommation extra urbaine : 6,00 litres - consommation mixte : 7,80 litres - consommation urbaine : 10,90 litres - kilométrage garanti - puissance réelle : 116 ch - émission CO2 : 187 g/km Référence annonce : | AO25: Permis : Avec permis ; VO récent : false ; custom_ref : 459 ; Importé : true ; vehicle_history_report_status : visible ; spare_parts_availability : Non renseignée | AP25: Voir | AQ25: 3275857889
A26: BMW Z3 1.9i / 2.0i | B26: BMW Z3 Roadster 1.9i - 118 ch - Origine France - Entretien Complet - Garantie 12 Mois | C26: Z3 Roadster 1.9i 118ch | D26: Base | E26: En vente | F26: 46293 | G26: 46293 | H26: 46310 | J26: =IF(OR(ISNUMBER(F26),ISNUMBER(G26)),IF(ISNUMBER(I26),I26,H26)-IF(ISNUMBER(F26),F26,G26),"") | K26: 11990 | L26: 11990 | M26: =IF(AND(ISNUMBER(K26),ISNUMBER(L26),K26>0),1-L26/K26,"") | N26: 0 | R26: =IF(AND(ISNUMBER(L26),ISNUMBER(P26),ISNUMBER(Q26)),L26/((P26+Q26)/2)-1,"") | T26: 90000 | U26: 2002 | V26: 06/2002 | W26: Essence | X26: Manuelle | Y26: 118 | Z26: 8 | AA26: Noir | AB26: 2 | AC26: Cabriolet | AF26: Pro | AG26: Illkirch-Graffenstaden | AH26: 67400 | AI26: Bas-Rhin | AJ26: Alsace | AK26: 26 | AL26: Oui | AM26: Non | AN26: L'agence TEVO a le plaisir de vous proposer ce véhicule : BMW Z3 Roadster 1.9i - 118 ch - Origine France - Entretien Complet - Garantie 12 Mois Première mise en circulation le 05-06-2002 Kilométrage : 90000 km Puissance fiscale : 8 cv, 118 ch Garantie 12 Mois OPTIONS ET EQUIPEMENTS : Antenne radio courte sur aile AR gauche Appuis-tête avant Capote renbourrée (meilleure isolation thermique et acoustique) Ceintures de sécurité avec rétracteurs Chrome-Line extérieur Compte-tours Couvre-capote Direc | AO26: Dommages : Bon état général ; Permis : Avec permis ; VO récent : false ; custom_ref : 1793-0000054 ; Importé : true ; vehicle_history_report_status : visible ; spare_parts_availability : Non renseignée | AP26: Voir | AQ26: 3278275196
A27: BMW Z3 1.9i / 2.0i | B27: BMW Z3 Roadster 1.8i ROADSTER E36 Roadster 1.8i Capote neuve Collector | C27: Z3 Roadster 1.8i 115ch | D27: Base | E27: En vente | F27: 46198 | G27: 46198 | H27: 46310 | J27: =IF(OR(ISNUMBER(F27),ISNUMBER(G27)),IF(ISNUMBER(I27),I27,H27)-IF(ISNUMBER(F27),F27,G27),"") | K27: 8990 | L27: 8990 | M27: =IF(AND(ISNUMBER(K27),ISNUMBER(L27),K27>0),1-L27/K27,"") | N27: 0 | R27: =IF(AND(ISNUMBER(L27),ISNUMBER(P27),ISNUMBER(Q27)),L27/((P27+Q27)/2)-1,"") | T27: 160000 | U27: 1996 | V27: 08/1996 | W27: Essence | X27: Manuelle | Y27: 115 | Z27: 9 | AA27: Noir | AB27: 2 | AC27: Cabriolet | AF27: Pro | AG27: Mérignac | AH27: 33700 | AI27: Gironde | AJ27: Aquitaine | AK27: 26 | AL27: Oui | AM27: Non | AN27: BMW Z3 Roadster 1.8 115 ch 1996 Future véhicule de collection Capote neuve Le plaisir du roadster à l’ancienne, cheveux au vent. Je mets en vente cette magnifique BMW Z3 Roadster de 1996, un cabriolet devenu iconique qui traverse les années sans prendre une ride. Avec ses lignes intemporelles, son long capot et sa propulsion, elle offre un véritable plaisir de conduite et attire les regards partout où elle passe. Cette Z3 totalise 160 000 km et sera éligible au statut de véhicule de collection d | AO27: Dommages : Bon état général ; Permis : Avec permis ; VO récent : false ; custom_ref : 1022-0001933 ; Importé : true ; vehicle_history_report_status : visible ; spare_parts_availability : Non renseignée | AP27: Voir | AQ27: 3278297992
A28: BMW Z3 1.9i / 2.0i | B28: BMW Z3 Roadster 1.8i ROADSTER E36 Roadster 1.8i | C28: Z3 Roadster 1.8i 115ch | D28: Base | E28: En vente | F28: 46287 | G28: 46287 | H28: 46310 | J28: =IF(OR(ISNUMBER(F28),ISNUMBER(G28)),IF(ISNUMBER(I28),I28,H28)-IF(ISNUMBER(F28),F28,G28),"") | K28: 9490 | L28: 9490 | M28: =IF(AND(ISNUMBER(K28),ISNUMBER(L28),K28>0),1-L28/K28,"") | N28: 0 | R28: =IF(AND(ISNUMBER(L28),ISNUMBER(P28),ISNUMBER(Q28)),L28/((P28+Q28)/2)-1,"") | T28: 126000 | U28: 1998 | V28: 04/1998 | W28: Essence | X28: Manuelle | Y28: 115 | Z28: 9 | AA28: Gris | AB28: 2 | AC28: Cabriolet | AF28: Pro | AG28: Saint-Rémy-de-Provence | AH28: 13210 | AI28: Bouches-du-Rhône | AJ28: Provence-Alpes-Côte d'Azur | AK28: 18 | AL28: Oui | AM28: Non | AN28: Alpilles Automobile vous propose cette magnifique BMW Z3 Roadster 1.8i ROADSTER E36 Roadster Z3 1.8i , un véhicule au design soigné offrant performance, confort et plaisir de conduite. Chaque voiture proposée par Alpilles Automobile fait l’objet d’une sélection rigoureuse avant la mise en vente. - Véhicule visible uniquement sur rendez-vous à l’agence Alpilles Automobile Contactez nous par téléphone pour une réponse plus rapide. -Garantie assimilée constructeur possible jusqu’à 24 mois -Financem | AO28: Dommages : Bon état général ; Équipements intérieurs : Climatisation, Jantes en alliage, Vitres électriques arrières ; Permis : Avec permis ; VO récent : false ; custom_ref : 1732-0000727 ; Importé : true ; vehicle_history_report_status : visible ; spare_parts_availability : Non renseignée | AP28: Voir | AQ28: 3278388364
A29: BMW Z3 1.9i / 2.0i | B29: BMW Z3 Roadster 1.9 i 115cv - Pack M | C29: Z3 Roadster 1.8i 115ch | D29: Base | E29: En vente | F29: 46293 | G29: 46293 | H29: 46310 | J29: =IF(OR(ISNUMBER(F29),ISNUMBER(G29)),IF(ISNUMBER(I29),I29,H29)-IF(ISNUMBER(F29),F29,G29),"") | K29: 9990 | L29: 9990 | M29: =IF(AND(ISNUMBER(K29),ISNUMBER(L29),K29>0),1-L29/K29,"") | N29: 0 | R29: =IF(AND(ISNUMBER(L29),ISNUMBER(P29),ISNUMBER(Q29)),L29/((P29+Q29)/2)-1,"") | T29: 135400 | U29: 2001 | V29: 06/2001 | W29: Essence | X29: Manuelle | Y29: 115 | Z29: 8 | AA29: Noir | AB29: 2 | AC29: Cabriolet | AF29: Pro | AG29: Nice | AH29: 06200 | AI29: Alpes-Maritimes | AJ29: Provence-Alpes-Côte d'Azur | AK29: 28 | AL29: Oui | AM29: Non | AN29: BMW Z3 ROADSTER 1.9i – PACK M – 2001 2ÈME MAIN • 135 000 KM • CABRIOLET • PROPULSION Il y a des voitures que l'on achète pour aller vite. Et d'autres simplement parce qu'elles donnent envie de prendre la route. Cette BMW Z3 Roadster 1.9i de 115 ch, mise en circulation en 2001, appartient clairement à la seconde catégorie. Une silhouette devenue iconique, un long capot, deux places, une capote que l'on ouvre dès que le soleil apparaît et surtout cette architecture devenue rare : moteur à l'avant, | AO29: Équipements intérieurs : Climatisation, Ordinateur de bord, Vitres électriques arrières ; VO récent : false ; custom_ref : 509335 ; Importé : true ; vehicle_history_report_status : visible ; spare_parts_availability : Non renseignée | AP29: Voir | AQ29: 3278435582
A30: BMW Z3 1.9i / 2.0i | B30: Bmw z3 | E30: En vente | F30: 46301 | G30: 46301 | H30: 46310 | J30: =IF(OR(ISNUMBER(F30),ISNUMBER(G30)),IF(ISNUMBER(I30),I30,H30)-IF(ISNUMBER(F30),F30,G30),"") | K30: 10500 | L30: 10500 | M30: =IF(AND(ISNUMBER(K30),ISNUMBER(L30),K30>0),1-L30/K30,"") | N30: 0 | R30: =IF(AND(ISNUMBER(L30),ISNUMBER(P30),ISNUMBER(Q30)),L30/((P30+Q30)/2)-1,"") | T30: 119000 | U30: 2002 | V30: 02/2002 | W30: Essence | X30: Manuelle | Y30: 85 | Z30: 8 | AA30: Vert | AB30: 2 | AC30: Cabriolet | AF30: Particulier | AG30: Plounévez-Lochrist | AH30: 29430 | AI30: Finistère | AJ30: Bretagne | AK30: 3 | AM30: Non | AN30: Je vends ma BMW Z3 de 2002, un cabriolet sportif et élégant pour profiter de la route en toute liberté. - Marque : BMW - Modèle : Z3 - Année : 2002 - Kilométrage : 119 000 km - Motorisation : 1.9i 85 ch - Carburant : Essence - Boîte de vitesses : Manuelle - Couleur : Vert - Type de véhicule : Cabriolet - Nombre de sièges : 2 - Nombre de portes : 2 - Puissance fiscale : 8 Cv - Contrôle technique : Valide jusqu'en 02/2028 N'hésitez pas à me contacter pour plus d'informations ou pour convenir d'un | AO30: vehicle_technical_inspection_valid : Oui ; Contrôle technique : 2028 ; Dommages : Bon état général ; Sellerie : Tout cuir ; Permis : Avec permis ; Importé : false | AP30: Voir | AQ30: 3283125826
A31: BMW Z3 1.9i / 2.0i | B31: Bmw Z3 | E31: En vente | F31: 46301 | G31: 46301 | H31: 46310 | J31: =IF(OR(ISNUMBER(F31),ISNUMBER(G31)),IF(ISNUMBER(I31),I31,H31)-IF(ISNUMBER(F31),F31,G31),"") | K31: 10500 | L31: 10500 | M31: =IF(AND(ISNUMBER(K31),ISNUMBER(L31),K31>0),1-L31/K31,"") | N31: 0 | R31: =IF(AND(ISNUMBER(L31),ISNUMBER(P31),ISNUMBER(Q31)),L31/((P31+Q31)/2)-1,"") | T31: 85000 | U31: 1998 | V31: 08/1998 | W31: Essence | X31: Manuelle | Y31: 115 | Z31: 7 | AA31: Noir | AB31: 2 | AC31: Cabriolet | AF31: Particulier | AG31: Dolmayrac | AH31: 47110 | AI31: Lot-et-Garonne | AJ31: Aquitaine | AK31: 3 | AM31: Non | AN31: BMW Z3 cabriolet 1998 85000 klm très bon état | AO31: vehicle_technical_inspection_valid : Non ; Dommages : Bon état général ; Sellerie : Tout cuir ; Permis : Avec permis ; Importé : false | AP31: Voir | AQ31: 3283519181
A32: BMW Z3 1.9i / 2.0i | B32: Bmw Z3 E36 Luxe 1.9 118ch Phase 2 | C32: Z3 Roadster 1.9i 118ch | D32: Base | E32: En vente | F32: 46302 | G32: 46302 | H32: 46310 | J32: =IF(OR(ISNUMBER(F32),ISNUMBER(G32)),IF(ISNUMBER(I32),I32,H32)-IF(ISNUMBER(F32),F32,G32),"") | K32: 9990 | L32: 9990 | M32: =IF(AND(ISNUMBER(K32),ISNUMBER(L32),K32>0),1-L32/K32,"") | N32: 0 | R32: =IF(AND(ISNUMBER(L32),ISNUMBER(P32),ISNUMBER(Q32)),L32/((P32+Q32)/2)-1,"") | T32: 180000 | U32: 2001 | V32: 06/2001 | W32: Essence | X32: Manuelle | Y32: 118 | Z32: 8 | AA32: Gris | AB32: 2 | AC32: Cabriolet | AF32: Pro | AG32: Reims | AH32: 51100 | AI32: Marne | AJ32: Champagne-Ardenne | AK32: 40 | AL32: Oui | AM32: Non | AN32: L'Agence TransakAuto REIMS, société spécialisée en courtage automobile, 1er réseau d'intermédiation automobile auprès des particuliers avec + de 180 agences en France depuis 2011, vous propose ce véhicule Bmw, Z3, Gris, 8 chevaux fiscaux, 2 portes, 180 000 km. ⚠ 🔦 Véhicule visible uniquement sur rdv à l'agence TransakAuto REIMS, du mardi au samedi de 10h à 18h Véhicule en dépôt-vente [non stocké sur place]. Visible uniquement sur rendez-vous dans votre agence après avoir appelé le commercial po | AO32: Équipements intérieurs : Climatisation, Essuie-glaces automatiques, Sièges sport ; VO récent : false ; custom_ref : VO73669779 ; Importé : true ; vehicle_history_report_status : visible ; spare_parts_availability : Non renseignée | AP32: Voir | AQ32: 3283890361
A33: BMW Z3 1.9i / 2.0i | B33: Bmw z3 | E33: En vente | F33: 46306 | G33: 46306 | H33: 46310 | J33: =IF(OR(ISNUMBER(F33),ISNUMBER(G33)),IF(ISNUMBER(I33),I33,H33)-IF(ISNUMBER(F33),F33,G33),"") | K33: 8900 | L33: 8900 | M33: =IF(AND(ISNUMBER(K33),ISNUMBER(L33),K33>0),1-L33/K33,"") | N33: 0 | R33: =IF(AND(ISNUMBER(L33),ISNUMBER(P33),ISNUMBER(Q33)),L33/((P33+Q33)/2)-1,"") | T33: 207000 | U33: 1996 | V33: 08/1996 | W33: Essence | X33: Manuelle | Y33: 140 | Z33: 9 | AA33: Autre | AB33: 2 | AC33: Cabriolet | AF33: Particulier | AG33: Flassans-sur-Issole | AH33: 83340 | AI33: Var | AJ33: Provence-Alpes-Côte d'Azur | AK33: 3 | AM33: Non | AN33: BMW Z3 Roadster 1.9 140 ch 1996 très bon état roule tous les jours quelques options comme vitre électrique, siège électrique, intérieur Cuir rouge rétroviseur électrique, la couleur est bleu et des reflets violets au soleil pas mal de frais ont été fait dessus : - capote en alpaga noir ( 2200 €) - 4 pneus 225/50zr16 neuf - soufflé de cardan - plaquette de frein arrière - demarreur - visco coupleur - thermostat d'eau - demi-ligne d'échappement inox cobra sport Elle a 207000 km le contrôle techniq | AO33: Permis : Avec permis ; Importé : false | AP33: Voir | AQ33: 3286480975
A34: BMW Z3 1.9i / 2.0i | B34: Bmw z3 | E34: En vente | F34: 46306 | G34: 46306 | H34: 46310 | J34: =IF(OR(ISNUMBER(F34),ISNUMBER(G34)),IF(ISNUMBER(I34),I34,H34)-IF(ISNUMBER(F34),F34,G34),"") | K34: 15000 | L34: 15000 | M34: =IF(AND(ISNUMBER(K34),ISNUMBER(L34),K34>0),1-L34/K34,"") | N34: 0 | R34: =IF(AND(ISNUMBER(L34),ISNUMBER(P34),ISNUMBER(Q34)),L34/((P34+Q34)/2)-1,"") | T34: 187000 | U34: 1997 | V34: 12/1997 | W34: Essence | X34: Manuelle | Y34: 115 | Z34: 9 | AA34: Autre | AB34: 2 | AC34: Cabriolet | AF34: Particulier | AG34: Jard-sur-Mer | AH34: 85520 | AI34: Vendée | AJ34: Pays de la Loire | AK34: 3 | AM34: Non | AN34: BMW Z3 en bonne état controle technique ok effectuer le 17/06/2026 contacter moi pour plus d'information le véhicule est visible a Jard sur mer ou Luçon. | AO34: vehicle_technical_inspection_valid : Non ; Dommages : Bon état général ; Permis : Avec permis ; Importé : false | AP34: Voir | AQ34: 3286625426
A35: BMW Z3 1.9i / 2.0i | B35: BMW z3 | E35: En vente | F35: 46307 | G35: 46307 | H35: 46310 | J35: =IF(OR(ISNUMBER(F35),ISNUMBER(G35)),IF(ISNUMBER(I35),I35,H35)-IF(ISNUMBER(F35),F35,G35),"") | K35: 7800 | L35: 7800 | M35: =IF(AND(ISNUMBER(K35),ISNUMBER(L35),K35>0),1-L35/K35,"") | N35: 0 | R35: =IF(AND(ISNUMBER(L35),ISNUMBER(P35),ISNUMBER(Q35)),L35/((P35+Q35)/2)-1,"") | T35: 148000 | U35: 1998 | V35: 02/1998 | W35: Essence | X35: Manuelle | Y35: 115 | Z35: 7 | AA35: Noir | AB35: 2 | AC35: Cabriolet | AD35: Véhicule non fumeur, Réparations utiles déjà faites, Factures disponibles | AF35: Particulier | AG35: Saint-Gingolph | AH35: 74500 | AI35: Haute-Savoie | AJ35: Rhône-Alpes | AK35: 3 | AM35: Non | AN35: Bonjour, Je mets en vente ma BMW Z3 que j’ai depuis plus d’un an. CT OK Option: - sièges électriques en cuire chauffant. - jantes m homologué pour la 1.8 (1560€) La voiture est en très bon état mécanique avec tout les entretiens fait dans les temps et plusieurs frais effectués comme: - radiateur haute performance installé (147500 km) - thermostat système de refroidissement neuf (147500km) - circuit de filtrage d’huile changé (141000km) - plaquettes de freins (141000km) - 4 pneu (140000km) - vida | AO35: Dommages : Bon état général ; Sellerie : Tout cuir ; Équipements intérieurs : Chargeurs USB, Jantes en alliage, Phares anti-brouillard, Sièges chauffants, Sièges en cuir, Sièges sport, Sièges électriques, Toit ouvrant / Toit panoramique ; Permis : Avec permis ; Importé : false | AP35: Voir | AQ35: 3287385983
A36: BMW Z3 1.9i / 2.0i | B36: BMW Z3 1.9i 140ch Pack M Sport tbé Cuir Clim | E36: En vente | F36: 46112 | G36: 46112 | H36: 46296 | J36: =IF(OR(ISNUMBER(F36),ISNUMBER(G36)),IF(ISNUMBER(I36),I36,H36)-IF(ISNUMBER(F36),F36,G36),"") | K36: 8990 | L36: 8990 | M36: =IF(AND(ISNUMBER(K36),ISNUMBER(L36),K36>0),1-L36/K36,"") | N36: 0 | R36: =IF(AND(ISNUMBER(L36),ISNUMBER(P36),ISNUMBER(Q36)),L36/((P36+Q36)/2)-1,"") | T36: 186000 | U36: 1998 | W36: Essence | X36: Manuelle | Y36: 140 | AA36: Noir | AB36: 3 | AC36: Cabriolet | AF36: Pro | AG36: Jury | AH36: 57245 | AI36: Moselle | AJ36: Lorraine | AL36: Oui | AP36: Voir | AQ36: 3171562700
A37: BMW Z3 1.9i / 2.0i | B37: Bmw z3 1.8 roadster GARANTIE | E37: En vente | F37: 46281 | G37: 46281 | H37: 46296 | J37: =IF(OR(ISNUMBER(F37),ISNUMBER(G37)),IF(ISNUMBER(I37),I37,H37)-IF(ISNUMBER(F37),F37,G37),"") | K37: 11490 | L37: 11490 | M37: =IF(AND(ISNUMBER(K37),ISNUMBER(L37),K37>0),1-L37/K37,"") | N37: 0 | R37: =IF(AND(ISNUMBER(L37),ISNUMBER(P37),ISNUMBER(Q37)),L37/((P37+Q37)/2)-1,"") | T37: 119627 | U37: 1997 | W37: Essence | X37: Manuelle | Y37: 115 | Z37: 7 | AA37: Gris | AB37: 2 | AC37: Cabriolet | AF37: Pro | AG37: Montélimar | AH37: 26200 | AI37: Drôme | AJ37: Rhône-Alpes | AL37: Oui | AP37: Voir | AQ37: 3197947364
A38: BMW Z3 1.9i / 2.0i | B38: BMW Z3 1.9 140cv | E38: En vente | F38: 46244 | G38: 46244 | H38: 46296 | J38: =IF(OR(ISNUMBER(F38),ISNUMBER(G38)),IF(ISNUMBER(I38),I38,H38)-IF(ISNUMBER(F38),F38,G38),"") | K38: 9990 | L38: 9990 | M38: =IF(AND(ISNUMBER(K38),ISNUMBER(L38),K38>0),1-L38/K38,"") | N38: 0 | R38: =IF(AND(ISNUMBER(L38),ISNUMBER(P38),ISNUMBER(Q38)),L38/((P38+Q38)/2)-1,"") | T38: 154000 | U38: 1997 | W38: Essence | X38: Manuelle | Y38: 140 | Z38: 10 | AA38: Gris | AB38: 2 | AC38: Autre | AF38: Pro | AG38: La Roche-sur-Yon | AH38: 85000 | AI38: Vendée | AJ38: Pays de la Loire | AL38: Oui | AP38: Voir | AQ38: 3217262918
A39: BMW Z3 1.9i / 2.0i | B39: BMW Z3 cabriolet 2.2 170 ch 6 cylindres 84700 km | E39: En vente | F39: 46254 | G39: 46254 | H39: 46296 | J39: =IF(OR(ISNUMBER(F39),ISNUMBER(G39)),IF(ISNUMBER(I39),I39,H39)-IF(ISNUMBER(F39),F39,G39),"") | K39: 17900 | L39: 17900 | M39: =IF(AND(ISNUMBER(K39),ISNUMBER(L39),K39>0),1-L39/K39,"") | N39: 0 | R39: =IF(AND(ISNUMBER(L39),ISNUMBER(P39),ISNUMBER(Q39)),L39/((P39+Q39)/2)-1,"") | T39: 84700 | U39: 2002 | W39: Essence | X39: Manuelle | Y39: 170 | Z39: 11 | AA39: Argent | AB39: 2 | AC39: Cabriolet | AF39: Particulier | AG39: Yerres | AH39: 91330 | AI39: Essonne | AJ39: Ile-de-France | AL39: Oui | AP39: Voir | AQ39: 3220328214
A40: BMW Z3 1.9i / 2.0i | B40: Bmw Z3 ROADSTER (E36) 2.0 150CH | E40: En vente | F40: 46270 | G40: 46270 | H40: 46296 | J40: =IF(OR(ISNUMBER(F40),ISNUMBER(G40)),IF(ISNUMBER(I40),I40,H40)-IF(ISNUMBER(F40),F40,G40),"") | K40: 15990 | L40: 15990 | M40: =IF(AND(ISNUMBER(K40),ISNUMBER(L40),K40>0),1-L40/K40,"") | N40: 0 | R40: =IF(AND(ISNUMBER(L40),ISNUMBER(P40),ISNUMBER(Q40)),L40/((P40+Q40)/2)-1,"") | T40: 122000 | U40: 2002 | W40: Essence | X40: Manuelle | Y40: 150 | Z40: 10 | AA40: Bleu | AB40: 3 | AC40: Cabriolet | AF40: Pro | AG40: Melesse | AH40: 35520 | AI40: Ille-et-Vilaine | AJ40: Bretagne | AL40: Oui | AP40: Voir | AQ40: 3230964764
A41: BMW Z3 1.9i / 2.0i | B41: BMW Z3 Roadster 1.9i ROADSTER E36 Roadster BVM - GARANTIE 12 MOIS | E41: En vente | F41: 46240 | G41: 46240 | H41: 46296 | J41: =IF(OR(ISNUMBER(F41),ISNUMBER(G41)),IF(ISNUMBER(I41),I41,H41)-IF(ISNUMBER(F41),F41,G41),"") | K41: 10990 | L41: 10990 | M41: =IF(AND(ISNUMBER(K41),ISNUMBER(L41),K41>0),1-L41/K41,"") | N41: 0 | R41: =IF(AND(ISNUMBER(L41),ISNUMBER(P41),ISNUMBER(Q41)),L41/((P41+Q41)/2)-1,"") | T41: 171000 | U41: 2001 | W41: Essence | X41: Manuelle | Y41: 116 | AA41: Argent | AB41: 3 | AC41: Cabriolet | AF41: Pro | AG41: Montussan | AH41: 33450 | AI41: Gironde | AJ41: Aquitaine | AL41: Oui | AP41: Voir | AQ41: 3245635449
A42: BMW Z3 1.9i / 2.0i | B42: BMW Z3 Roadster 1.9i 118ch Garantie 6 Mois | E42: En vente | F42: 46246 | G42: 46246 | H42: 46296 | J42: =IF(OR(ISNUMBER(F42),ISNUMBER(G42)),IF(ISNUMBER(I42),I42,H42)-IF(ISNUMBER(F42),F42,G42),"") | K42: 9990 | L42: 9990 | M42: =IF(AND(ISNUMBER(K42),ISNUMBER(L42),K42>0),1-L42/K42,"") | N42: 0 | R42: =IF(AND(ISNUMBER(L42),ISNUMBER(P42),ISNUMBER(Q42)),L42/((P42+Q42)/2)-1,"") | T42: 195944 | U42: 2000 | W42: Essence | X42: Manuelle | Y42: 118 | Z42: 8 | AA42: Gris | AB42: 2 | AC42: Cabriolet | AF42: Pro | AG42: Herrlisheim-près-Colmar | AH42: 68420 | AI42: Haut-Rhin | AJ42: Alsace | AL42: Oui | AP42: Voir | AQ42: 3249081293
A43: BMW Z3 1.9i / 2.0i | B43: Bmw z3 1.9 i | E43: En vente | F43: 46247 | G43: 46247 | H43: 46296 | J43: =IF(OR(ISNUMBER(F43),ISNUMBER(G43)),IF(ISNUMBER(I43),I43,H43)-IF(ISNUMBER(F43),F43,G43),"") | K43: 9500 | L43: 9500 | M43: =IF(AND(ISNUMBER(K43),ISNUMBER(L43),K43>0),1-L43/K43,"") | N43: 0 | R43: =IF(AND(ISNUMBER(L43),ISNUMBER(P43),ISNUMBER(Q43)),L43/((P43+Q43)/2)-1,"") | T43: 128482 | U43: 1999 | W43: Essence | X43: Manuelle | AF43: Pro | AG43: Andilly | AH43: 17230 | AI43: Charente-Maritime | AJ43: Poitou-Charentes | AL43: Oui | AP43: Voir | AQ43: 3249519594
A44: BMW Z3 1.9i / 2.0i | B44: Bmw z3 roadster 1.9 118 cv - 85 500 km - 13 900.00 | E44: En vente | F44: 46259 | G44: 46259 | H44: 46296 | J44: =IF(OR(ISNUMBER(F44),ISNUMBER(G44)),IF(ISNUMBER(I44),I44,H44)-IF(ISNUMBER(F44),F44,G44),"") | K44: 13900 | L44: 13900 | M44: =IF(AND(ISNUMBER(K44),ISNUMBER(L44),K44>0),1-L44/K44,"") | N44: 0 | R44: =IF(AND(ISNUMBER(L44),ISNUMBER(P44),ISNUMBER(Q44)),L44/((P44+Q44)/2)-1,"") | T44: 85500 | U44: 2002 | W44: Essence | X44: Manuelle | Y44: 118 | Z44: 8 | AA44: Bleu | AB44: 2 | AC44: Cabriolet | AF44: Pro | AG44: Chambray-lès-Tours | AH44: 37170 | AI44: Indre-et-Loire | AJ44: Centre | AL44: Oui | AP44: Voir | AQ44: 3256683007
A45: BMW Z3 1.9i / 2.0i | B45: BMW Z3 Z3 1.9i ORIGINE FRANCE | E45: En vente | F45: 46262 | G45: 46262 | H45: 46296 | J45: =IF(OR(ISNUMBER(F45),ISNUMBER(G45)),IF(ISNUMBER(I45),I45,H45)-IF(ISNUMBER(F45),F45,G45),"") | K45: 10990 | L45: 10990 | M45: =IF(AND(ISNUMBER(K45),ISNUMBER(L45),K45>0),1-L45/K45,"") | N45: 0 | R45: =IF(AND(ISNUMBER(L45),ISNUMBER(P45),ISNUMBER(Q45)),L45/((P45+Q45)/2)-1,"") | T45: 114150 | U45: 2001 | W45: Essence | X45: Manuelle | Y45: 116 | Z45: 8 | AA45: Gris | AB45: 2 | AF45: Pro | AG45: Distré | AH45: 49400 | AI45: Maine-et-Loire | AJ45: Pays de la Loire | AL45: Oui | AP45: Voir | AQ45: 3258200097
A46: BMW Z3 1.9i / 2.0i | B46: Bmw Z3 1,8 L 115 CV PACK M + 2 EME MAIN | E46: En vente | F46: 46262 | G46: 46262 | H46: 46296 | J46: =IF(OR(ISNUMBER(F46),ISNUMBER(G46)),IF(ISNUMBER(I46),I46,H46)-IF(ISNUMBER(F46),F46,G46),"") | K46: 11990 | L46: 11990 | M46: =IF(AND(ISNUMBER(K46),ISNUMBER(L46),K46>0),1-L46/K46,"") | N46: 0 | R46: =IF(AND(ISNUMBER(L46),ISNUMBER(P46),ISNUMBER(Q46)),L46/((P46+Q46)/2)-1,"") | T46: 47300 | U46: 1999 | W46: Essence | X46: Manuelle | Y46: 116 | Z46: 7 | AA46: Bleu | AB46: 3 | AC46: Cabriolet | AF46: Pro | AG46: Pibrac | AH46: 31820 | AI46: Haute-Garonne | AJ46: Midi-Pyrénées | AL46: Oui | AP46: Voir | AQ46: 3258446503
A47: BMW Z3 1.9i / 2.0i | B47: Bmw Z3 2.0 150 ch 6 cylindres cabriolet | E47: En vente | F47: 46265 | G47: 46265 | H47: 46296 | J47: =IF(OR(ISNUMBER(F47),ISNUMBER(G47)),IF(ISNUMBER(I47),I47,H47)-IF(ISNUMBER(F47),F47,G47),"") | K47: 7490 | L47: 7490 | M47: =IF(AND(ISNUMBER(K47),ISNUMBER(L47),K47>0),1-L47/K47,"") | N47: 0 | R47: =IF(AND(ISNUMBER(L47),ISNUMBER(P47),ISNUMBER(Q47)),L47/((P47+Q47)/2)-1,"") | T47: 231500 | U47: 2000 | W47: Essence | X47: Manuelle | Y47: 150 | Z47: 10 | AA47: Noir | AB47: 2 | AC47: Cabriolet | AF47: Particulier | AG47: Saint-Étienne | AH47: 42100 | AI47: Loire | AJ47: Rhône-Alpes | AL47: Oui | AP47: Voir | AQ47: 3258548235
A48: BMW Z3 1.9i / 2.0i | B48: Bmw z3 roadster 1.9 i 140 | E48: En vente | F48: 46281 | G48: 46281 | H48: 46296 | J48: =IF(OR(ISNUMBER(F48),ISNUMBER(G48)),IF(ISNUMBER(I48),I48,H48)-IF(ISNUMBER(F48),F48,G48),"") | K48: 12990 | L48: 12990 | M48: =IF(AND(ISNUMBER(K48),ISNUMBER(L48),K48>0),1-L48/K48,"") | N48: 0 | R48: =IF(AND(ISNUMBER(L48),ISNUMBER(P48),ISNUMBER(Q48)),L48/((P48+Q48)/2)-1,"") | T48: 90000 | U48: 1998 | W48: Essence | X48: Manuelle | Y48: 140 | Z48: 10 | AA48: Gris | AB48: 2 | AC48: Cabriolet | AF48: Pro | AG48: Compiègne | AH48: 60200 | AI48: Oise | AJ48: Picardie | AL48: Oui | AP48: Voir | AQ48: 3271074708
A49: BMW Z3 1.9i / 2.0i | B49: Bmw Z3 1.8 116cv *Moteur 175000Km + factures BMW | E49: En vente | F49: 46284 | G49: 46284 | H49: 46296 | J49: =IF(OR(ISNUMBER(F49),ISNUMBER(G49)),IF(ISNUMBER(I49),I49,H49)-IF(ISNUMBER(F49),F49,G49),"") | K49: 11490 | L49: 11490 | M49: =IF(AND(ISNUMBER(K49),ISNUMBER(L49),K49>0),1-L49/K49,"") | N49: 0 | R49: =IF(AND(ISNUMBER(L49),ISNUMBER(P49),ISNUMBER(Q49)),L49/((P49+Q49)/2)-1,"") | T49: 295000 | U49: 1996 | W49: Essence | X49: Manuelle | Y49: 116 | Z49: 9 | AA49: Rouge | AB49: 2 | AF49: Pro | AG49: Loupiac-de-la-Réole | AH49: 33190 | AI49: Gironde | AJ49: Aquitaine | AL49: Oui | AP49: Voir | AQ49: 3272577206
A50: Citroën Saxo VTS 16V | B50: Citroen saxo vts | E50: En vente | F50: 46284 | G50: 46284 | H50: 46310 | J50: =IF(OR(ISNUMBER(F50),ISNUMBER(G50)),IF(ISNUMBER(I50),I50,H50)-IF(ISNUMBER(F50),F50,G50),"") | K50: 5500 | L50: 5500 | M50: =IF(AND(ISNUMBER(K50),ISNUMBER(L50),K50>0),1-L50/K50,"") | N50: 0 | R50: =IF(AND(ISNUMBER(L50),ISNUMBER(P50),ISNUMBER(Q50)),L50/((P50+Q50)/2)-1,"") | T50: 261273 | U50: 1998 | V50: 08/1998 | W50: Essence | X50: Manuelle | Y50: 90 | Z50: 6 | AA50: Noir | AB50: 3 | AC50: Citadine | AF50: Particulier | AG50: Sully-sur-Loire | AH50: 45600 | AI50: Loiret | AJ50: Centre | AK50: 3 | AM50: Non | AN50: Bonjour, je vends ma petite Saxo, entièrement restaurée et repeinte il y a 8 mois, avec des éléments de peinture personnalisée. De nombreuses pièces ont été remplacées : kit de distribution, courroie d'accessoires, radiateur d'eau, 4 disques Brembo Sport Max neufs avec plaquettes neuves, câbles et flexibles de frein à main neufs, 245 000 km pont arrière, avec roulements neufs et rabaissement d'environ 30 mm, catalyseur et silencieux neufs, ressorts rouges et amortisseurs KYB neufs. Alternateur r | AO50: Dommages : Bon état général ; Sellerie : Tissu ; vehicle_euro_emissions_standard : Euro 2 ; Permis : Avec permis ; Importé : false | AP50: Voir | AQ50: 3122468671
A51: Citroën Saxo VTS 16V | B51: Saxo vts / 85000 km / a restaurer | C51: Saxo 1.4 VTS 3p | D51: VTS | E51: En vente | F51: 46302 | G51: 46302 | H51: 46310 | J51: =IF(OR(ISNUMBER(F51),ISNUMBER(G51)),IF(ISNUMBER(I51),I51,H51)-IF(ISNUMBER(F51),F51,G51),"") | K51: 4500 | L51: 4500 | M51: =IF(AND(ISNUMBER(K51),ISNUMBER(L51),K51>0),1-L51/K51,"") | N51: 0 | O51: 5000 | R51: =IF(AND(ISNUMBER(L51),ISNUMBER(P51),ISNUMBER(Q51)),L51/((P51+Q51)/2)-1,"") | T51: 85000 | U51: 1999 | V51: 07/1999 | W51: Essence | X51: Manuelle | Y51: 75 | Z51: 5 | AA51: Noir | AB51: 3 | AC51: Berline | AF51: Pro | AG51: Taissy | AH51: 51500 | AI51: Marne | AJ51: Champagne-Ardenne | AK51: 5 | AM51: Non | AN51: Saxo VTS 1l4 essence 75 (55 kw / 5 cv) 2eme main 13/07/1999 Vendu chez nous avec 76000 km en 2023 en 1ere main Kit distribution, vidange filtre à huile et kit frein arrière effectués A restaurer : bas de caisse, corrosion perforante VENDU DANS L'ETAT, AVEC CONTRE VISITE CT ATTENTION UNIQUEMENT SUR RDV PAR TELEPHONE Tous nos véhicules sont visibles sur la boutique en haut en droite interieur velours silencieux inox direction assistée air bag vitres electriques centralisation à distance TRES PROPR | AO51: vehicle_technical_inspection_valid : Non ; Sellerie : Velours ; Permis : Avec permis ; Vente en LOA/LLD : Non ; VO récent : false ; vehicle_commercial_warranty : Non ; vehicle_manufacturer_warranty : Non ; Importé : false ; vehicle_history_report_status : visible ; spare_parts_availability : Non renseignée | AP51: Voir | AQ51: 3177027931
A52: Citroën Saxo VTS 16V | B52: Citroen Saxo VTS 16v | C52: Saxo 1.6 16V 120ch VTS 3p | D52: VTS | E52: En vente | F52: 46306 | G52: 46245 | H52: 46310 | J52: =IF(OR(ISNUMBER(F52),ISNUMBER(G52)),IF(ISNUMBER(I52),I52,H52)-IF(ISNUMBER(F52),F52,G52),"") | K52: 7500 | L52: 7000 | M52: =IF(AND(ISNUMBER(K52),ISNUMBER(L52),K52>0),1-L52/K52,"") | N52: 1 | O52: 9500 | R52: =IF(AND(ISNUMBER(L52),ISNUMBER(P52),ISNUMBER(Q52)),L52/((P52+Q52)/2)-1,"") | T52: 200000 | U52: 2000 | V52: 04/2000 | W52: Essence | X52: Manuelle | Y52: 118 | Z52: 8 | AA52: Gris | AB52: 3 | AC52: Berline | AF52: Particulier | AG52: Sisteron | AH52: 04200 | AI52: Alpes-de-Haute-Provence | AJ52: Provence-Alpes-Côte d'Azur | AK52: 7 | AM52: Non | AN52: Bonjour, Je vends ma Citroën Saxo VTS 16v 120ch, phase 2 de 2000 avec 200 000 km au compteur, tres peu evolutif. En ma possession depuis 2015. Toute d’origine, sauf : 4 jantes OZ Racing blanches en 15 pouces. Interieur full cuir noir, siege conducteur décousu (voir photo). Collecteur 4/2/1 momifié (origine dispo) Elle vient de sortir du garage d’une renovation mécanique complète, entre autres : - Distribution - Entretien complet (filtre a air, essence, huile, bougies etc…) - Disques et plaquette | AO52: Dommages : Bon état général ; Sellerie : Tout cuir ; Permis : Avec permis ; Importé : false | AP52: Voir | AQ52: 3179205726
A53: Citroën Saxo VTS 16V | B53: Saxo vts 1.6 90cv | E53: En vente | F53: 46274 | G53: 46274 | H53: 46310 | J53: =IF(OR(ISNUMBER(F53),ISNUMBER(G53)),IF(ISNUMBER(I53),I53,H53)-IF(ISNUMBER(F53),F53,G53),"") | K53: 5500 | L53: 4800 | M53: =IF(AND(ISNUMBER(K53),ISNUMBER(L53),K53>0),1-L53/K53,"") | N53: 1 | O53: 6500 | R53: =IF(AND(ISNUMBER(L53),ISNUMBER(P53),ISNUMBER(Q53)),L53/((P53+Q53)/2)-1,"") | T53: 190000 | U53: 2000 | V53: 07/2000 | W53: Essence | X53: Manuelle | Y53: 88 | Z53: 6 | AA53: Rouge | AB53: 3 | AC53: Berline | AF53: Particulier | AG53: Creutzwald | AH53: 57150 | AI53: Moselle | AJ53: Lorraine | AK53: 3 | AL53: Oui | AM53: Non | AN53: Je vends ma saxo vts, 3ème main, sans clim, le c.t sera passé pour la vente. Admission dynamique, decata, la vidange vient d'être effectuée, bougies + bobine neuve, batterie neuve, donne admission d'origine, catalyseur, volant tulipé alcantara, silencieux inox + 5ème roue jante toulouse. Traitement anti corrosion. Visible = disponible. Plus de renseignements, uniquement par téléphone ou sms (appel de préférence). Pas d'échanges, sauf golf 4 ou 5 tdi en bonne état + rajout de votre part. 4800€ à | AO53: Dommages : Bon état général ; Sellerie : Velours ; Permis : Avec permis ; Importé : false | AP53: Voir | AQ53: 3179893341
A54: Citroën Saxo VTS 16V | B54: Saxo vts 1.6l 16s | C54: VTS_Saxo 1.6 16v VTS 3p | D54: VTS | E54: En vente | F54: 46271 | G54: 46271 | H54: 46310 | J54: =IF(OR(ISNUMBER(F54),ISNUMBER(G54)),IF(ISNUMBER(I54),I54,H54)-IF(ISNUMBER(F54),F54,G54),"") | K54: 5000 | L54: 5000 | M54: =IF(AND(ISNUMBER(K54),ISNUMBER(L54),K54>0),1-L54/K54,"") | N54: 0 | R54: =IF(AND(ISNUMBER(L54),ISNUMBER(P54),ISNUMBER(Q54)),L54/((P54+Q54)/2)-1,"") | T54: 95000 | U54: 2003 | V54: 02/2003 | W54: Essence | X54: Manuelle | Y54: 120 | Z54: 8 | AA54: Autre | AB54: 3 | AC54: Berline | AF54: Particulier | AG54: Longwy | AH54: 54400 | AI54: Meurthe-et-Moselle | AJ54: Lorraine | AK54: 3 | AM54: Non | AN54: Saxo piste 1.6l 16v 120cv Usages circuit uniquement 95000klm Livraison possible Carte grise à mon nom Avec de nombreuses pièces Stoker depuis plusieurs années au garage ,pas pressé de la vendre , les photos dates de plusieurs années Clim et abs supprimés Quasiment vidée Amortisseur Bisteim B6 Motorsport Barre anti rapprochement supérieur Silent bloc power flex sur barre stab et triangle Étriers avant 4 piston brembo de 406v6 avec disque de c5 hdi et plaquette carbone Maître cylindres de 406v6 Du | AO54: Permis : Avec permis ; Importé : false | AP54: Voir | AQ54: 3229777091
A55: Citroën Saxo VTS 16V | B55: Saxo vts 1l4 echange possible | C55: VTS_Saxo 1.4 VTS 3p | D55: VTS | E55: En vente | F55: 46278 | G55: 46278 | H55: 46310 | J55: =IF(OR(ISNUMBER(F55),ISNUMBER(G55)),IF(ISNUMBER(I55),I55,H55)-IF(ISNUMBER(F55),F55,G55),"") | K55: 4500 | L55: 4500 | M55: =IF(AND(ISNUMBER(K55),ISNUMBER(L55),K55>0),1-L55/K55,"") | N55: 0 | O55: 5000 | R55: =IF(AND(ISNUMBER(L55),ISNUMBER(P55),ISNUMBER(Q55)),L55/((P55+Q55)/2)-1,"") | T55: 181000 | U55: 2000 | V55: 05/2000 | W55: Essence | X55: Manuelle | Y55: 75 | Z55: 5 | AA55: Autre | AB55: 3 | AC55: Berline | AF55: Particulier | AG55: La Bastide | AH55: 83840 | AI55: Var | AJ55: Provence-Alpes-Côte d'Azur | AK55: 3 | AM55: Non | AN55: Saxo vts 1l4 echange possible, Beaucoup de piece neuve prête a rouler pour plus d'informations contacté moi | AO55: Permis : Avec permis ; Importé : false | AP55: Voir | AQ55: 3233589487
A56: Citroën Saxo VTS 16V | B56: Saxo vts 1l6 16s | E56: En vente | F56: 46303 | G56: 46303 | H56: 46310 | J56: =IF(OR(ISNUMBER(F56),ISNUMBER(G56)),IF(ISNUMBER(I56),I56,H56)-IF(ISNUMBER(F56),F56,G56),"") | K56: 5900 | L56: 5900 | M56: =IF(AND(ISNUMBER(K56),ISNUMBER(L56),K56>0),1-L56/K56,"") | N56: 0 | R56: =IF(AND(ISNUMBER(L56),ISNUMBER(P56),ISNUMBER(Q56)),L56/((P56+Q56)/2)-1,"") | T56: 197000 | U56: 2002 | V56: 06/2002 | W56: Essence | X56: Manuelle | Y56: 120 | Z56: 8 | AA56: Noir | AB56: 3 | AC56: Berline | AF56: Particulier | AG56: Héricourt | AH56: 70400 | AI56: Haute-Saône | AJ56: Franche-Comté | AK56: 3 | AM56: Non | AN56: Saxo vts démarre roule nombreux frais réalisés : Batterie Distri pompe à eau Bobine bougie Pompe à essence Pneus neuf etc… c’est une sortie de grange j’ai fait le nécessaire pour qu’elle passe le ct je préviens c’est pour un gars qui s’y connaît y’a encore du travail pour qu’elle soit super mais roule bien contrôle technique à jour carte grise à jour Oui elle a connu la rouille , oui cela a été traité et blaxonné oui c’est pas parfait. C’est pour ça que le prix est divisé par deux par rapport au | AO56: Permis : Avec permis ; Importé : false | AP56: Voir | AQ56: 3247144718
A57: Citroën Saxo VTS 16V | B57: Saxo VTS 16S | C57: VTS_Saxo 1.6 16V 120ch VTS 3p | D57: VTS | E57: En vente | F57: 46263 | G57: 46263 | H57: 46310 | J57: =IF(OR(ISNUMBER(F57),ISNUMBER(G57)),IF(ISNUMBER(I57),I57,H57)-IF(ISNUMBER(F57),F57,G57),"") | K57: 5000 | L57: 5000 | M57: =IF(AND(ISNUMBER(K57),ISNUMBER(L57),K57>0),1-L57/K57,"") | N57: 0 | R57: =IF(AND(ISNUMBER(L57),ISNUMBER(P57),ISNUMBER(Q57)),L57/((P57+Q57)/2)-1,"") | T57: 159000 | U57: 1999 | V57: 12/1999 | W57: Essence | X57: Manuelle | Y57: 118 | Z57: 8 | AA57: Rouge | AB57: 3 | AC57: Berline | AF57: Particulier | AG57: Château-Thierry | AH57: 02400 | AI57: Aisne | AJ57: Picardie | AK57: 3 | AM57: Non | AN57: Bonjour, Je vends ma Citroën Saxo VTS 16V de 1999. Carte grise ok. La voiture a été vidée par moi même, je ne possède plus les pièces. La voiture est en ma possession depuis plus de 10 ans. Immobiliser plusieurs années en box. Actuellement dans ma cour en extérieur depuis environ 6 mois. La voiture roule bien et le moteur démarre bien lors de la sortie de box (roulage de environ 150km). Frais à prévoir : - Révision complète + distribution (une vidange moteur a été faite pour la sortie de box). - | AO57: vehicle_technical_inspection_valid : Oui ; Contrôle technique : 2027 ; Permis : Avec permis ; Importé : false | AP57: Voir | AQ57: 3259234628
A58: Citroën Saxo VTS 16V | B58: Saxo Vts 1.6 8s | E58: En vente | F58: 46265 | G58: 46265 | H58: 46310 | J58: =IF(OR(ISNUMBER(F58),ISNUMBER(G58)),IF(ISNUMBER(I58),I58,H58)-IF(ISNUMBER(F58),F58,G58),"") | K58: 6000 | L58: 6000 | M58: =IF(AND(ISNUMBER(K58),ISNUMBER(L58),K58>0),1-L58/K58,"") | N58: 0 | R58: =IF(AND(ISNUMBER(L58),ISNUMBER(P58),ISNUMBER(Q58)),L58/((P58+Q58)/2)-1,"") | T58: 229523 | U58: 2002 | V58: 06/2002 | W58: Essence | X58: Manuelle | Y58: 100 | Z58: 6 | AA58: Autre | AB58: 3 | AC58: Berline | AF58: Particulier | AG58: Privas | AH58: 07000 | AI58: Ardèche | AJ58: Rhône-Alpes | AK58: 3 | AM58: Non | AN58: Je vends ma Citroën Saxo VTS 1.6 8V de 2002, une citadine dynamique et fiable. - Marque : Citroën - Modèle : Saxo - Année : 2002 - Kilométrage : 229 523 km - Motorisation : 1.6 8V 100 ch - Carburant : Essence - Boîte de vitesses : Manuelle - Type : Berline - Nombre de portes : 3 - Puissance fiscale : 6 Cv - Couleur : Gris N'hésitez pas à me contacter pour plus d'informations ou pour organiser un essai. | AO58: Permis : Avec permis ; Importé : false | AP58: Voir | AQ58: 3260316059
A59: Citroën Saxo VTS 16V | B59: Saxo vts 120ch | E59: En vente | F59: 46265 | G59: 46265 | H59: 46310 | J59: =IF(OR(ISNUMBER(F59),ISNUMBER(G59)),IF(ISNUMBER(I59),I59,H59)-IF(ISNUMBER(F59),F59,G59),"") | K59: 9990 | L59: 9990 | M59: =IF(AND(ISNUMBER(K59),ISNUMBER(L59),K59>0),1-L59/K59,"") | N59: 0 | R59: =IF(AND(ISNUMBER(L59),ISNUMBER(P59),ISNUMBER(Q59)),L59/((P59+Q59)/2)-1,"") | T59: 79000 | U59: 2003 | V59: 02/2003 | W59: Essence | X59: Manuelle | Y59: 120 | Z59: 8 | AA59: Autre | AB59: 3 | AC59: Berline | AF59: Particulier | AG59: Richwiller | AH59: 68120 | AI59: Haut-Rhin | AJ59: Alsace | AK59: 3 | AM59: Non | AN59: Vend saxo 1L6 vts 16V Voiture entretenue Révision faite ; Vidange moteur , boîte de vitesse, bougies, liquide de frein , distribution, frein , pneus et amortisseurs neuf , etc Me contacter uniquement par téléphone. | AO59: Permis : Avec permis ; Importé : false | AP59: Voir | AQ59: 3260650856
A60: Citroën Saxo VTS 16V | B60: Saxo Vts 1.6 8s 100ch | E60: En vente | F60: 46266 | G60: 46266 | H60: 46310 | J60: =IF(OR(ISNUMBER(F60),ISNUMBER(G60)),IF(ISNUMBER(I60),I60,H60)-IF(ISNUMBER(F60),F60,G60),"") | K60: 6700 | L60: 6700 | M60: =IF(AND(ISNUMBER(K60),ISNUMBER(L60),K60>0),1-L60/K60,"") | N60: 0 | R60: =IF(AND(ISNUMBER(L60),ISNUMBER(P60),ISNUMBER(Q60)),L60/((P60+Q60)/2)-1,"") | T60: 242000 | U60: 2002 | V60: 04/2002 | W60: Essence | X60: Manuelle | Y60: 100 | Z60: 6 | AA60: Rouge | AB60: 3 | AC60: Berline | AF60: Particulier | AG60: Gétigné | AH60: 44190 | AI60: Loire-Atlantique | AJ60: Pays de la Loire | AK60: 3 | AM60: Non | AN60: Bonjour, Je met en vente ma Citroën Saxo VTS 1.6 8S de 2002 - Marque : Citroën - Modèle : Saxo VTS - Année : 2002 - Kilométrage : 242 000 km - Motorisation : 1.6 8S 100 ch - Carburant : Essence - Boîte de vitesses : Manuelle - Couleur : Rouge - Type de véhicule : Berline - Nombre de portes : 3 - Nombre de sièges : 5 - Puissance fiscale : 6 Cv Frais effectuée depuis février 2025 - Alternateur - Batterie - Souffler de cardans - Pompe de lave glace - Soufflet de direction - Roture de suspension - C | AO60: Dommages : Bon état général ; Sellerie : Tissu ; Permis : Avec permis ; Importé : false | AP60: Voir | AQ60: 3260831234
A61: Citroën Saxo VTS 16V | B61: Saxo vts 16v/16s route/piste | E61: En vente | F61: 46267 | G61: 46267 | H61: 46310 | J61: =IF(OR(ISNUMBER(F61),ISNUMBER(G61)),IF(ISNUMBER(I61),I61,H61)-IF(ISNUMBER(F61),F61,G61),"") | K61: 6800 | L61: 6800 | M61: =IF(AND(ISNUMBER(K61),ISNUMBER(L61),K61>0),1-L61/K61,"") | N61: 0 | R61: =IF(AND(ISNUMBER(L61),ISNUMBER(P61),ISNUMBER(Q61)),L61/((P61+Q61)/2)-1,"") | T61: 135000 | U61: 2000 | V61: 09/2000 | W61: Essence | X61: Manuelle | Y61: 118 | Z61: 8 | AA61: Blanc | AB61: 3 | AC61: Berline | AF61: Particulier | AG61: Messein | AH61: 54850 | AI61: Meurthe-et-Moselle | AJ61: Lorraine | AK61: 3 | AM61: Non | AN61: Bonjour, suite à de nouveaux projet de vie j’envisage de me séparer de ma voiture de piste. La voiture est roulante, mais ct plus de 6 mois et est restée à l’arrêt plus d’un an. Un entretiens est à prévoir, la voiture est équipée pour la piste et est vendu en tant que telle. -ct + 6 mois CG à mon nom -135k km -un peu de frais de carrosserie bosse aile/coffre, rouille de surface sous le coffre -caisse complètement vidée mais intérieur présent et/ou panneau de porte Carbon à posé -baquet et harnai | AO61: vehicle_technical_inspection_valid : Oui ; Contrôle technique : 2027 ; Permis : Avec permis ; Importé : false | AP61: Voir | AQ61: 3261627755
A62: Citroën Saxo VTS 16V | B62: Saxo vts 16s 120ch | C62: Saxo 1.6 16v VTS 3p | D62: VTS | E62: En vente | F62: 46269 | G62: 46269 | H62: 46310 | J62: =IF(OR(ISNUMBER(F62),ISNUMBER(G62)),IF(ISNUMBER(I62),I62,H62)-IF(ISNUMBER(F62),F62,G62),"") | K62: 7600 | L62: 7600 | M62: =IF(AND(ISNUMBER(K62),ISNUMBER(L62),K62>0),1-L62/K62,"") | N62: 0 | R62: =IF(AND(ISNUMBER(L62),ISNUMBER(P62),ISNUMBER(Q62)),L62/((P62+Q62)/2)-1,"") | T62: 209000 | U62: 2002 | V62: 11/2002 | W62: Essence | X62: Manuelle | Y62: 120 | Z62: 8 | AA62: Gris | AB62: 3 | AC62: Berline | AF62: Particulier | AG62: Bennwihr | AH62: 68630 | AI62: Haut-Rhin | AJ62: Alsace | AK62: 3 | AM62: Non | AN62: À vendre – Saxo VTS 16V 120 ch de 2002, gris EZR Merci de bien vouloir lire l’annonce avant de me contacter : je ne répondrai pas aux questions dont la réponse figure déjà dans l’annonce. Bon état général. Beaucoup de frais effectués, en voici une liste non exhaustive : Transmission refaite à neuf (10 000 km) : cardans AVG/AVD, embrayage, boîte de vitesses et roulements AVG/ARG/ARD Bobine d’allumage et démarreur (5 000 km) Supports moteur (10 000 km) Amortisseurs arrière ARG/ARD (5 000 km) Distr | AO62: Permis : Avec permis ; Importé : false | AP62: Voir | AQ62: 3262635276
A63: Citroën Saxo VTS 16V | B63: Saxo vts 16v | C63: VTS_Saxo 1.6 16V 120ch VTS 3p | D63: VTS | E63: En vente | F63: 46271 | G63: 46271 | H63: 46310 | J63: =IF(OR(ISNUMBER(F63),ISNUMBER(G63)),IF(ISNUMBER(I63),I63,H63)-IF(ISNUMBER(F63),F63,G63),"") | K63: 10900 | L63: 10900 | M63: =IF(AND(ISNUMBER(K63),ISNUMBER(L63),K63>0),1-L63/K63,"") | N63: 0 | R63: =IF(AND(ISNUMBER(L63),ISNUMBER(P63),ISNUMBER(Q63)),L63/((P63+Q63)/2)-1,"") | T63: 144000 | U63: 1997 | V63: 02/1997 | W63: Essence | X63: Manuelle | Y63: 120 | Z63: 8 | AA63: Bleu | AB63: 3 | AC63: Berline | AD63: Factures disponibles, Véhicule non fumeur, Réparations utiles déjà faites | AF63: Particulier | AG63: Festubert | AH63: 62149 | AI63: Pas-de-Calais | AJ63: Nord-Pas-de-Calais | AK63: 3 | AM63: Non | AN63: Saxo vts 16v 144000kms Nombreuses factures d entretien Train arrière changer il y a 1 an. En février 2027 , elle peu etre passé en véhicule de collection. Face avant mise en phase 2. Je possède le volant d origine Caisse très saine. Pas de corrosion Carrosserie extérieur présente bien mais pas neuve ! Pas de collection de photo! Intéressé vous venez l avoir si vous avez le budget! Annonce en ligne= dispo | AO63: vehicle_technical_inspection_valid : Oui ; Contrôle technique : 2028 ; Dommages : Bon état général ; Sellerie : Velours ; Équipements intérieurs : Jantes en alliage, Sièges sport ; Permis : Avec permis ; Importé : false | AP63: Voir | AQ63: 3264107945
A64: Citroën Saxo VTS 16V | B64: Saxo vts 16v 2000 | E64: En vente | F64: 46273 | G64: 46273 | H64: 46310 | J64: =IF(OR(ISNUMBER(F64),ISNUMBER(G64)),IF(ISNUMBER(I64),I64,H64)-IF(ISNUMBER(F64),F64,G64),"") | K64: 7500 | L64: 7500 | M64: =IF(AND(ISNUMBER(K64),ISNUMBER(L64),K64>0),1-L64/K64,"") | N64: 0 | R64: =IF(AND(ISNUMBER(L64),ISNUMBER(P64),ISNUMBER(Q64)),L64/((P64+Q64)/2)-1,"") | T64: 216500 | U64: 2000 | V64: 07/2000 | W64: Essence | X64: Manuelle | Y64: 118 | Z64: 8 | AA64: Autre | AB64: 3 | AC64: Berline | AF64: Particulier | AG64: Ménétreux-le-Pitois | AH64: 21150 | AI64: Côte-d'Or | AJ64: Bourgogne | AK64: 3 | AM64: Non | AN64: Bonjour, A vendre Saxo vts 16v de 2000. Refaite complète, quelques bricoles à revoir malgré tout. -centralisation ne fonctionne pas -retros électrique ne fonctionne pas -capot voilé ( je fourni un capot d’occas à reprendre -pare choc avant et arrière à repeindre ( mal préparé et la peinture s’écaille) Peinture neuve (teinte biton mais pas une vrai) 216500 kms au compteur. Moteur neuf (4 pistons, coussinets, culasse contrôlée) Boîte de vitesse neuve 6000€ de factures Carte grise à jour et CT ok d | AO64: vehicle_technical_inspection_valid : Oui ; Contrôle technique : 2028 ; Permis : Avec permis ; Importé : false | AP64: Voir | AQ64: 3266045304
A65: Citroën Saxo VTS 16V | B65: Citroën saxo vts | E65: En vente | F65: 46279 | G65: 46279 | H65: 46310 | J65: =IF(OR(ISNUMBER(F65),ISNUMBER(G65)),IF(ISNUMBER(I65),I65,H65)-IF(ISNUMBER(F65),F65,G65),"") | K65: 2500 | L65: 2500 | M65: =IF(AND(ISNUMBER(K65),ISNUMBER(L65),K65>0),1-L65/K65,"") | N65: 0 | R65: =IF(AND(ISNUMBER(L65),ISNUMBER(P65),ISNUMBER(Q65)),L65/((P65+Q65)/2)-1,"") | T65: 150000 | U65: 2000 | V65: 04/2000 | W65: Essence | X65: Manuelle | Y65: 75 | Z65: 5 | AA65: Autre | AB65: 3 | AC65: Berline | AF65: Particulier | AG65: Naintré | AH65: 86530 | AI65: Vienne | AJ65: Poitou-Charentes | AK65: 1 | AM65: Non | AN65: Saxo vts entière pour la pièce ou bien à Remonter swap 2l16 toutes les pièce d origine sont présente et fournie avec !!! plus d info par message | AO65: Permis : Avec permis ; Importé : false | AP65: Voir | AQ65: 3269890983
A66: Citroën Saxo VTS 16V | B66: Saxo Vts 1.6 8s | E66: En vente | F66: 46280 | G66: 46280 | H66: 46310 | J66: =IF(OR(ISNUMBER(F66),ISNUMBER(G66)),IF(ISNUMBER(I66),I66,H66)-IF(ISNUMBER(F66),F66,G66),"") | K66: 4500 | L66: 4500 | M66: =IF(AND(ISNUMBER(K66),ISNUMBER(L66),K66>0),1-L66/K66,"") | N66: 0 | R66: =IF(AND(ISNUMBER(L66),ISNUMBER(P66),ISNUMBER(Q66)),L66/((P66+Q66)/2)-1,"") | T66: 250000 | U66: 2001 | V66: 11/2001 | W66: Essence | X66: Manuelle | Y66: 90 | Z66: 5 | AA66: Argent | AB66: 3 | AC66: Berline | AD66: Factures disponibles, Réparations utiles déjà faites, Véhicule non fumeur | AF66: Particulier | AG66: Saint-Pierre | AH66: 97410 | AJ66: Réunion | AK66: 3 | AM66: Non | AN66: Vend Saxo Vts 1.6 8s. Distribution, embrayage et train avant viens d'être fais. Modification : swap 1.6 8s, gros injecteur, poulie réglable, frein s16, boîte s16 14.60, train avant s16. Vend avec kit en fibre complet pour le véhicule. Plus d'informations en privé. | AO66: Dommages : Bon état général ; Sellerie : Tissu ; Permis : Avec permis ; Importé : false | AP66: Voir | AQ66: 3270100305
A67: Citroën Saxo VTS 16V | B67: Saxo vts 1.6 8s | E67: En vente | F67: 46281 | G67: 46281 | H67: 46310 | J67: =IF(OR(ISNUMBER(F67),ISNUMBER(G67)),IF(ISNUMBER(I67),I67,H67)-IF(ISNUMBER(F67),F67,G67),"") | K67: 1600 | L67: 1600 | M67: =IF(AND(ISNUMBER(K67),ISNUMBER(L67),K67>0),1-L67/K67,"") | N67: 0 | R67: =IF(AND(ISNUMBER(L67),ISNUMBER(P67),ISNUMBER(Q67)),L67/((P67+Q67)/2)-1,"") | T67: 281740 | U67: 2003 | V67: 01/2003 | W67: Essence | X67: Manuelle | Y67: 100 | Z67: 6 | AA67: Autre | AB67: 3 | AC67: Berline | AF67: Particulier | AG67: Le Robert | AH67: 97231 | AJ67: Martinique | AK67: 1 | AM67: Non | AN67: Saxo vts 1.6 8s d’origine Carte grise OK Pas de CT , en état Voyant abs allumé Quelques défauts carrosserie, point de rouille portière gauche, fixation siège chauffeur | AO67: vehicle_technical_inspection_valid : Non ; Permis : Avec permis ; Importé : false | AP67: Voir | AQ67: 3271080732
A68: Citroën Saxo VTS 16V | B68: Saxo vts | E68: En vente | F68: 46287 | G68: 46287 | H68: 46310 | J68: =IF(OR(ISNUMBER(F68),ISNUMBER(G68)),IF(ISNUMBER(I68),I68,H68)-IF(ISNUMBER(F68),F68,G68),"") | K68: 9000 | L68: 9000 | M68: =IF(AND(ISNUMBER(K68),ISNUMBER(L68),K68>0),1-L68/K68,"") | N68: 0 | R68: =IF(AND(ISNUMBER(L68),ISNUMBER(P68),ISNUMBER(Q68)),L68/((P68+Q68)/2)-1,"") | T68: 230000 | U68: 1999 | V68: 10/1999 | W68: Essence | X68: Manuelle | Y68: 118 | Z68: 8 | AA68: Autre | AB68: 3 | AC68: Berline | AF68: Particulier | AG68: Morteau | AH68: 25500 | AI68: Doubs | AJ68: Franche-Comté | AK68: 3 | AM68: Non | AN68: Citroën Saxo VTS 1.6 16V – 1999 Je mets en vente ma Citroën Saxo VTS 1.6 16V de 1999. Je m’en sépare à contrecœur car j’ai un autre projet automobile qui me prend du temps et du budget. Informations : Citroën Saxo VTS 1.6 16 soupapes Année : 1999 Boîte manuelle Carte grise à mon nom Amortisseur BC racing Commande boîte satchell Jante pts Nankang AR 1 Durite avia Liquide frein RBF 660 Collecteur 4-2-1 Ligne groupe N oreca DEMI Arceau AST À POSER Siège Sparco Évo QRT Plaquettes avant ferodo DS 250 | AO68: Permis : Avec permis ; Importé : false | AP68: Voir | AQ68: 3274386766
A69: Citroën Saxo VTS 16V | B69: Saxo VTS 16V restaurée | E69: En vente | F69: 46289 | G69: 46289 | H69: 46310 | J69: =IF(OR(ISNUMBER(F69),ISNUMBER(G69)),IF(ISNUMBER(I69),I69,H69)-IF(ISNUMBER(F69),F69,G69),"") | K69: 10000 | L69: 10000 | M69: =IF(AND(ISNUMBER(K69),ISNUMBER(L69),K69>0),1-L69/K69,"") | N69: 0 | R69: =IF(AND(ISNUMBER(L69),ISNUMBER(P69),ISNUMBER(Q69)),L69/((P69+Q69)/2)-1,"") | T69: 195184 | U69: 2000 | V69: 08/2000 | W69: Essence | X69: Manuelle | Y69: 118 | Z69: 8 | AA69: Jaune | AB69: 3 | AC69: Berline | AD69: Factures disponibles, Réparations utiles déjà faites | AF69: Particulier | AG69: Soissons | AH69: 02200 | AI69: Aisne | AJ69: Picardie | AK69: 3 | AM69: Non | AN69: Bonjour, je met en vente ma saxo après deux ans en ma possession (400kms…) Je l’ai acheté dans un garage de restauration de véhicules ( vintage car à maroilles 59 ) La carosserie et le châssis ont intégralement été traité contre la rouille et refait Peinture complète orange mango ( bic ) Baie moteur également Pour ce qui est de la meca que j’ai réalisé sur ces deux années Distribution + PAE Sonde de température LR Intermédiaire + silencieux neufs Vidange + filtre Joints spy boîte de vitesse Biel | AO69: vehicle_technical_inspection_valid : Non ; Dommages : Excellent état (proche du neuf) ; Sellerie : Tissu ; Équipements intérieurs : Bluetooth, Jantes en alliage, Phares anti-brouillard, Radio numérique DAB, Roue de secours, Siège arrière rabattable, Suspension sport / adaptative ; Permis : Avec permis ; Importé : false ; vehicle_history_teaser_critair : 3 ; vehicle_history_teaser_owners : 3 ; vehicle_history_teaser_expertises : true ; vehicle_history_teaser_special_uses : false ; vehicle_history_teaser_atypical_operations : true ; vehicle_history_teaser_importations : false | AP69: Voir | AQ69: 3275636332
A70: Citroën Saxo VTS 16V | B70: Citroën saxo vts | E70: En vente | F70: 46289 | G70: 46289 | H70: 46310 | J70: =IF(OR(ISNUMBER(F70),ISNUMBER(G70)),IF(ISNUMBER(I70),I70,H70)-IF(ISNUMBER(F70),F70,G70),"") | K70: 6000 | L70: 6000 | M70: =IF(AND(ISNUMBER(K70),ISNUMBER(L70),K70>0),1-L70/K70,"") | N70: 0 | R70: =IF(AND(ISNUMBER(L70),ISNUMBER(P70),ISNUMBER(Q70)),L70/((P70+Q70)/2)-1,"") | T70: 111111 | U70: 1998 | V70: 02/1998 | W70: Essence | X70: Manuelle | Y70: 75 | Z70: 6 | AA70: Gris | AB70: 3 | AC70: Berline | AF70: Particulier | AG70: Saint-Agnan | AH70: 89340 | AI70: Yonne | AJ70: Bourgogne | AK70: 3 | AM70: Non | AN70: Bonjour, Je vends ma Citroën Saxo vts de 98 qui est en ma possession depuis un peux plus de 20ans. Elle n'est plus d'origine. La caisse a été complète vidé et souder. Il y a un arceau qui est soudé. La voiture a eu une peinture complète intérieure/extérieur et la pose d'un kit carrosserie de saxo kit car. Le capot est en fibre. Elle a un train arrière à disque qui avait été révisé. Suspension blisten B6 Frein avant de 206S16 Maître cylindre en 23.8 Triangle avant renforcé. Je dois en oublier sûr | AO70: Permis : Avec permis ; Importé : false | AP70: Voir | AQ70: 3275939150
A71: Citroën Saxo VTS 16V | B71: Vend saxo vts 100ch | E71: En vente | F71: 46289 | G71: 46289 | H71: 46310 | J71: =IF(OR(ISNUMBER(F71),ISNUMBER(G71)),IF(ISNUMBER(I71),I71,H71)-IF(ISNUMBER(F71),F71,G71),"") | K71: 5500 | L71: 5500 | M71: =IF(AND(ISNUMBER(K71),ISNUMBER(L71),K71>0),1-L71/K71,"") | N71: 0 | R71: =IF(AND(ISNUMBER(L71),ISNUMBER(P71),ISNUMBER(Q71)),L71/((P71+Q71)/2)-1,"") | T71: 207000 | U71: 2002 | V71: 01/2002 | W71: Essence | X71: Manuelle | Y71: 100 | Z71: 6 | AA71: Jaune | AB71: 3 | AC71: Citadine | AF71: Particulier | AG71: Villemolaque | AH71: 66300 | AI71: Pyrénées-Orientales | AJ71: Languedoc-Roussillon | AK71: 3 | AM71: Non | AN71: 🚗 Citroën Saxo vts 100ch– bon état – À vendre Citroën Saxo 3 portes – couleur dorée Je mets en vente ma Citroën Saxo, une petite voiture agréable et pratique, idéale comme première voiture ou pour les trajets quotidiens. 🔹 Marque : Citroën 🔹 Modèle : Saxo 🔹 Année : 2002 🔹 Kilométrage : 207000 🔹 Motorisation : [essence] 🔹 Boîte : manuelle 🔹 Couleur : doré 🔹 Nombre de portes : 3 🔹 Prix : 5500 La voiture est roulante et en bon état général. Elle présente quelques marques normales compte t | AO71: Permis : Avec permis ; Importé : false | AP71: Voir | AQ71: 3276019569
A72: Citroën Saxo VTS 16V | B72: Saxo VTS 16v | E72: En vente | F72: 46289 | G72: 46289 | H72: 46310 | J72: =IF(OR(ISNUMBER(F72),ISNUMBER(G72)),IF(ISNUMBER(I72),I72,H72)-IF(ISNUMBER(F72),F72,G72),"") | K72: 8800 | L72: 8800 | M72: =IF(AND(ISNUMBER(K72),ISNUMBER(L72),K72>0),1-L72/K72,"") | N72: 0 | R72: =IF(AND(ISNUMBER(L72),ISNUMBER(P72),ISNUMBER(Q72)),L72/((P72+Q72)/2)-1,"") | T72: 181200 | U72: 2000 | V72: 08/2000 | W72: Essence | X72: Manuelle | Y72: 118 | Z72: 8 | AA72: Noir | AB72: 3 | AC72: Berline | AF72: Particulier | AG72: Bar-le-Duc | AH72: 55000 | AI72: Meuse | AJ72: Lorraine | AK72: 10 | AM72: Non | AN72: Bonjour, Je vends ma Saxo VTS à contre-cœur car j’ai d’autres projets. * 1.6 16V 120 ch * Noir Onyx * Phase 2 d’août 2000 * Vitres électriques * Rétroviseurs électriques * Climatisation * 181 200 km (légèrement évolutifs) Travaux effectués et pièces montées par l’ancien propriétaire : * Restauration complète de la caisse avec peinture complète (photos disponibles) * Train arrière neuf + décranté * Durites aviation * Ressorts courts + amortisseurs Bilstein * Cône d’admission * Collecteur inox * C | AO72: vehicle_technical_inspection_valid : Oui ; Contrôle technique : 2028 ; Permis : Avec permis ; Importé : false | AP72: Voir | AQ72: 3276045076
A73: Citroën Saxo VTS 16V | B73: Saxo Vts 16v | C73: Saxo 1.6 16V 120ch VTS 3p | D73: VTS | E73: En vente | F73: 46291 | G73: 46291 | H73: 46310 | J73: =IF(OR(ISNUMBER(F73),ISNUMBER(G73)),IF(ISNUMBER(I73),I73,H73)-IF(ISNUMBER(F73),F73,G73),"") | K73: 7500 | L73: 7500 | M73: =IF(AND(ISNUMBER(K73),ISNUMBER(L73),K73>0),1-L73/K73,"") | N73: 0 | R73: =IF(AND(ISNUMBER(L73),ISNUMBER(P73),ISNUMBER(Q73)),L73/((P73+Q73)/2)-1,"") | T73: 185000 | U73: 2000 | V73: 09/2000 | W73: Essence | X73: Manuelle | Y73: 120 | Z73: 8 | AA73: Autre | AB73: 3 | AC73: Berline | AF73: Particulier | AG73: Solliès-Pont | AH73: 83210 | AI73: Var | AJ73: Provence-Alpes-Côte d'Azur | AK73: 3 | AM73: Non | AN73: Vend saxo Vts 16v Dans l état contrôle technique a faire Tourne nikel distri a prévoir et quelques defaults carrosserie | AO73: Permis : Avec permis ; Importé : false | AP73: Voir | AQ73: 3276707355
A74: Citroën Saxo VTS 16V | B74: Saxo VTS | E74: En vente | F74: 46294 | G74: 46294 | H74: 46310 | J74: =IF(OR(ISNUMBER(F74),ISNUMBER(G74)),IF(ISNUMBER(I74),I74,H74)-IF(ISNUMBER(F74),F74,G74),"") | K74: 6000 | L74: 6000 | M74: =IF(AND(ISNUMBER(K74),ISNUMBER(L74),K74>0),1-L74/K74,"") | N74: 0 | R74: =IF(AND(ISNUMBER(L74),ISNUMBER(P74),ISNUMBER(Q74)),L74/((P74+Q74)/2)-1,"") | T74: 170600 | U74: 2002 | V74: 04/2002 | W74: Essence | X74: Manuelle | Y74: 75 | Z74: 5 | AA74: Bleu | AB74: 3 | AC74: Berline | AD74: Véhicule non fumeur, Réparations utiles déjà faites | AF74: Particulier | AG74: Faulquemont | AH74: 57380 | AI74: Moselle | AJ74: Lorraine | AK74: 3 | AM74: Non | AN74: Bonjour, Je vend ma saxo VTS 1.4 75 avec clim et 170600km. Le moteur tourne comme une horloge démarre au quart de tour. Tout fonctionne Elle est complètement d'origine et ne sera pas vendu avec les jantes tôles. Niveau entretien. La distribution et embrayage neuf. Le freins avant et arriere neuf Les triangles et toute les rotules sont neuf Le catalyseur est neuf La ligne d'échappement est neuf La vidange a ete faite il y a moins de 2000km Le train arriere est en excellent état La climatisation f | AO74: Dommages : Excellent état (proche du neuf) ; Sellerie : Tissu ; Équipements intérieurs : Bluetooth, Climatisation, Jantes en alliage, Roue de secours, Siège arrière rabattable, Sièges sport ; Permis : Avec permis ; Importé : false | AP74: Voir | AQ74: 3278923547
A75: Citroën Saxo VTS 16V | B75: Saxo vts 16v | E75: En vente | F75: 46297 | G75: 46297 | H75: 46310 | J75: =IF(OR(ISNUMBER(F75),ISNUMBER(G75)),IF(ISNUMBER(I75),I75,H75)-IF(ISNUMBER(F75),F75,G75),"") | K75: 10000 | L75: 10000 | M75: =IF(AND(ISNUMBER(K75),ISNUMBER(L75),K75>0),1-L75/K75,"") | N75: 0 | R75: =IF(AND(ISNUMBER(L75),ISNUMBER(P75),ISNUMBER(Q75)),L75/((P75+Q75)/2)-1,"") | T75: 230000 | U75: 1999 | V75: 10/1999 | W75: Essence | X75: Manuelle | Y75: 118 | Z75: 8 | AA75: Blanc | AB75: 3 | AC75: Berline | AF75: Particulier | AG75: Croix | AH75: 90100 | AI75: Territoire de Belfort | AJ75: Franche-Comté | AK75: 1 | AM75: Non | AN75: Saxo vts 16v, cg en règle à mon nom depuis 16 ans, la caisse a 230000km environ En équipement : Train avant - amortisseur viarouge sur mesure, coupelle sup réglable, étrier brembo de 406, circuit full durit avia, combiné fileté CS min GrA Barre anti rapprochement sup et inf Pedal box pour les freins, avec plein de Maître cylindre différents pour tout essayer Compartiment moteur souder, renfort de coupelle, triangle Train arrière : Poutre renforcer, étrier de visa double piston (+ 4 autres en sto | AO75: vehicle_technical_inspection_valid : Oui ; Permis : Avec permis ; Importé : false | AP75: Voir | AQ75: 3280590101
A76: Citroën Saxo VTS 16V | B76: Citroen SAXO VTS 1,6L 16V | E76: En vente | F76: 46298 | G76: 46298 | H76: 46310 | J76: =IF(OR(ISNUMBER(F76),ISNUMBER(G76)),IF(ISNUMBER(I76),I76,H76)-IF(ISNUMBER(F76),F76,G76),"") | K76: 8800 | L76: 8800 | M76: =IF(AND(ISNUMBER(K76),ISNUMBER(L76),K76>0),1-L76/K76,"") | N76: 0 | R76: =IF(AND(ISNUMBER(L76),ISNUMBER(P76),ISNUMBER(Q76)),L76/((P76+Q76)/2)-1,"") | T76: 150500 | U76: 2000 | V76: 04/2000 | W76: Essence | X76: Manuelle | Y76: 118 | Z76: 8 | AA76: Autre | AB76: 3 | AC76: Berline | AF76: Particulier | AG76: Chassiers | AH76: 07110 | AI76: Ardèche | AJ76: Rhône-Alpes | AK76: 3 | AM76: Non | AN76: SAXO VTS 1,6L 16V Loisirs / Circuit (Pas de passeport) Année 2000 Carte Grise à mon nom sans CT 150.500km Moteur: collecteur 4.2.1 Inox ligne d'échappement complète inox de saxo cup silent-bloc moteur inférieur rigide boite à Citroën sport avec filtre green arbre à cames shrick mini Groupe A (montage poussoirs hydro) bougies Bosch iridium coussinets de bielle tri-métal calculateur d'origine reprogrammer (chez mf power) vidange (Motul 300V) filtre à huile, essence, filtre à air nettoyer batterie | AO76: Dommages : Bon état général ; Permis : Avec permis ; Importé : false | AP76: Voir | AQ76: 3281202476
A77: Citroën Saxo VTS 16V | B77: Saxo VTS 1l4 75cv | E77: En vente | F77: 46298 | G77: 46298 | H77: 46310 | J77: =IF(OR(ISNUMBER(F77),ISNUMBER(G77)),IF(ISNUMBER(I77),I77,H77)-IF(ISNUMBER(F77),F77,G77),"") | K77: 5000 | L77: 5000 | M77: =IF(AND(ISNUMBER(K77),ISNUMBER(L77),K77>0),1-L77/K77,"") | N77: 0 | R77: =IF(AND(ISNUMBER(L77),ISNUMBER(P77),ISNUMBER(Q77)),L77/((P77+Q77)/2)-1,"") | T77: 210000 | U77: 1999 | V77: 10/1999 | W77: Essence | X77: Manuelle | Y77: 75 | Z77: 5 | AA77: Jaune | AB77: 3 | AC77: Berline | AD77: Carnet d'entretien disponible, Factures disponibles, Véhicule non fumeur, Réparations utiles déjà faites | AF77: Particulier | AG77: Champdray | AH77: 88640 | AI77: Vosges | AJ77: Lorraine | AK77: 3 | AM77: Non | AN77: Je vends ma Citroën Saxo VTS de 1999, une citadine robuste et économique avec 210 000 km au compteur. - Marque : Citroën - Modèle : Saxo - Année : 1999 - Kilométrage : 210 000 km - Motorisation : 1.4 75 ch - Carburant : Essence - Boîte de vitesses : Manuelle - Couleur : Jaune - Type de véhicule : Berline - Nombre de portes : 3 - Puissance fiscale : 5 Cv - Crit'air : 3 - Contrôle technique : Valide jusqu'à février 2028. Sera refait pour la vente . Auto très économique et très bien entretenue (vid | AO77: vehicle_technical_inspection_valid : Oui ; Dommages : Bon état général ; Sellerie : Velours ; Équipements intérieurs : Climatisation, Phares anti-brouillard, Roue de secours, Rétroviseurs dégivrants ; Permis : Avec permis ; Importé : false | AP77: Voir | AQ77: 3281577931
A78: Citroën Saxo VTS 16V | B78: Saxo vts | E78: En vente | F78: 46299 | G78: 46299 | H78: 46310 | J78: =IF(OR(ISNUMBER(F78),ISNUMBER(G78)),IF(ISNUMBER(I78),I78,H78)-IF(ISNUMBER(F78),F78,G78),"") | K78: 7600 | L78: 7600 | M78: =IF(AND(ISNUMBER(K78),ISNUMBER(L78),K78>0),1-L78/K78,"") | N78: 0 | R78: =IF(AND(ISNUMBER(L78),ISNUMBER(P78),ISNUMBER(Q78)),L78/((P78+Q78)/2)-1,"") | T78: 179999 | U78: 2001 | V78: 08/2001 | W78: Essence | X78: Manuelle | Y78: 120 | Z78: 8 | AA78: Autre | AB78: 3 | AC78: Berline | AF78: Particulier | AG78: Angers | AH78: 49100 | AI78: Maine-et-Loire | AJ78: Pays de la Loire | AK78: 3 | AM78: Non | AN78: Saxo vts 1.6L 120ch 16V Toit ouvrant Clim Vitres électriques Son focal Roue de secours En très bon état général, carrosserie 9,5/10 179600km Boite 5 vitesses Distribution à faire fin d'année Consommables ✅️ Vidange ✅️ Elle possède 40% de suivi garage ou entretien. | AO78: Permis : Avec permis ; Importé : false | AP78: Voir | AQ78: 3282361681
A79: Citroën Saxo VTS 16V | B79: Saxo vts | C79: Saxo 1.4 VTS 3p | D79: VTS | E79: En vente | F79: 46299 | G79: 46299 | H79: 46310 | J79: =IF(OR(ISNUMBER(F79),ISNUMBER(G79)),IF(ISNUMBER(I79),I79,H79)-IF(ISNUMBER(F79),F79,G79),"") | K79: 5500 | L79: 5500 | M79: =IF(AND(ISNUMBER(K79),ISNUMBER(L79),K79>0),1-L79/K79,"") | N79: 0 | R79: =IF(AND(ISNUMBER(L79),ISNUMBER(P79),ISNUMBER(Q79)),L79/((P79+Q79)/2)-1,"") | T79: 250000 | U79: 1999 | V79: 10/1999 | W79: Essence | X79: Manuelle | Y79: 75 | Z79: 5 | AA79: Jaune | AB79: 3 | AC79: Berline | AD79: Carnet d'entretien disponible, Factures disponibles, Véhicule non fumeur, Réparations utiles déjà faites | AF79: Particulier | AG79: Saint-Germain-du-Plain | AH79: 71370 | AI79: Saône-et-Loire | AJ79: Bourgogne | AK79: 3 | AM79: Non | AN79: Citroën Saxo VTS 1.4 75 ch – Caisse très saine – Factures – CT OK Je vends ma Citroën Saxo VTS 1.4 de 1999. Voiture qui roule parfaitement, très saine pour son âge et de plus en plus rare dans cet état. Caractéristiques : - Année : 1999 - Moteur : 1.4 75 ch - Kilométrage : 250 000 Km - Contrôle technique valide - Joint de culasse refait à 242 012 km (factures à l’appui) - Toutes les factures d’entretien disponibles État : - Caisse très saine, aucun point de rouille - Plancher propre (photos disp | AO79: vehicle_technical_inspection_valid : Oui ; Contrôle technique : 2027 ; Dommages : Bon état général ; Permis : Avec permis ; Importé : false | AP79: Voir | AQ79: 3282370613
A80: Citroën Saxo VTS 16V | B80: Saxo vts DIESEL | E80: En vente | F80: 46303 | G80: 46303 | H80: 46310 | J80: =IF(OR(ISNUMBER(F80),ISNUMBER(G80)),IF(ISNUMBER(I80),I80,H80)-IF(ISNUMBER(F80),F80,G80),"") | K80: 3000 | L80: 3000 | M80: =IF(AND(ISNUMBER(K80),ISNUMBER(L80),K80>0),1-L80/K80,"") | N80: 0 | R80: =IF(AND(ISNUMBER(L80),ISNUMBER(P80),ISNUMBER(Q80)),L80/((P80+Q80)/2)-1,"") | T80: 220000 | U80: 2002 | V80: 03/2002 | W80: Diesel | X80: Manuelle | Y80: 58 | Z80: 4 | AA80: Gris | AB80: 3 | AC80: Berline | AF80: Particulier | AG80: Thun-Saint-Amand | AH80: 59158 | AI80: Nord | AJ80: Nord-Pas-de-Calais | AK80: 3 | AM80: Non | AN80: Bonjour Je vends ma saxo vts New norming diesel Travaux effectués : - distribution - embrayage - entretien complet - 4 pneus neuf N'hésitez pas pour tout renseignement Cordialement | AO80: Sellerie : Tissu ; Permis : Avec permis ; Importé : false | AP80: Voir | AQ80: 3284453819
A81: Citroën Saxo VTS 16V | B81: Saxo vts 16v | E81: En vente | F81: 46304 | G81: 46304 | H81: 46310 | J81: =IF(OR(ISNUMBER(F81),ISNUMBER(G81)),IF(ISNUMBER(I81),I81,H81)-IF(ISNUMBER(F81),F81,G81),"") | K81: 13000 | L81: 13000 | M81: =IF(AND(ISNUMBER(K81),ISNUMBER(L81),K81>0),1-L81/K81,"") | N81: 0 | R81: =IF(AND(ISNUMBER(L81),ISNUMBER(P81),ISNUMBER(Q81)),L81/((P81+Q81)/2)-1,"") | T81: 183800 | U81: 2001 | V81: 05/2001 | W81: Essence | X81: Manuelle | Y81: 120 | Z81: 8 | AA81: Autre | AB81: 3 | AC81: Berline | AD81: Factures disponibles | AE81: Première main | AF81: Particulier | AG81: Yvetot | AH81: 76190 | AI81: Seine-Maritime | AJ81: Haute-Normandie | AK81: 10 | AM81: Non | AN81: Vend SAXO VTS 16V ce n'est pas une première main mais connaissais très bien son propriétaire, bon de commande du véhicule neuf, double des clés, factures d'entretien depuis sa mise en circulation, CT de 2024 RAS, sera refait pour la vente. Voiture restauré dans les règles de l'art, intérieur comme extérieur, jusqu'au jantes. Vente car suite à sa restauration, ne roule pas 330 kms en 2 ans. État vraiment très proche du neuf. | AO81: vehicle_technical_inspection_valid : Oui ; Dommages : Excellent état (proche du neuf) ; Sellerie : Velours ; Permis : Avec permis ; Importé : false ; vehicle_history_report_status : hidden | AP81: Voir | AQ81: 3285059925
A82: Citroën Saxo VTS 16V | B82: Citroën Saxo VTS 16V | E82: En vente | F82: 46305 | G82: 46305 | H82: 46310 | J82: =IF(OR(ISNUMBER(F82),ISNUMBER(G82)),IF(ISNUMBER(I82),I82,H82)-IF(ISNUMBER(F82),F82,G82),"") | K82: 12000 | L82: 12000 | M82: =IF(AND(ISNUMBER(K82),ISNUMBER(L82),K82>0),1-L82/K82,"") | N82: 0 | R82: =IF(AND(ISNUMBER(L82),ISNUMBER(P82),ISNUMBER(Q82)),L82/((P82+Q82)/2)-1,"") | T82: 199800 | U82: 2002 | V82: 01/2002 | W82: Essence | X82: Manuelle | Y82: 120 | Z82: 8 | AA82: Blanc | AB82: 3 | AC82: Citadine | AD82: Carnet d'entretien disponible, Factures disponibles, Véhicule non fumeur, Réparations utiles déjà faites | AF82: Particulier | AG82: Tours | AH82: 37100 | AI82: Indre-et-Loire | AJ82: Centre | AK82: 3 | AM82: Non | AN82: Bonjour, Citroën Saxo VTS 16V de 2002 avec 199800 km peu évolutif en excellent état de présentation. Voiture passion en ma possession depuis plus de 8 ans. Usage loisirs uniquement pour les week-ends. Look rallye certain mais ce n'est pas une pistarde. Toujours stocker en garage sous bâche. Nettoyage minutieux après chaque sortie. Contrôle technique OK du 02/10/2026. Carnet d'entretien présent ainsi qu'un historique complet de factures depuis l'achat du véhicule de l'ensemble des propriétaires p | AO82: Dommages : Excellent état (proche du neuf) ; Sellerie : Tissu ; Équipements intérieurs : Bluetooth, Phares anti-brouillard, Roue de secours, Sièges sport, Système audio haut de gamme ; Permis : Avec permis ; Importé : false | AP82: Voir | AQ82: 3285502703
A83: Citroën Saxo VTS 16V | B83: Citroën saxo vts 16v | E83: En vente | F83: 46305 | G83: 46305 | H83: 46310 | J83: =IF(OR(ISNUMBER(F83),ISNUMBER(G83)),IF(ISNUMBER(I83),I83,H83)-IF(ISNUMBER(F83),F83,G83),"") | K83: 11000 | L83: 11000 | M83: =IF(AND(ISNUMBER(K83),ISNUMBER(L83),K83>0),1-L83/K83,"") | N83: 0 | R83: =IF(AND(ISNUMBER(L83),ISNUMBER(P83),ISNUMBER(Q83)),L83/((P83+Q83)/2)-1,"") | T83: 157000 | U83: 2002 | V83: 08/2002 | W83: Essence | X83: Manuelle | Y83: 120 | Z83: 8 | AA83: Noir | AB83: 3 | AC83: Berline | AD83: Factures disponibles, Véhicule non fumeur, Réparations utiles déjà faites | AF83: Particulier | AG83: Dieppe | AH83: 76200 | AI83: Seine-Maritime | AJ83: Haute-Normandie | AK83: 6 | AM83: Non | AN83: Véhicule très entretenu ,aucun frais à prévoir ct ok,nombreuses factures.negociation dans la limite du raisonnable ! | AO83: Dommages : Excellent état (proche du neuf) ; Sellerie : Velours ; Permis : Avec permis ; Importé : false ; vehicle_history_teaser_critair : 3 ; vehicle_history_teaser_owners : 4 ; vehicle_history_teaser_expertises : false ; vehicle_history_teaser_special_uses : false ; vehicle_history_teaser_atypical_operations : false ; vehicle_history_teaser_importations : false | AP83: Voir | AQ83: 3285503812
A84: Citroën Saxo VTS 16V | B84: Saxo Vts | E84: En vente | F84: 46305 | G84: 46305 | H84: 46310 | J84: =IF(OR(ISNUMBER(F84),ISNUMBER(G84)),IF(ISNUMBER(I84),I84,H84)-IF(ISNUMBER(F84),F84,G84),"") | K84: 16000 | L84: 16000 | M84: =IF(AND(ISNUMBER(K84),ISNUMBER(L84),K84>0),1-L84/K84,"") | N84: 0 | R84: =IF(AND(ISNUMBER(L84),ISNUMBER(P84),ISNUMBER(Q84)),L84/((P84+Q84)/2)-1,"") | T84: 62000 | U84: 2001 | V84: 07/2001 | W84: Essence | X84: Manuelle | Y84: 120 | Z84: 8 | AA84: Gris | AB84: 3 | AC84: Berline | AD84: Carnet d'entretien disponible, Factures disponibles, Véhicule non fumeur, Réparations utiles déjà faites | AF84: Particulier | AG84: Forges-les-Bains | AH84: 91470 | AI84: Essonne | AJ84: Ile-de-France | AK84: 2 | AM84: Non | AN84: Bonjour, Je souhaite vendre ma Saxo Vts. Entièrement d'origine hors poste audio. Véhicule 3 ème main mais sont histoire -> 1 er propriétaire, ancien chef d'atelier l'avait et l'entreposer dans un garage sans rouler pratiquement en faisant l'entretien (voiture de collection), 2 ème propriétaire sont apprentis qui lui achète la voiture avec 33000 km, et la utiliser jusqu'à moi 3 ème propriétaire acheter avec 52000 km. Voiture entretenue avec facture (sauf dernière vidange faites par moi, vu le nom | AO84: vehicle_technical_inspection_valid : Oui ; Contrôle technique : 2027 ; Dommages : Excellent état (proche du neuf) ; Sellerie : Tissu ; Permis : Avec permis ; Importé : false ; vehicle_history_report_status : visible | AP84: Voir | AQ84: 3286019685
A85: Citroën Saxo VTS 16V | B85: Saxo vts 1.6 16v | C85: Saxo 1.6 16v VTS 3p | D85: VTS | E85: En vente | F85: 46306 | G85: 46306 | H85: 46310 | J85: =IF(OR(ISNUMBER(F85),ISNUMBER(G85)),IF(ISNUMBER(I85),I85,H85)-IF(ISNUMBER(F85),F85,G85),"") | K85: 8500 | L85: 8500 | M85: =IF(AND(ISNUMBER(K85),ISNUMBER(L85),K85>0),1-L85/K85,"") | N85: 0 | R85: =IF(AND(ISNUMBER(L85),ISNUMBER(P85),ISNUMBER(Q85)),L85/((P85+Q85)/2)-1,"") | T85: 194500 | U85: 2001 | V85: 06/2001 | W85: Essence | X85: Manuelle | Y85: 120 | Z85: 8 | AA85: Bleu | AB85: 3 | AC85: Berline | AF85: Particulier | AG85: Saint-Laurent-les-Tours | AH85: 46400 | AI85: Lot | AJ85: Midi-Pyrénées | AK85: 3 | AM85: Non | AN85: Citroën Saxo VTS 1.6 16V – 2001 Je mets en vente ma Citroën Saxo VTS 1.6 16V de 2001 Informations : Citroën Saxo VTS 1.6 16 soupapes Année : 06/ 2001 Boîte manuelle Carte grise à mon nom Amortisseur blistein b4 Jante Toulouse origine Collecteur 4-1 daluz développement Ligne groupe À daluz Plaquettes avant et disque avant neuf zéro km Bobine changer récemment Bougies 1 ans Pneus av neuf 100km Vidange sera faite pour la vente Mais fait tous les 5000km max Prix : 8800 N’hésitez pas à me contacter p | AO85: Dommages : Bon état général ; Sellerie : Tissu ; Permis : Avec permis ; Importé : false ; vehicle_history_teaser_critair : 3 ; vehicle_history_teaser_owners : 8 ; vehicle_history_teaser_expertises : true ; vehicle_history_teaser_special_uses : false ; vehicle_history_teaser_atypical_operations : false ; vehicle_history_teaser_importations : false | AP85: Voir | AQ85: 3286165040
A86: Citroën Saxo VTS 16V | B86: Saxo vts | E86: En vente | F86: 46307 | G86: 46307 | H86: 46310 | J86: =IF(OR(ISNUMBER(F86),ISNUMBER(G86)),IF(ISNUMBER(I86),I86,H86)-IF(ISNUMBER(F86),F86,G86),"") | K86: 800 | L86: 800 | M86: =IF(AND(ISNUMBER(K86),ISNUMBER(L86),K86>0),1-L86/K86,"") | N86: 0 | R86: =IF(AND(ISNUMBER(L86),ISNUMBER(P86),ISNUMBER(Q86)),L86/((P86+Q86)/2)-1,"") | T86: 100000 | U86: 2001 | V86: 04/2001 | W86: Essence | X86: Manuelle | Y86: 70 | Z86: 4 | AA86: Bleu | AB86: 5 | AC86: Berline | AF86: Particulier | AG86: Chasseneuil | AH86: 36800 | AI86: Indre | AJ86: Centre | AK86: 1 | AM86: Non | AN86: Caisse saxo phase 2, vidé pour projet course mais abandon de projet Kit vts complet, 3 portes droite, 1 porte gauche, extension arrière droit et gauche Me contacter pour plus de renseignements Fol car, rallycross , rally , poursuite sur terre, autocross | AO86: Permis : Avec permis ; Importé : false | AP86: Voir | AQ86: 3287369967
A87: Citroën Saxo VTS 16V | B87: Saxo vts 1.1 | C87: Saxo 1.1 4cv Bic 3p | D87: Bic | E87: En vente | F87: 46308 | G87: 46308 | H87: 46310 | J87: =IF(OR(ISNUMBER(F87),ISNUMBER(G87)),IF(ISNUMBER(I87),I87,H87)-IF(ISNUMBER(F87),F87,G87),"") | K87: 4500 | L87: 4500 | M87: =IF(AND(ISNUMBER(K87),ISNUMBER(L87),K87>0),1-L87/K87,"") | N87: 0 | R87: =IF(AND(ISNUMBER(L87),ISNUMBER(P87),ISNUMBER(Q87)),L87/((P87+Q87)/2)-1,"") | T87: 129000 | U87: 2001 | V87: 11/2001 | W87: Essence | X87: Manuelle | Y87: 60 | Z87: 4 | AA87: Violet | AB87: 3 | AC87: Berline | AD87: Réparations utiles déjà faites, Véhicule non fumeur | AF87: Particulier | AG87: Millau | AH87: 12100 | AI87: Aveyron | AJ87: Midi-Pyrénées | AK87: 3 | AM87: Non | AN87: n lire l’annonce complète Je vend ma saxo1.1 60ch pour changement de project Tout les papier son à jour Entièrement monter par mes soin en 2024 La caisse a 226000km et le moteur a 129000km Changement de moteur car j’ai acheter cette caisse avec le moteur cassé Tout a étais repeint de la baie moteur a l’intérieur Train avant neuf triangle /suspension ( biltein b8) 4 jante de saxo challenge (Speedline) Baquet rrs futura 3 Harnais driftshop Volant driftshop avec bande voilette Quik release Ciel de | AO87: Dommages : Bon état général ; Sellerie : Tissu ; Permis : Avec permis ; Importé : false | AP87: Voir | AQ87: 3287966186
A88: Citroën Saxo VTS 16V | B88: Saxo vts 16s phase 1 | E88: En vente | F88: 46309 | G88: 46309 | H88: 46310 | J88: =IF(OR(ISNUMBER(F88),ISNUMBER(G88)),IF(ISNUMBER(I88),I88,H88)-IF(ISNUMBER(F88),F88,G88),"") | K88: 11000 | L88: 11000 | M88: =IF(AND(ISNUMBER(K88),ISNUMBER(L88),K88>0),1-L88/K88,"") | N88: 0 | R88: =IF(AND(ISNUMBER(L88),ISNUMBER(P88),ISNUMBER(Q88)),L88/((P88+Q88)/2)-1,"") | T88: 126850 | U88: 1999 | V88: 04/1999 | W88: Essence | X88: Manuelle | Y88: 118 | Z88: 8 | AA88: Bleu | AB88: 3 | AC88: Berline | AD88: Carnet d'entretien disponible, Factures disponibles | AF88: Particulier | AG88: Badonviller | AH88: 54540 | AI88: Meurthe-et-Moselle | AJ88: Lorraine | AK88: 3 | AM88: Non | AN88: Je vends ma Citroën Saxo VTS 16S de 1999, une citadine sportive et attachante avec 126 890 km au compteur. - Marque : Citroën - Modèle : Saxo VTS 16S - Année : 1999 - Kilométrage : 126 890 km - Motorisation : 118 Ch - Puissance fiscale : 8 Cv - Carburant : Essence - Boîte de vitesses : Manuelle - Couleur : Bleu - Type de véhicule : Berline - Nombre de portes : 3 - Nombre de sièges : 4 N'hésitez pas à me contacter pour plus d'informations, véhicule sort très peu et très bien entretenu. Prix négoc | AO88: Dommages : Excellent état (proche du neuf) ; Sellerie : Tissu ; Permis : Avec permis ; Importé : false | AP88: Voir | AQ88: 3288262834
A89: Citroën Saxo VTS 16V | B89: Saxo vts trackday | E89: En vente | F89: 46310 | G89: 46310 | H89: 46310 | J89: =IF(OR(ISNUMBER(F89),ISNUMBER(G89)),IF(ISNUMBER(I89),I89,H89)-IF(ISNUMBER(F89),F89,G89),"") | K89: 7000 | L89: 7000 | M89: =IF(AND(ISNUMBER(K89),ISNUMBER(L89),K89>0),1-L89/K89,"") | N89: 0 | R89: =IF(AND(ISNUMBER(L89),ISNUMBER(P89),ISNUMBER(Q89)),L89/((P89+Q89)/2)-1,"") | T89: 240000 | U89: 1999 | V89: 11/1999 | W89: Essence | X89: Manuelle | Y89: 118 | Z89: 8 | AA89: Autre | AB89: 3 | AC89: Berline | AF89: Particulier | AG89: Arzacq-Arraziguet | AH89: 64410 | AI89: Pyrénées-Atlantiques | AJ89: Aquitaine | AK89: 2 | AM89: Non | AN89: Bonjour, Je vend cette saxo vts 16v (vrais pas de swap) Culasse c2 vts Papillon clio 2 rs Collecteur c2 vts Bilstein b8 avant ar Train arrière sur sylimbloc renforcer Admission saxo challenge Collecteur 4 2 1 Ligne groupe n Frein à main hydraulique Short shift Arceaux 6 point boulonner 2 baquet Barre anti rapprochement avant inf et supp Boitier omex Ct + de 6 mois mais peut être repassé pour la vente (en contre visite) Cg a mon nom | AO89: Permis : Avec permis ; Importé : false | AP89: Voir | AQ89: 3288655322
A90: Citroën Saxo VTS 16V | B90: Saxo VTS 1.6l 16s | E90: En vente | F90: 46281 | G90: 46281 | H90: 46296 | J90: =IF(OR(ISNUMBER(F90),ISNUMBER(G90)),IF(ISNUMBER(I90),I90,H90)-IF(ISNUMBER(F90),F90,G90),"") | K90: 10500 | L90: 10500 | M90: =IF(AND(ISNUMBER(K90),ISNUMBER(L90),K90>0),1-L90/K90,"") | N90: 0 | R90: =IF(AND(ISNUMBER(L90),ISNUMBER(P90),ISNUMBER(Q90)),L90/((P90+Q90)/2)-1,"") | T90: 150500 | U90: 2000 | W90: Essence | X90: Manuelle | Y90: 118 | Z90: 8 | AA90: Autre | AB90: 3 | AC90: Berline | AF90: Particulier | AG90: Chassiers | AH90: 07110 | AI90: Ardèche | AJ90: Rhône-Alpes | AP90: Voir | AQ90: 3198012563
A91: Citroën Saxo VTS 16V | B91: Citroen saxo vts 16v | E91: En vente | F91: 46249 | G91: 46249 | H91: 46296 | J91: =IF(OR(ISNUMBER(F91),ISNUMBER(G91)),IF(ISNUMBER(I91),I91,H91)-IF(ISNUMBER(F91),F91,G91),"") | K91: 6700 | L91: 6700 | M91: =IF(AND(ISNUMBER(K91),ISNUMBER(L91),K91>0),1-L91/K91,"") | N91: 0 | R91: =IF(AND(ISNUMBER(L91),ISNUMBER(P91),ISNUMBER(Q91)),L91/((P91+Q91)/2)-1,"") | T91: 232000 | U91: 2001 | W91: Essence | X91: Manuelle | Y91: 120 | Z91: 8 | AA91: Noir | AB91: 3 | AC91: Berline | AF91: Particulier | AG91: Méry-ès-Bois | AH91: 18380 | AI91: Cher | AJ91: Centre | AP91: Voir | AQ91: 3217942758
A92: Citroën Saxo VTS 16V | B92: Saxo vts 1l6 | E92: En vente | F92: 46248 | G92: 46248 | H92: 46296 | J92: =IF(OR(ISNUMBER(F92),ISNUMBER(G92)),IF(ISNUMBER(I92),I92,H92)-IF(ISNUMBER(F92),F92,G92),"") | K92: 3000 | L92: 3000 | M92: =IF(AND(ISNUMBER(K92),ISNUMBER(L92),K92>0),1-L92/K92,"") | N92: 0 | R92: =IF(AND(ISNUMBER(L92),ISNUMBER(P92),ISNUMBER(Q92)),L92/((P92+Q92)/2)-1,"") | T92: 213500 | U92: 1999 | W92: Essence | X92: Manuelle | Y92: 90 | Z92: 6 | AA92: Noir | AB92: 3 | AC92: Coupe | AF92: Particulier | AG92: Forges-les-Eaux | AH92: 76440 | AI92: Seine-Maritime | AJ92: Haute-Normandie | AP92: Voir | AQ92: 3249782225
A93: Citroën Saxo VTS 16V | B93: Saxo VTS | E93: En vente | F93: 46250 | G93: 46250 | H93: 46296 | J93: =IF(OR(ISNUMBER(F93),ISNUMBER(G93)),IF(ISNUMBER(I93),I93,H93)-IF(ISNUMBER(F93),F93,G93),"") | K93: 8000 | L93: 8000 | M93: =IF(AND(ISNUMBER(K93),ISNUMBER(L93),K93>0),1-L93/K93,"") | N93: 0 | R93: =IF(AND(ISNUMBER(L93),ISNUMBER(P93),ISNUMBER(Q93)),L93/((P93+Q93)/2)-1,"") | T93: 200000 | U93: 1999 | W93: Essence | X93: Manuelle | Y93: 75 | Z93: 5 | AA93: Jaune | AB93: 3 | AC93: Berline | AF93: Particulier | AG93: Cholet | AH93: 49300 | AI93: Maine-et-Loire | AJ93: Pays de la Loire | AP93: Voir | AQ93: 3250813636
A94: Citroën Saxo VTS 16V | B94: Saxo VTS 1.4 75cv | E94: En vente | F94: 46252 | G94: 46252 | H94: 46296 | J94: =IF(OR(ISNUMBER(F94),ISNUMBER(G94)),IF(ISNUMBER(I94),I94,H94)-IF(ISNUMBER(F94),F94,G94),"") | K94: 3000 | L94: 3000 | M94: =IF(AND(ISNUMBER(K94),ISNUMBER(L94),K94>0),1-L94/K94,"") | N94: 0 | R94: =IF(AND(ISNUMBER(L94),ISNUMBER(P94),ISNUMBER(Q94)),L94/((P94+Q94)/2)-1,"") | T94: 263848 | U94: 1998 | W94: Essence | X94: Manuelle | Y94: 75 | Z94: 5 | AA94: Rouge | AB94: 3 | AC94: Berline | AF94: Particulier | AG94: Condé-sur-l'Escaut | AH94: 59163 | AI94: Nord | AJ94: Nord-Pas-de-Calais | AP94: Voir | AQ94: 3252260409
A95: Citroën Saxo VTS 16V | B95: Citröen Saxo VTS 16v | E95: En vente | F95: 46254 | G95: 46254 | H95: 46296 | J95: =IF(OR(ISNUMBER(F95),ISNUMBER(G95)),IF(ISNUMBER(I95),I95,H95)-IF(ISNUMBER(F95),F95,G95),"") | K95: 12900 | L95: 12900 | M95: =IF(AND(ISNUMBER(K95),ISNUMBER(L95),K95>0),1-L95/K95,"") | N95: 0 | R95: =IF(AND(ISNUMBER(L95),ISNUMBER(P95),ISNUMBER(Q95)),L95/((P95+Q95)/2)-1,"") | T95: 166000 | U95: 1999 | W95: Essence | X95: Manuelle | Y95: 118 | Z95: 8 | AA95: Autre | AB95: 3 | AC95: Berline | AF95: Particulier | AG95: Sallanches | AH95: 74700 | AI95: Haute-Savoie | AJ95: Rhône-Alpes | AP95: Voir | AQ95: 3253410252
A96: Citroën Saxo VTS 16V | B96: Saxo vts | E96: En vente | F96: 46255 | G96: 46255 | H96: 46296 | J96: =IF(OR(ISNUMBER(F96),ISNUMBER(G96)),IF(ISNUMBER(I96),I96,H96)-IF(ISNUMBER(F96),F96,G96),"") | K96: 3000 | L96: 3000 | M96: =IF(AND(ISNUMBER(K96),ISNUMBER(L96),K96>0),1-L96/K96,"") | N96: 0 | R96: =IF(AND(ISNUMBER(L96),ISNUMBER(P96),ISNUMBER(Q96)),L96/((P96+Q96)/2)-1,"") | T96: 170000 | U96: 1999 | W96: Essence | X96: Manuelle | Y96: 75 | Z96: 5 | AA96: Blanc | AB96: 3 | AC96: Berline | AF96: Particulier | AG96: Delme | AH96: 57590 | AI96: Moselle | AJ96: Lorraine | AP96: Voir | AQ96: 3253798936
A97: Citroën Saxo VTS 16V | B97: Citroën Saxo Vts 1.6 8s | E97: En vente | F97: 46264 | G97: 46264 | H97: 46296 | J97: =IF(OR(ISNUMBER(F97),ISNUMBER(G97)),IF(ISNUMBER(I97),I97,H97)-IF(ISNUMBER(F97),F97,G97),"") | K97: 5990 | L97: 5990 | M97: =IF(AND(ISNUMBER(K97),ISNUMBER(L97),K97>0),1-L97/K97,"") | N97: 0 | R97: =IF(AND(ISNUMBER(L97),ISNUMBER(P97),ISNUMBER(Q97)),L97/((P97+Q97)/2)-1,"") | T97: 183500 | U97: 1997 | W97: Essence | X97: Manuelle | Y97: 88 | Z97: 7 | AA97: Bleu | AB97: 3 | AC97: Berline | AF97: Particulier | AG97: Toulouse | AH97: 31000 | AI97: Haute-Garonne | AJ97: Midi-Pyrénées | AP97: Voir | AQ97: 3259437359
A98: Citroën Saxo VTS 16V | B98: Saxo vts | E98: En vente | F98: 46287 | G98: 46287 | H98: 46296 | J98: =IF(OR(ISNUMBER(F98),ISNUMBER(G98)),IF(ISNUMBER(I98),I98,H98)-IF(ISNUMBER(F98),F98,G98),"") | K98: 8000 | L98: 8000 | M98: =IF(AND(ISNUMBER(K98),ISNUMBER(L98),K98>0),1-L98/K98,"") | N98: 0 | R98: =IF(AND(ISNUMBER(L98),ISNUMBER(P98),ISNUMBER(Q98)),L98/((P98+Q98)/2)-1,"") | T98: 188000 | U98: 1997 | W98: Essence | X98: Manuelle | Y98: 120 | Z98: 8 | AA98: Noir | AB98: 3 | AC98: Berline | AF98: Particulier | AG98: Pouilly-sur-Serre | AH98: 02270 | AI98: Aisne | AJ98: Picardie | AP98: Voir | AQ98: 3274786995
A99: Citroën Saxo VTS 16V | B99: Saxo vts | E99: En vente | F99: 46289 | G99: 46289 | H99: 46296 | J99: =IF(OR(ISNUMBER(F99),ISNUMBER(G99)),IF(ISNUMBER(I99),I99,H99)-IF(ISNUMBER(F99),F99,G99),"") | K99: 5250 | L99: 5250 | M99: =IF(AND(ISNUMBER(K99),ISNUMBER(L99),K99>0),1-L99/K99,"") | N99: 0 | R99: =IF(AND(ISNUMBER(L99),ISNUMBER(P99),ISNUMBER(Q99)),L99/((P99+Q99)/2)-1,"") | T99: 224000 | U99: 2001 | W99: Essence | X99: Manuelle | Y99: 100 | Z99: 6 | AA99: Autre | AB99: 3 | AC99: Berline | AF99: Particulier | AG99: Renage | AH99: 38140 | AI99: Isère | AJ99: Rhône-Alpes | AP99: Voir | AQ99: 3275584509
A100: Citroën Saxo VTS 16V | B100: Saxo vts | E100: En vente | F100: 46292 | G100: 46292 | H100: 46296 | J100: =IF(OR(ISNUMBER(F100),ISNUMBER(G100)),IF(ISNUMBER(I100),I100,H100)-IF(ISNUMBER(F100),F100,G100),"") | K100: 4000 | L100: 4000 | M100: =IF(AND(ISNUMBER(K100),ISNUMBER(L100),K100>0),1-L100/K100,"") | N100: 0 | R100: =IF(AND(ISNUMBER(L100),ISNUMBER(P100),ISNUMBER(Q100)),L100/((P100+Q100)/2)-1,"") | T100: 266000 | U100: 2001 | W100: Essence | X100: Manuelle | Y100: 75 | Z100: 5 | AA100: Gris | AB100: 3 | AC100: Berline | AF100: Particulier | AG100: Le Cellier | AH100: 44850 | AI100: Loire-Atlantique | AJ100: Pays de la Loire | AP100: Voir | AQ100: 3277544949
...

Sheet Historique des prix
A1: Véhicule | B1: Id annonce | C1: Titre | D1: Date | E1: Prix | F1: Évolution vs prix précédent | G1: Annonce
A2: Alfa Romeo 156 2.5 V6 24V | B2: 2903975057 | C2: Alfa Roméo 156 SW V6 2,5l 24s | D2: 46296 | E2: 7500 | F2: =IF(AND($B2=$B1,ISNUMBER(E1),E1>0),E2/E1-1,"") | G2: Voir
A3: Alfa Romeo 156 2.5 V6 24V | B3: 3212500586 | C3: ALFA ROMEO 156 2.5 V6 24V BOÎTE AUTOMATIQUE 195cv COMPLÈTEMENT RÉVISÉ | D3: 46296 | E3: 4900 | F3: =IF(AND($B3=$B2,ISNUMBER(E2),E2>0),E3/E2-1,"") | G3: Voir
A4: Alfa Romeo 156 2.5 V6 24V | B4: 3222893175 | C4: Alfa Romeo 156 2.5 V6 Busso | D4: 46296 | E4: 8800 | F4: =IF(AND($B4=$B3,ISNUMBER(E3),E3>0),E4/E3-1,"") | G4: Voir
A5: Alfa Romeo 156 2.5 V6 24V | B5: 3237198858 | C5: Alfa romeo 156 2.5 v6 24v | D5: 46296 | E5: 6490 | F5: =IF(AND($B5=$B4,ISNUMBER(E4),E4>0),E5/E4-1,"") | G5: Voir
A6: Alfa Romeo 156 2.5 V6 24V | B6: 3261414202 | C6: Alfa 156 2.5 v6 GPL | D6: 46296 | E6: 3200 | F6: =IF(AND($B6=$B5,ISNUMBER(E5),E5>0),E6/E5-1,"") | G6: Voir
A7: Alfa Romeo 156 2.5 V6 24V | B7: 3262191550 | C7: Alfa romeo 166 v6 busso 2003 | D7: 46296 | E7: 4390 | F7: =IF(AND($B7=$B6,ISNUMBER(E6),E6>0),E7/E6-1,"") | G7: Voir
A8: Alfa Romeo 156 2.5 V6 24V | B8: 3270896149 | C8: Alfa Romeo 156 2.5 V6 24V | D8: 46296 | E8: 7000 | F8: =IF(AND($B8=$B7,ISNUMBER(E7),E7>0),E8/E7-1,"") | G8: Voir
A9: Alfa Romeo 156 2.5 V6 24V | B9: 3275564839 | C9: Alfa Romeo 156 v6 SW 2.5 | D9: 46296 | E9: 4000 | F9: =IF(AND($B9=$B8,ISNUMBER(E8),E8>0),E9/E8-1,"") | G9: Voir
A10: Alfa Romeo 156 2.5 V6 24V | B10: 3281190008 | C10: Alfa Romeo 156 2.5 V6 Busso Rouge 1997 | D10: 46310 | E10: 14900 | F10: =IF(AND($B10=$B9,ISNUMBER(E9),E9>0),E10/E9-1,"") | G10: Voir
A11: Alfa Romeo 156 2.5 V6 24V | B11: 3283116401 | C11: Alfa Romeo 156 2.5 V6 24V | D11: 46310 | E11: 7800 | F11: =IF(AND($B11=$B10,ISNUMBER(E10),E10>0),E11/E10-1,"") | G11: Voir
A12: BMW Z3 1.9i / 2.0i | B12: 3171562700 | C12: BMW Z3 1.9i 140ch Pack M Sport tbé Cuir Clim | D12: 46296 | E12: 8990 | F12: =IF(AND($B12=$B11,ISNUMBER(E11),E11>0),E12/E11-1,"") | G12: Voir
A13: BMW Z3 1.9i / 2.0i | B13: 3197947364 | C13: Bmw z3 1.8 roadster GARANTIE | D13: 46296 | E13: 11490 | F13: =IF(AND($B13=$B12,ISNUMBER(E12),E12>0),E13/E12-1,"") | G13: Voir
... A726: Volkswagen Golf IV GTI 25th Anniversary | B726: 3284612097 | C726: Golf 4 gti 25 | D726: 46310 | E726: 11000 | F726: =IF(AND($B726=$B725,ISNUMBER(E725),E725>0),E726/E725-1,"") | G726: Voir

Sheet Par année-modèle
A1: Annonces en vente, par véhicule et année-modèle (formules sur l'onglet Annonces)
A2: Véhicule | B2: Année-modèle | C2: Annonces | D2: Prix moyen | E2: Prix le plus bas | F2: Prix le plus haut | G2: Km moyen
A3: Alfa Romeo 156 2.5 V6 24V | B3: 1997 | C3: =COUNTIFS(Annonces!$A$2:$A$701,$A3,Annonces!$E$2:$E$701,"En vente",Annonces!$U$2:$U$701,$B3) | D3: =IFERROR(AVERAGEIFS(Annonces!$L$2:$L$701,Annonces!$A$2:$A$701,$A3,Annonces!$E$2:$E$701,"En vente",Annonces!$U$2:$U$701,$B3),"") | E3: =IF(C3>0,_xlfn.MINIFS(Annonces!$L$2:$L$701,Annonces!$A$2:$A$701,$A3,Annonces!$E$2:$E$701,"En vente",Annonces!$U$2:$U$701,$B3),"") | F3: =IF(C3>0,_xlfn.MAXIFS(Annonces!$L$2:$L$701,Annonces!$A$2:$A$701,$A3,Annonces!$E$2:$E$701,"En vente",Annonces!$U$2:$U$701,$B3),"") | G3: =IFERROR(AVERAGEIFS(Annonces!$T$2:$T$701,Annonces!$A$2:$A$701,$A3,Annonces!$E$2:$E$701,"En vente",Annonces!$U$2:$U$701,$B3),"")
A4: Alfa Romeo 156 2.5 V6 24V | B4: 1998 | C4: =COUNTIFS(Annonces!$A$2:$A$701,$A4,Annonces!$E$2:$E$701,"En vente",Annonces!$U$2:$U$701,$B4) | D4: =IFERROR(AVERAGEIFS(Annonces!$L$2:$L$701,Annonces!$A$2:$A$701,$A4,Annonces!$E$2:$E$701,"En vente",Annonces!$U$2:$U$701,$B4),"") | E4: =IF(C4>0,_xlfn.MINIFS(Annonces!$L$2:$L$701,Annonces!$A$2:$A$701,$A4,Annonces!$E$2:$E$701,"En vente",Annonces!$U$2:$U$701,$B4),"") | F4: =IF(C4>0,_xlfn.MAXIFS(Annonces!$L$2:$L$701,Annonces!$A$2:$A$701,$A4,Annonces!$E$2:$E$701,"En vente",Annonces!$U$2:$U$701,$B4),"") | G4: =IFERROR(AVERAGEIFS(Annonces!$T$2:$T$701,Annonces!$A$2:$A$701,$A4,Annonces!$E$2:$E$701,"En vente",Annonces!$U$2:$U$701,$B4),"")
A5: Alfa Romeo 156 2.5 V6 24V | B5: 1999 | C5: =COUNTIFS(Annonces!$A$2:$A$701,$A5,Annonces!$E$2:$E$701,"En vente",Annonces!$U$2:$U$701,$B5) | D5: =IFERROR(AVERAGEIFS(Annonces!$L$2:$L$701,Annonces!$A$2:$A$701,$A5,Annonces!$E$2:$E$701,"En vente",Annonces!$U$2:$U$701,$B5),"") | E5: =IF(C5>0,_xlfn.MINIFS(Annonces!$L$2:$L$701,Annonces!$A$2:$A$701,$A5,Annonces!$E$2:$E$701,"En vente",Annonces!$U$2:$U$701,$B5),"") | F5: =IF(C5>0,_xlfn.MAXIFS(Annonces!$L$2:$L$701,Annonces!$A$2:$A$701,$A5,Annonces!$E$2:$E$701,"En vente",Annonces!$U$2:$U$701,$B5),"") | G5: =IFERROR(AVERAGEIFS(Annonces!$T$2:$T$701,Annonces!$A$2:$A$701,$A5,Annonces!$E$2:$E$701,"En vente",Annonces!$U$2:$U$701,$B5),"")
A6: Alfa Romeo 156 2.5 V6 24V | B6: 2001 | C6: =COUNTIFS(Annonces!$A$2:$A$701,$A6,Annonces!$E$2:$E$701,"En vente",Annonces!$U$2:$U$701,$B6) | D6: =IFERROR(AVERAGEIFS(Annonces!$L$2:$L$701,Annonces!$A$2:$A$701,$A6,Annonces!$E$2:$E$701,"En vente",Annonces!$U$2:$U$701,$B6),"") | E6: =IF(C6>0,_xlfn.MINIFS(Annonces!$L$2:$L$701,Annonces!$A$2:$A$701,$A6,Annonces!$E$2:$E$701,"En vente",Annonces!$U$2:$U$701,$B6),"") | F6: =IF(C6>0,_xlfn.MAXIFS(Annonces!$L$2:$L$701,Annonces!$A$2:$A$701,$A6,Annonces!$E$2:$E$701,"En vente",Annonces!$U$2:$U$701,$B6),"") | G6: =IFERROR(AVERAGEIFS(Annonces!$T$2:$T$701,Annonces!$A$2:$A$701,$A6,Annonces!$E$2:$E$701,"En vente",Annonces!$U$2:$U$701,$B6),"")
A7: Alfa Romeo 156 2.5 V6 24V | B7: 2002 | C7: =COUNTIFS(Annonces!$A$2:$A$701,$A7,Annonces!$E$2:$E$701,"En vente",Annonces!$U$2:$U$701,$B7) | D7: =IFERROR(AVERAGEIFS(Annonces!$L$2:$L$701,Annonces!$A$2:$A$701,$A7,Annonces!$E$2:$E$701,"En vente",Annonces!$U$2:$U$701,$B7),"") | E7: =IF(C7>0,_xlfn.MINIFS(Annonces!$L$2:$L$701,Annonces!$A$2:$A$701,$A7,Annonces!$E$2:$E$701,"En vente",Annonces!$U$2:$U$701,$B7),"") | F7: =IF(C7>0,_xlfn.MAXIFS(Annonces!$L$2:$L$701,Annonces!$A$2:$A$701,$A7,Annonces!$E$2:$E$701,"En vente",Annonces!$U$2:$U$701,$B7),"") | G7: =IFERROR(AVERAGEIFS(Annonces!$T$2:$T$701,Annonces!$A$2:$A$701,$A7,Annonces!$E$2:$E$701,"En vente",Annonces!$U$2:$U$701,$B7),"")
A8: Alfa Romeo 156 2.5 V6 24V | B8: 2003 | C8: =COUNTIFS(Annonces!$A$2:$A$701,$A8,Annonces!$E$2:$E$701,"En vente",Annonces!$U$2:$U$701,$B8) | D8: =IFERROR(AVERAGEIFS(Annonces!$L$2:$L$701,Annonces!$A$2:$A$701,$A8,Annonces!$E$2:$E$701,"En vente",Annonces!$U$2:$U$701,$B8),"") | E8: =IF(C8>0,_xlfn.MINIFS(Annonces!$L$2:$L$701,Annonces!$A$2:$A$701,$A8,Annonces!$E$2:$E$701,"En vente",Annonces!$U$2:$U$701,$B8),"") | F8: =IF(C8>0,_xlfn.MAXIFS(Annonces!$L$2:$L$701,Annonces!$A$2:$A$701,$A8,Annonces!$E$2:$E$701,"En vente",Annonces!$U$2:$U$701,$B8),"") | G8: =IFERROR(AVERAGEIFS(Annonces!$T$2:$T$701,Annonces!$A$2:$A$701,$A8,Annonces!$E$2:$E$701,"En vente",Annonces!$U$2:$U$701,$B8),"")
A9: Alfa Romeo 156 2.5 V6 24V | B9: 2004 | C9: =COUNTIFS(Annonces!$A$2:$A$701,$A9,Annonces!$E$2:$E$701,"En vente",Annonces!$U$2:$U$701,$B9) | D9: =IFERROR(AVERAGEIFS(Annonces!$L$2:$L$701,Annonces!$A$2:$A$701,$A9,Annonces!$E$2:$E$701,"En vente",Annonces!$U$2:$U$701,$B9),"") | E9: =IF(C9>0,_xlfn.MINIFS(Annonces!$L$2:$L$701,Annonces!$A$2:$A$701,$A9,Annonces!$E$2:$E$701,"En vente",Annonces!$U$2:$U$701,$B9),"") | F9: =IF(C9>0,_xlfn.MAXIFS(Annonces!$L$2:$L$701,Annonces!$A$2:$A$701,$A9,Annonces!$E$2:$E$701,"En vente",Annonces!$U$2:$U$701,$B9),"") | G9: =IFERROR(AVERAGEIFS(Annonces!$T$2:$T$701,Annonces!$A$2:$A$701,$A9,Annonces!$E$2:$E$701,"En vente",Annonces!$U$2:$U$701,$B9),"")
A10: BMW Z3 1.9i / 2.0i | B10: 1996 | C10: =COUNTIFS(Annonces!$A$2:$A$701,$A10,Annonces!$E$2:$E$701,"En vente",Annonces!$U$2:$U$701,$B10) | D10: =IFERROR(AVERAGEIFS(Annonces!$L$2:$L$701,Annonces!$A$2:$A$701,$A10,Annonces!$E$2:$E$701,"En vente",Annonces!$U$2:$U$701,$B10),"") | E10: =IF(C10>0,_xlfn.MINIFS(Annonces!$L$2:$L$701,Annonces!$A$2:$A$701,$A10,Annonces!$E$2:$E$701,"En vente",Annonces!$U$2:$U$701,$B10),"") | F10: =IF(C10>0,_xlfn.MAXIFS(Annonces!$L$2:$L$701,Annonces!$A$2:$A$701,$A10,Annonces!$E$2:$E$701,"En vente",Annonces!$U$2:$U$701,$B10),"") | G10: =IFERROR(AVERAGEIFS(Annonces!$T$2:$T$701,Annonces!$A$2:$A$701,$A10,Annonces!$E$2:$E$701,"En vente",Annonces!$U$2:$U$701,$B10),"")
A11: BMW Z3 1.9i / 2.0i | B11: 1997 | C11: =COUNTIFS(Annonces!$A$2:$A$701,$A11,Annonces!$E$2:$E$701,"En vente",Annonces!$U$2:$U$701,$B11) | D11: =IFERROR(AVERAGEIFS(Annonces!$L$2:$L$701,Annonces!$A$2:$A$701,$A11,Annonces!$E$2:$E$701,"En vente",Annonces!$U$2:$U$701,$B11),"") | E11: =IF(C11>0,_xlfn.MINIFS(Annonces!$L$2:$L$701,Annonces!$A$2:$A$701,$A11,Annonces!$E$2:$E$701,"En vente",Annonces!$U$2:$U$701,$B11),"") | F11: =IF(C11>0,_xlfn.MAXIFS(Annonces!$L$2:$L$701,Annonces!$A$2:$A$701,$A11,Annonces!$E$2:$E$701,"En vente",Annonces!$U$2:$U$701,$B11),"") | G11: =IFERROR(AVERAGEIFS(Annonces!$T$2:$T$701,Annonces!$A$2:$A$701,$A11,Annonces!$E$2:$E$701,"En vente",Annonces!$U$2:$U$701,$B11),"")
A12: BMW Z3 1.9i / 2.0i | B12: 1998 | C12: =COUNTIFS(Annonces!$A$2:$A$701,$A12,Annonces!$E$2:$E$701,"En vente",Annonces!$U$2:$U$701,$B12) | D12: =IFERROR(AVERAGEIFS(Annonces!$L$2:$L$701,Annonces!$A$2:$A$701,$A12,Annonces!$E$2:$E$701,"En vente",Annonces!$U$2:$U$701,$B12),"") | E12: =IF(C12>0,_xlfn.MINIFS(Annonces!$L$2:$L$701,Annonces!$A$2:$A$701,$A12,Annonces!$E$2:$E$701,"En vente",Annonces!$U$2:$U$701,$B12),"") | F12: =IF(C12>0,_xlfn.MAXIFS(Annonces!$L$2:$L$701,Annonces!$A$2:$A$701,$A12,Annonces!$E$2:$E$701,"En vente",Annonces!$U$2:$U$701,$B12),"") | G12: =IFERROR(AVERAGEIFS(Annonces!$T$2:$T$701,Annonces!$A$2:$A$701,$A12,Annonces!$E$2:$E$701,"En vente",Annonces!$U$2:$U$701,$B12),"")
A13: BMW Z3 1.9i / 2.0i | B13: 1999 | C13: =COUNTIFS(Annonces!$A$2:$A$701,$A13,Annonces!$E$2:$E$701,"En vente",Annonces!$U$2:$U$701,$B13) | D13: =IFERROR(AVERAGEIFS(Annonces!$L$2:$L$701,Annonces!$A$2:$A$701,$A13,Annonces!$E$2:$E$701,"En vente",Annonces!$U$2:$U$701,$B13),"") | E13: =IF(C13>0,_xlfn.MINIFS(Annonces!$L$2:$L$701,Annonces!$A$2:$A$701,$A13,Annonces!$E$2:$E$701,"En vente",Annonces!$U$2:$U$701,$B13),"") | F13: =IF(C13>0,_xlfn.MAXIFS(Annonces!$L$2:$L$701,Annonces!$A$2:$A$701,$A13,Annonces!$E$2:$E$701,"En vente",Annonces!$U$2:$U$701,$B13),"") | G13: =IFERROR(AVERAGEIFS(Annonces!$T$2:$T$701,Annonces!$A$2:$A$701,$A13,Annonces!$E$2:$E$701,"En vente",Annonces!$U$2:$U$701,$B13),"")
A14: BMW Z3 1.9i / 2.0i | B14: 2000 | C14: =COUNTIFS(Annonces!$A$2:$A$701,$A14,Annonces!$E$2:$E$701,"En vente",Annonces!$U$2:$U$701,$B14) | D14: =IFERROR(AVERAGEIFS(Annonces!$L$2:$L$701,Annonces!$A$2:$A$701,$A14,Annonces!$E$2:$E$701,"En vente",Annonces!$U$2:$U$701,$B14),"") | E14: =IF(C14>0,_xlfn.MINIFS(Annonces!$L$2:$L$701,Annonces!$A$2:$A$701,$A14,Annonces!$E$2:$E$701,"En vente",Annonces!$U$2:$U$701,$B14),"") | F14: =IF(C14>0,_xlfn.MAXIFS(Annonces!$L$2:$L$701,Annonces!$A$2:$A$701,$A14,Annonces!$E$2:$E$701,"En vente",Annonces!$U$2:$U$701,$B14),"") | G14: =IFERROR(AVERAGEIFS(Annonces!$T$2:$T$701,Annonces!$A$2:$A$701,$A14,Annonces!$E$2:$E$701,"En vente",Annonces!$U$2:$U$701,$B14),"")
... A115: Volkswagen Golf IV GTI 25th Anniversary | B115: 2001 | C115: =COUNTIFS(Annonces!$A$2:$A$701,$A115,Annonces!$E$2:$E$701,"En vente",Annonces!$U$2:$U$701,$B115) | D115: =IFERROR(AVERAGEIFS(Annonces!$L$2:$L$701,Annonces!$A$2:$A$701,$A115,Annonces!$E$2:$E$701,"En vente",Annonces!$U$2:$U$701,$B115),"") | E115: =IF(C115>0,_xlfn.MINIFS(Annonces!$L$2:$L$701,Annonces!$A$2:$A$701,$A115,Annonces!$E$2:$E$701,"En vente",Annonces!$U$2:$U$701,$B115),"") | F115: =IF(C115>0,_xlfn.MAXIFS(Annonces!$L$2:$L$701,Annonces!$A$2:$A$701,$A115,Annonces!$E$2:$E$701,"En vente",Annonces!$U$2:$U$701,$B115),"") | G115: =IFERROR(AVERAGEIFS(Annonces!$T$2:$T$701,Annonces!$A$2:$A$701,$A115,Annonces!$E$2:$E$701,"En vente",Annonces!$U$2:$U$701,$B115),"")

Sheet Par kilométrage
A1: Annonces en vente, par véhicule et tranche de km (formules sur l'onglet Annonces)
A2: Véhicule | B2: Tranche de km | C2: Annonces | D2: Prix moyen | E2: Prix le plus bas | F2: Prix le plus haut | G2: Km moyen | H2: Km min | I2: Km max (exclu)
A3: Alfa Romeo 156 2.5 V6 24V | B3: < 100 000 km | C3: =COUNTIFS(Annonces!$A$2:$A$701,$A3,Annonces!$E$2:$E$701,"En vente",Annonces!$T$2:$T$701,">="&$H3,Annonces!$T$2:$T$701,"<"&$I3) | D3: =IFERROR(AVERAGEIFS(Annonces!$L$2:$L$701,Annonces!$A$2:$A$701,$A3,Annonces!$E$2:$E$701,"En vente",Annonces!$T$2:$T$701,">="&$H3,Annonces!$T$2:$T$701,"<"&$I3),"") | E3: =IF(C3>0,_xlfn.MINIFS(Annonces!$L$2:$L$701,Annonces!$A$2:$A$701,$A3,Annonces!$E$2:$E$701,"En vente",Annonces!$T$2:$T$701,">="&$H3,Annonces!$T$2:$T$701,"<"&$I3),"") | F3: =IF(C3>0,_xlfn.MAXIFS(Annonces!$L$2:$L$701,Annonces!$A$2:$A$701,$A3,Annonces!$E$2:$E$701,"En vente",Annonces!$T$2:$T$701,">="&$H3,Annonces!$T$2:$T$701,"<"&$I3),"") | G3: =IFERROR(AVERAGEIFS(Annonces!$T$2:$T$701,Annonces!$A$2:$A$701,$A3,Annonces!$E$2:$E$701,"En vente",Annonces!$T$2:$T$701,">="&$H3,Annonces!$T$2:$T$701,"<"&$I3),"") | H3: 0 | I3: 100000
A4: Alfa Romeo 156 2.5 V6 24V | B4: 150 000 – 200 000 km | C4: =COUNTIFS(Annonces!$A$2:$A$701,$A4,Annonces!$E$2:$E$701,"En vente",Annonces!$T$2:$T$701,">="&$H4,Annonces!$T$2:$T$701,"<"&$I4) | D4: =IFERROR(AVERAGEIFS(Annonces!$L$2:$L$701,Annonces!$A$2:$A$701,$A4,Annonces!$E$2:$E$701,"En vente",Annonces!$T$2:$T$701,">="&$H4,Annonces!$T$2:$T$701,"<"&$I4),"") | E4: =IF(C4>0,_xlfn.MINIFS(Annonces!$L$2:$L$701,Annonces!$A$2:$A$701,$A4,Annonces!$E$2:$E$701,"En vente",Annonces!$T$2:$T$701,">="&$H4,Annonces!$T$2:$T$701,"<"&$I4),"") | F4: =IF(C4>0,_xlfn.MAXIFS(Annonces!$L$2:$L$701,Annonces!$A$2:$A$701,$A4,Annonces!$E$2:$E$701,"En vente",Annonces!$T$2:$T$701,">="&$H4,Annonces!$T$2:$T$701,"<"&$I4),"") | G4: =IFERROR(AVERAGEIFS(Annonces!$T$2:$T$701,Annonces!$A$2:$A$701,$A4,Annonces!$E$2:$E$701,"En vente",Annonces!$T$2:$T$701,">="&$H4,Annonces!$T$2:$T$701,"<"&$I4),"") | H4: 150000 | I4: 200000
A5: Alfa Romeo 156 2.5 V6 24V | B5: ≥ 200 000 km | C5: =COUNTIFS(Annonces!$A$2:$A$701,$A5,Annonces!$E$2:$E$701,"En vente",Annonces!$T$2:$T$701,">="&$H5,Annonces!$T$2:$T$701,"<"&$I5) | D5: =IFERROR(AVERAGEIFS(Annonces!$L$2:$L$701,Annonces!$A$2:$A$701,$A5,Annonces!$E$2:$E$701,"En vente",Annonces!$T$2:$T$701,">="&$H5,Annonces!$T$2:$T$701,"<"&$I5),"") | E5: =IF(C5>0,_xlfn.MINIFS(Annonces!$L$2:$L$701,Annonces!$A$2:$A$701,$A5,Annonces!$E$2:$E$701,"En vente",Annonces!$T$2:$T$701,">="&$H5,Annonces!$T$2:$T$701,"<"&$I5),"") | F5: =IF(C5>0,_xlfn.MAXIFS(Annonces!$L$2:$L$701,Annonces!$A$2:$A$701,$A5,Annonces!$E$2:$E$701,"En vente",Annonces!$T$2:$T$701,">="&$H5,Annonces!$T$2:$T$701,"<"&$I5),"") | G5: =IFERROR(AVERAGEIFS(Annonces!$T$2:$T$701,Annonces!$A$2:$A$701,$A5,Annonces!$E$2:$E$701,"En vente",Annonces!$T$2:$T$701,">="&$H5,Annonces!$T$2:$T$701,"<"&$I5),"") | H5: 200000 | I5: 10000000
A6: BMW Z3 1.9i / 2.0i | B6: < 100 000 km | C6: =COUNTIFS(Annonces!$A$2:$A$701,$A6,Annonces!$E$2:$E$701,"En vente",Annonces!$T$2:$T$701,">="&$H6,Annonces!$T$2:$T$701,"<"&$I6) | D6: =IFERROR(AVERAGEIFS(Annonces!$L$2:$L$701,Annonces!$A$2:$A$701,$A6,Annonces!$E$2:$E$701,"En vente",Annonces!$T$2:$T$701,">="&$H6,Annonces!$T$2:$T$701,"<"&$I6),"") | E6: =IF(C6>0,_xlfn.MINIFS(Annonces!$L$2:$L$701,Annonces!$A$2:$A$701,$A6,Annonces!$E$2:$E$701,"En vente",Annonces!$T$2:$T$701,">="&$H6,Annonces!$T$2:$T$701,"<"&$I6),"") | F6: =IF(C6>0,_xlfn.MAXIFS(Annonces!$L$2:$L$701,Annonces!$A$2:$A$701,$A6,Annonces!$E$2:$E$701,"En vente",Annonces!$T$2:$T$701,">="&$H6,Annonces!$T$2:$T$701,"<"&$I6),"") | G6: =IFERROR(AVERAGEIFS(Annonces!$T$2:$T$701,Annonces!$A$2:$A$701,$A6,Annonces!$E$2:$E$701,"En vente",Annonces!$T$2:$T$701,">="&$H6,Annonces!$T$2:$T$701,"<"&$I6),"") | H6: 0 | I6: 100000
A7: BMW Z3 1.9i / 2.0i | B7: 100 000 – 150 000 km | C7: =COUNTIFS(Annonces!$A$2:$A$701,$A7,Annonces!$E$2:$E$701,"En vente",Annonces!$T$2:$T$701,">="&$H7,Annonces!$T$2:$T$701,"<"&$I7) | D7: =IFERROR(AVERAGEIFS(Annonces!$L$2:$L$701,Annonces!$A$2:$A$701,$A7,Annonces!$E$2:$E$701,"En vente",Annonces!$T$2:$T$701,">="&$H7,Annonces!$T$2:$T$701,"<"&$I7),"") | E7: =IF(C7>0,_xlfn.MINIFS(Annonces!$L$2:$L$701,Annonces!$A$2:$A$701,$A7,Annonces!$E$2:$E$701,"En vente",Annonces!$T$2:$T$701,">="&$H7,Annonces!$T$2:$T$701,"<"&$I7),"") | F7: =IF(C7>0,_xlfn.MAXIFS(Annonces!$L$2:$L$701,Annonces!$A$2:$A$701,$A7,Annonces!$E$2:$E$701,"En vente",Annonces!$T$2:$T$701,">="&$H7,Annonces!$T$2:$T$701,"<"&$I7),"") | G7: =IFERROR(AVERAGEIFS(Annonces!$T$2:$T$701,Annonces!$A$2:$A$701,$A7,Annonces!$E$2:$E$701,"En vente",Annonces!$T$2:$T$701,">="&$H7,Annonces!$T$2:$T$701,"<"&$I7),"") | H7: 100000 | I7: 150000
A8: BMW Z3 1.9i / 2.0i | B8: 150 000 – 200 000 km | C8: =COUNTIFS(Annonces!$A$2:$A$701,$A8,Annonces!$E$2:$E$701,"En vente",Annonces!$T$2:$T$701,">="&$H8,Annonces!$T$2:$T$701,"<"&$I8) | D8: =IFERROR(AVERAGEIFS(Annonces!$L$2:$L$701,Annonces!$A$2:$A$701,$A8,Annonces!$E$2:$E$701,"En vente",Annonces!$T$2:$T$701,">="&$H8,Annonces!$T$2:$T$701,"<"&$I8),"") | E8: =IF(C8>0,_xlfn.MINIFS(Annonces!$L$2:$L$701,Annonces!$A$2:$A$701,$A8,Annonces!$E$2:$E$701,"En vente",Annonces!$T$2:$T$701,">="&$H8,Annonces!$T$2:$T$701,"<"&$I8),"") | F8: =IF(C8>0,_xlfn.MAXIFS(Annonces!$L$2:$L$701,Annonces!$A$2:$A$701,$A8,Annonces!$E$2:$E$701,"En vente",Annonces!$T$2:$T$701,">="&$H8,Annonces!$T$2:$T$701,"<"&$I8),"") | G8: =IFERROR(AVERAGEIFS(Annonces!$T$2:$T$701,Annonces!$A$2:$A$701,$A8,Annonces!$E$2:$E$701,"En vente",Annonces!$T$2:$T$701,">="&$H8,Annonces!$T$2:$T$701,"<"&$I8),"") | H8: 150000 | I8: 200000
A9: BMW Z3 1.9i / 2.0i | B9: ≥ 200 000 km | C9: =COUNTIFS(Annonces!$A$2:$A$701,$A9,Annonces!$E$2:$E$701,"En vente",Annonces!$T$2:$T$701,">="&$H9,Annonces!$T$2:$T$701,"<"&$I9) | D9: =IFERROR(AVERAGEIFS(Annonces!$L$2:$L$701,Annonces!$A$2:$A$701,$A9,Annonces!$E$2:$E$701,"En vente",Annonces!$T$2:$T$701,">="&$H9,Annonces!$T$2:$T$701,"<"&$I9),"") | E9: =IF(C9>0,_xlfn.MINIFS(Annonces!$L$2:$L$701,Annonces!$A$2:$A$701,$A9,Annonces!$E$2:$E$701,"En vente",Annonces!$T$2:$T$701,">="&$H9,Annonces!$T$2:$T$701,"<"&$I9),"") | F9: =IF(C9>0,_xlfn.MAXIFS(Annonces!$L$2:$L$701,Annonces!$A$2:$A$701,$A9,Annonces!$E$2:$E$701,"En vente",Annonces!$T$2:$T$701,">="&$H9,Annonces!$T$2:$T$701,"<"&$I9),"") | G9: =IFERROR(AVERAGEIFS(Annonces!$T$2:$T$701,Annonces!$A$2:$A$701,$A9,Annonces!$E$2:$E$701,"En vente",Annonces!$T$2:$T$701,">="&$H9,Annonces!$T$2:$T$701,"<"&$I9),"") | H9: 200000 | I9: 10000000
A10: Citroën Saxo VTS 16V | B10: < 100 000 km | C10: =COUNTIFS(Annonces!$A$2:$A$701,$A10,Annonces!$E$2:$E$701,"En vente",Annonces!$T$2:$T$701,">="&$H10,Annonces!$T$2:$T$701,"<"&$I10) | D10: =IFERROR(AVERAGEIFS(Annonces!$L$2:$L$701,Annonces!$A$2:$A$701,$A10,Annonces!$E$2:$E$701,"En vente",Annonces!$T$2:$T$701,">="&$H10,Annonces!$T$2:$T$701,"<"&$I10),"") | E10: =IF(C10>0,_xlfn.MINIFS(Annonces!$L$2:$L$701,Annonces!$A$2:$A$701,$A10,Annonces!$E$2:$E$701,"En vente",Annonces!$T$2:$T$701,">="&$H10,Annonces!$T$2:$T$701,"<"&$I10),"") | F10: =IF(C10>0,_xlfn.MAXIFS(Annonces!$L$2:$L$701,Annonces!$A$2:$A$701,$A10,Annonces!$E$2:$E$701,"En vente",Annonces!$T$2:$T$701,">="&$H10,Annonces!$T$2:$T$701,"<"&$I10),"") | G10: =IFERROR(AVERAGEIFS(Annonces!$T$2:$T$701,Annonces!$A$2:$A$701,$A10,Annonces!$E$2:$E$701,"En vente",Annonces!$T$2:$T$701,">="&$H10,Annonces!$T$2:$T$701,"<"&$I10),"") | H10: 0 | I10: 100000
A11: Citroën Saxo VTS 16V | B11: 100 000 – 150 000 km | C11: =COUNTIFS(Annonces!$A$2:$A$701,$A11,Annonces!$E$2:$E$701,"En vente",Annonces!$T$2:$T$701,">="&$H11,Annonces!$T$2:$T$701,"<"&$I11) | D11: =IFERROR(AVERAGEIFS(Annonces!$L$2:$L$701,Annonces!$A$2:$A$701,$A11,Annonces!$E$2:$E$701,"En vente",Annonces!$T$2:$T$701,">="&$H11,Annonces!$T$2:$T$701,"<"&$I11),"") | E11: =IF(C11>0,_xlfn.MINIFS(Annonces!$L$2:$L$701,Annonces!$A$2:$A$701,$A11,Annonces!$E$2:$E$701,"En vente",Annonces!$T$2:$T$701,">="&$H11,Annonces!$T$2:$T$701,"<"&$I11),"") | F11: =IF(C11>0,_xlfn.MAXIFS(Annonces!$L$2:$L$701,Annonces!$A$2:$A$701,$A11,Annonces!$E$2:$E$701,"En vente",Annonces!$T$2:$T$701,">="&$H11,Annonces!$T$2:$T$701,"<"&$I11),"") | G11: =IFERROR(AVERAGEIFS(Annonces!$T$2:$T$701,Annonces!$A$2:$A$701,$A11,Annonces!$E$2:$E$701,"En vente",Annonces!$T$2:$T$701,">="&$H11,Annonces!$T$2:$T$701,"<"&$I11),"") | H11: 100000 | I11: 150000
A12: Citroën Saxo VTS 16V | B12: 150 000 – 200 000 km | C12: =COUNTIFS(Annonces!$A$2:$A$701,$A12,Annonces!$E$2:$E$701,"En vente",Annonces!$T$2:$T$701,">="&$H12,Annonces!$T$2:$T$701,"<"&$I12) | D12: =IFERROR(AVERAGEIFS(Annonces!$L$2:$L$701,Annonces!$A$2:$A$701,$A12,Annonces!$E$2:$E$701,"En vente",Annonces!$T$2:$T$701,">="&$H12,Annonces!$T$2:$T$701,"<"&$I12),"") | E12: =IF(C12>0,_xlfn.MINIFS(Annonces!$L$2:$L$701,Annonces!$A$2:$A$701,$A12,Annonces!$E$2:$E$701,"En vente",Annonces!$T$2:$T$701,">="&$H12,Annonces!$T$2:$T$701,"<"&$I12),"") | F12: =IF(C12>0,_xlfn.MAXIFS(Annonces!$L$2:$L$701,Annonces!$A$2:$A$701,$A12,Annonces!$E$2:$E$701,"En vente",Annonces!$T$2:$T$701,">="&$H12,Annonces!$T$2:$T$701,"<"&$I12),"") | G12: =IFERROR(AVERAGEIFS(Annonces!$T$2:$T$701,Annonces!$A$2:$A$701,$A12,Annonces!$E$2:$E$701,"En vente",Annonces!$T$2:$T$701,">="&$H12,Annonces!$T$2:$T$701,"<"&$I12),"") | H12: 150000 | I12: 200000
A13: Citroën Saxo VTS 16V | B13: ≥ 200 000 km | C13: =COUNTIFS(Annonces!$A$2:$A$701,$A13,Annonces!$E$2:$E$701,"En vente",Annonces!$T$2:$T$701,">="&$H13,Annonces!$T$2:$T$701,"<"&$I13) | D13: =IFERROR(AVERAGEIFS(Annonces!$L$2:$L$701,Annonces!$A$2:$A$701,$A13,Annonces!$E$2:$E$701,"En vente",Annonces!$T$2:$T$701,">="&$H13,Annonces!$T$2:$T$701,"<"&$I13),"") | E13: =IF(C13>0,_xlfn.MINIFS(Annonces!$L$2:$L$701,Annonces!$A$2:$A$701,$A13,Annonces!$E$2:$E$701,"En vente",Annonces!$T$2:$T$701,">="&$H13,Annonces!$T$2:$T$701,"<"&$I13),"") | F13: =IF(C13>0,_xlfn.MAXIFS(Annonces!$L$2:$L$701,Annonces!$A$2:$A$701,$A13,Annonces!$E$2:$E$701,"En vente",Annonces!$T$2:$T$701,">="&$H13,Annonces!$T$2:$T$701,"<"&$I13),"") | G13: =IFERROR(AVERAGEIFS(Annonces!$T$2:$T$701,Annonces!$A$2:$A$701,$A13,Annonces!$E$2:$E$701,"En vente",Annonces!$T$2:$T$701,">="&$H13,Annonces!$T$2:$T$701,"<"&$I13),"") | H13: 200000 | I13: 10000000
A14: Honda S2000 | B14: < 100 000 km | C14: =COUNTIFS(Annonces!$A$2:$A$701,$A14,Annonces!$E$2:$E$701,"En vente",Annonces!$T$2:$T$701,">="&$H14,Annonces!$T$2:$T$701,"<"&$I14) | D14: =IFERROR(AVERAGEIFS(Annonces!$L$2:$L$701,Annonces!$A$2:$A$701,$A14,Annonces!$E$2:$E$701,"En vente",Annonces!$T$2:$T$701,">="&$H14,Annonces!$T$2:$T$701,"<"&$I14),"") | E14: =IF(C14>0,_xlfn.MINIFS(Annonces!$L$2:$L$701,Annonces!$A$2:$A$701,$A14,Annonces!$E$2:$E$701,"En vente",Annonces!$T$2:$T$701,">="&$H14,Annonces!$T$2:$T$701,"<"&$I14),"") | F14: =IF(C14>0,_xlfn.MAXIFS(Annonces!$L$2:$L$701,Annonces!$A$2:$A$701,$A14,Annonces!$E$2:$E$701,"En vente",Annonces!$T$2:$T$701,">="&$H14,Annonces!$T$2:$T$701,"<"&$I14),"") | G14: =IFERROR(AVERAGEIFS(Annonces!$T$2:$T$701,Annonces!$A$2:$A$701,$A14,Annonces!$E$2:$E$701,"En vente",Annonces!$T$2:$T$701,">="&$H14,Annonces!$T$2:$T$701,"<"&$I14),"") | H14: 0 | I14: 100000
... A59: Volkswagen Golf IV GTI 25th Anniversary | B59: 150 000 – 200 000 km | C59: =COUNTIFS(Annonces!$A$2:$A$701,$A59,Annonces!$E$2:$E$701,"En vente",Annonces!$T$2:$T$701,">="&$H59,Annonces!$T$2:$T$701,"<"&$I59) | D59: =IFERROR(AVERAGEIFS(Annonces!$L$2:$L$701,Annonces!$A$2:$A$701,$A59,Annonces!$E$2:$E$701,"En vente",Annonces!$T$2:$T$701,">="&$H59,Annonces!$T$2:$T$701,"<"&$I59),"") | E59: =IF(C59>0,_xlfn.MINIFS(Annonces!$L$2:$L$701,Annonces!$A$2:$A$701,$A59,Annonces!$E$2:$E$701,"En vente",Annonces!$T$2:$T$701,">="&$H59,Annonces!$T$2:$T$701,"<"&$I59),"") | F59: =IF(C59>0,_xlfn.MAXIFS(Annonces!$L$2:$L$701,Annonces!$A$2:$A$701,$A59,Annonces!$E$2:$E$701,"En vente",Annonces!$T$2:$T$701,">="&$H59,Annonces!$T$2:$T$701,"<"&$I59),"") | G59: =IFERROR(AVERAGEIFS(Annonces!$T$2:$T$701,Annonces!$A$2:$A$701,$A59,Annonces!$E$2:$E$701,"En vente",Annonces!$T$2:$T$701,">="&$H59,Annonces!$T$2:$T$701,"<"&$I59),"") | H59: 150000 | I59: 200000

Sheet Bonnes affaires
A1: Véhicule | B1: Titre | C1: Prix | D1: Cote attendue | E1: Décote | F1: Km | G1: Année | H1: Ville | I1: Annonce | J1: Relevé
A2: Citroën Saxo VTS 16V | B2: Saxo vts | C2: 800 | D2: 8090 | E2: =IF(AND(ISNUMBER(C2),ISNUMBER(D2),D2>0),1-C2/D2,"") | F2: 100000 | G2: 2001 | H2: Chasseneuil | I2: Voir | J2: 46310
A3: Honda S2000 | B3: MG MGF/MGTF TF 115 CV fiabilisée RHD + HARDTOP | C3: 4599 | D3: 21890 | E3: =IF(AND(ISNUMBER(C3),ISNUMBER(D3),D3>0),1-C3/D3,"") | F3: 147999 | G3: 2005 | H3: Salouël | I3: Voir | J3: 46310
A4: Citroën Saxo VTS 16V | B4: Saxo vts 1.6 8s | C4: 1600 | D4: 6280 | E4: =IF(AND(ISNUMBER(C4),ISNUMBER(D4),D4>0),1-C4/D4,"") | F4: 281740 | G4: 2003 | H4: Le Robert | I4: Voir | J4: 46310
A5: Mazda MX-5 NA | B5: Mazda Mx5 NA sans CT( à restaurer ou pièce) | C5: 3000 | D5: 10430 | E5: =IF(AND(ISNUMBER(C5),ISNUMBER(D5),D5>0),1-C5/D5,"") | F5: 205344 | G5: 1997 | H5: Les Villages Vovéens | I5: Voir | J5: 46310
A6: Citroën Saxo VTS 16V | B6: Citroën saxo vts | C6: 2500 | D6: 7450 | E6: =IF(AND(ISNUMBER(C6),ISNUMBER(D6),D6>0),1-C6/D6,"") | F6: 150000 | G6: 2000 | H6: Naintré | I6: Voir | J6: 46310
A7: Peugeot 306 S16 | B7: Peugeot 306 1.8 16S XT Pack | C7: 3500 | D7: 9590 | E7: =IF(AND(ISNUMBER(C7),ISNUMBER(D7),D7>0),1-C7/D7,"") | F7: 235000 | G7: 2000 | H7: Nice | I7: Voir | J7: 46310
A8: Peugeot 306 S16 | B8: 306 xsi swap TCT | C8: 3500 | D8: 9420 | E8: =IF(AND(ISNUMBER(C8),ISNUMBER(D8),D8>0),1-C8/D8,"") | F8: 240000 | G8: 1996 | H8: Les Angles | I8: Voir | J8: 46310
A9: Honda S2000 | B9: TOYOTA MR2 1.8 140 VVT-i 2005 - 110 430 km - Réfection complète peinture - sellerie - capote - pneus arrière neufs - | C9: 11990 | D9: 26500 | E9: =IF(AND(ISNUMBER(C9),ISNUMBER(D9),D9>0),1-C9/D9,"") | F9: 110430 | G9: 2005 | H9: Reims | I9: Voir | J9: 46310
A10: Peugeot 306 S16 | B10: 306 | C10: 5200 | D10: 11490 | E10: =IF(AND(ISNUMBER(C10),ISNUMBER(D10),D10>0),1-C10/D10,"") | F10: 179800 | G10: 1997 | H10: Yenne | I10: Voir | J10: 46310
A11: Citroën Saxo VTS 16V | B11: Saxo vts DIESEL | C11: 3000 | D11: 6570 | E11: =IF(AND(ISNUMBER(C11),ISNUMBER(D11),D11>0),1-C11/D11,"") | F11: 220000 | G11: 2002 | H11: Thun-Saint-Amand | I11: Voir | J11: 46310
A12: Alfa Romeo 156 2.5 V6 24V | B12: Alfa 156 2.5 v6 GPL | C12: 3200 | D12: 6960 | E12: =IF(AND(ISNUMBER(C12),ISNUMBER(D12),D12>0),1-C12/D12,"") | F12: 202000 | G12: 1999 | H12: Romans | I12: Voir | J12: 46310
A13: Honda S2000 | B13: Mazda Mx5 ROADSTER 1.8 MZR 125 ELEGANCE | C13: 12990 | D13: 27660 | E13: =IF(AND(ISNUMBER(C13),ISNUMBER(D13),D13>0),1-C13/D13,"") | F13: 101000 | G13: 2006 | H13: Creuzier-le-Vieux | I13: Voir | J13: 46310
... A64: Porsche 911 997 Carrera S | B64: Porsche 911 COUPE (997) CARRERA TIPTRONIC S | C64: 45990 | D64: 54360 | E64: =IF(AND(ISNUMBER(C64),ISNUMBER(D64),D64>0),1-C64/D64,"") | F64: 119000 | G64: 2005 | H64: Bazouges Cré sur Loir | I64: Voir | J64: 46310

Sheet Véhicules
A1: Véhicule | B1: Identifiant | C1: Statut | D1: Catégorie | E1: Recherche | F1: Années | G1: Mots obligatoires | H1: Variantes | I1: Mots exclus | J1: Rareté | K1: Dernier de | L1: Désirabilité | M1: Ajouté le | N1: Notes | O1: LeBonCoin
A2: Peugeot 208 GTi 30th | B2: peugeot-208-gti-30th | C2: Suivi | D2: Hot-hatch récente à tirage limité | E2: 208 gti 30th | F2: 2014-2016 | H2: 30th, 30 th, trentieme | J2: 85 | K2: 65 | L2: 80 | M2: 46273 | N2: Édition limitée et numérotée (1.6 THP 208 ch). | O2: Voir
A3: Porsche 911 997 Carrera S | B3: porsche-911-997 | C3: Suivi | D3: Sportive iconique | E3: 911 997 carrera s | F3: 2004-2012 | G3: 997 | I3: turbo, gt3, gt2 | J3: 40 | K3: 90 | L3: 90 | M3: 46273 | N3: Dernière 911 à direction assistée hydraulique. Recherche centrée sur la Carrera S : retirer « s » du texte de recherche pour inclure la Carrera de base. | O3: Voir
A4: Porsche Boxster 986 | B4: porsche-boxster-986 | C4: Suivi | D4: Roadster d'entrée de gamme Porsche | E4: boxster 986 | F4: 1996-2004 | G4: boxster | J4: 35 | K4: 30 | L4: 70 | M4: 46273 | N4: Première génération (1996-2004). Point de vigilance IMS à l'achat. | O4: Voir
A5: Porsche Boxster 987 | B5: porsche-boxster-987 | C5: Suivi | D5: Roadster Porsche | E5: boxster 987 | F5: 2005-2012 | G5: boxster | I5: spyder | J5: 30 | K5: 40 | L5: 75 | M5: 46273 | N5: Deuxième génération (2005-2012), fiabilité nettement améliorée. Spyder exclu (marché à part). | O5: Voir
A6: Renault Twingo 1 découvrable | B6: renault-twingo-1 | C6: Suivi | D6: Citadine iconique, variante toit ouvrant | E6: twingo toit ouvrant | F6: 1993-2007 | H6: toit ouvrant, decouvrable, toit toile, toit souple | I6: twingo 2, twingo ii, twingo 3, twingo iii | J6: 55 | K6: 50 | L6: 65 | M6: 46273 | N6: La Twingo 1 n'a jamais eu de cabriolet officiel : la variante suivie est le toit ouvrant en toile. | O6: Voir
A7: Peugeot 206 RC | B7: peugeot-206-rc | C7: Suivi | D7: Hot-hatch youngtimer 2000-2005 | E7: 206 rc | F7: 2003-2007 | G7: rc | I7: hdi, 206+, 206 cc, rc line, rcline, 1.4, 1.6, 110 cv, 110ch | J7: 45 | K7: 75 | L7: 70 | M7: 46273 | N7: 2.0 16v 177 ch. Nommée GTi 180 à l'export. | O7: Voir
A8: Renault Clio II RS (172/182 ch) | B8: renault-clio-2-rs | C8: Suivi | D8: Hot-hatch youngtimer 2000-2005 | E8: clio rs | F8: 2000-2006 | H8: 172, 182, rs | I8: v6, dci, clio 3, clio iii, clio 4, clio iv, gt line | J8: 40 | K8: 60 | L8: 75 | M8: 46273 | N8: Châssis Renault Sport très réputé, succède à la Williams déjà collector. | O8: Voir
A9: Citroën Saxo VTS 16V | B9: citroen-saxo-vts | C9: Suivi | D9: Hot-hatch youngtimer 2000-2005 | E9: saxo vts | F9: 1997-2004 | G9: vts | I9: rallye, piste, course, preparee, kit car | J9: 30 | K9: 55 | L9: 55 | M9: 46273 | N9: Marché parasité par les exemplaires modifiés/rallye, exclus par filtre : on suit les originaux. | O9: Voir
A10: Peugeot 306 S16 | B10: peugeot-306-s16 | C10: Suivi | D10: Hot-hatch youngtimer 1990-2000 | E10: 306 s16 | F10: 1993-2001 | G10: s16 | I10: hdi, cabriolet | J10: 40 | K10: 50 | L10: 65 | M10: 46296 | N10: 2.0 16v 150-167 ch, châssis encensé à l’époque. Beaucoup d’exemplaires fatigués : l’état d’origine fait la valeur. | O10: Voir
A11: BMW Z3 1.9i / 2.0i | B11: bmw-z3-19-20 | C11: Suivi | D11: Roadster youngtimer | E11: bmw z3 | F11: 1996-2002 | I11: m roadster, m coupe, coupe, 3.0, 2.8, 3.0i, 2.8i | J11: 35 | K11: 40 | L11: 65 | M11: 46296 | N11: Roadster BMW le plus abordable (1.8 à 2.2). M Roadster, coupé et 6 cylindres 2.8/3.0 exclus (marchés à part). | O11: Voir
A12: Volkswagen Golf IV GTI 25th Anniversary | B12: vw-golf-4-gti-25 | C12: Suivi | D12: Hot-hatch à série limitée | E12: golf gti 25 | F12: 2001-2002 | G12: gti | H12: 25, 25th, anniversary, anniversaire, edition 25 | I12: tdi, golf 5, golf v, golf 6, golf vi | J12: 70 | K12: 55 | L12: 65 | M12: 46296 | N12: 1.8T 180 ch, sièges Recaro, jantes BBS. Série limitée : vérifier la plaque et les équipements spécifiques. | O12: Voir
A13: Alfa Romeo 156 2.5 V6 24V | B13: alfa-156-v6 | C13: Suivi | D13: Berline sportive youngtimer | E13: alfa 156 v6 | F13: 1997-2005 | G13: v6 | I13: gta, jtd, diesel | J13: 50 | K13: 70 | L13: 65 | M13: 46296 | N13: V6 « Busso » atmosphérique. GTA exclue (marché à part). Courroie de distribution et variateur à surveiller. | O13: Voir
A14: Mazda MX-5 NA | B14: mazda-mx5-na | C14: Suivi | D14: Roadster youngtimer | E14: mazda mx5 | F14: 1989-1998 | I14: nb, nc, nd, hard top seul | J14: 25 | K14: 60 | L14: 75 | M14: 46296 | N14: Première génération, phares escamotables. Offre abondante : la corrosion des bas de caisse fait la différence. | O14: Voir
A15: Peugeot 205 GTI | B15: peugeot-205-gti | C15: Suivi | D15: Hot-hatch icône des années 80 | E15: 205 gti | F15: 1984-1994 | G15: gti | I15: look, replica, replique, gtx, xs, cti | J15: 45 | K15: 50 | L15: 85 | M15: 46296 | N15: 1.6 et 1.9. Cote déjà élevée et soutenue ; nombreuses « répliques » à partir de 205 XS/GT, exclues par filtre mais à vérifier (numéro de série). | O15: Voir
A16: Honda S2000 | B16: honda-s2000 | C16: Suivi | D16: Roadster japonais culte | E16: honda s2000 | F16: 1999-2009 | J16: 50 | K16: 85 | L16: 85 | M16: 46296 | N16: 2.0 VTEC atmosphérique à 9 000 tr/min, sans successeur. Exemplaires d’origine non modifiés de plus en plus recherchés. | O16: Voir
A17: Renault Mégane II RS R26 | B17: renault-megane-r26 | C17: Suivi | D17: Hot-hatch à série limitée | E17: megane rs r26 | F17: 2007-2009 | H17: r26, r 26 | I17: dci, gt line, megane 3, megane iii | J17: 55 | K17: 50 | L17: 75 | M17: 46296 | N17: Série R26 (différentiel autobloquant). La R26.R, beaucoup plus rare, sort du même filtre : à repérer à part. | O17: Voir
